Workbook

Sheet Paysheet
J1: tax ratio | Q1: =D2 -> 26.6951 | S1: =Q1 -> 26.6951 | AA1: Refer to leave section | AG1: Rate | AH1: =Q1 -> 26.6951 | AP1: Rate | AQ1: =AH1 -> 26.6951 | BG1: Garnish Believe Mhererwa
C2: Exchange rate | D2: 26.6951 | J2: USD/ZWL | P2: Basic | R2: Allowances | AC2: CILL | AD2: Bonus | AE2: USD/ZIG | AF2: Gross | AI2: Allowable Deductions | AO2: Taxable Income | AQ2: Total Taxable in | AR2: PAYE in | AS2: Tax Credits | AT2: Net PAYE | AU2: PAYE USD | AW2: PAYE ZIG | AY2: Salary After Tax | BA2: Other Deductions | BJ2: Advances | BL2: Net Salary | BO2: Tax Table USD | BU2: ZWL | BX2: USD | CA2: Leave Days | CH2: Rate | CI2: =AQ1 -> 26.6951
A3: Works # | B3: Netsai | C3: Nhemachena | D3: National 78-171262Y32 | E3: Pay Date | F3: Station | G3: Occupation | H3: Grade | I3: NSSA Number | J3: RATIO | K3: Period | L3: Hours | M3: Rate/hr | N3: UG Shifts | O3: NS Hours | P3: USD | Q3: ZWL | R3: USD | S3: COLA | T3: Underground | U3: Night Shift | V3: Project/Acting | W3: Overtime @2 | X3: Overtime @1.5 | Y3: Hours @2 | Z3: Hours @1.5 | AA3: Days sold | AB3: Gratuity | AC3: USD | AD3: USD | AE3: Ratio | AF3: Total | AG3: usd | AH3: ZWL | AI3: NSSA | AJ3: NSSA USD | AK3: NSSA ZIG | AL3: MIPF | AM3: NEC | AN3: Non Taxable Bonus | AO3: USD | AP3: ZIG | AQ3: USD | AR3: USD | AS3: USD | AT3: USD | AU3: PAYE | AV3: AIDS LEVY | AW3: PAYE | AX3: AIDS LEVY | AY3: USD | AZ3: ZWL | BA3: Nyaradzo | BB3: CBZ Life | BC3: Maint ZIG | BD3: Maint USD | BE3: Funeral Assist ZIG | BF3: Loan Repayment ZIG | BG3: Loan Repayment USD | BH3: Funeral USD | BI3: May Day (USD) | BJ3: USD | BK3: ZIG | BL3: USD | BM3: ZIG | BN3: 0-100 | BO3: 100.01-300 | BP3: 300.01-1000 | BQ3: 1000.01-2000 | BR3: 2000.01-3000 | BS3: 3000 and Above | BT3: Total | BU3: Bank | BV3: Branch | BW3: Account Number | BX3: Bank | BY3: Branch | BZ3: Account Number | CA3: Opening | CB3: Acrued | CC3: Taken | CD3: CILL | CE3: Closing | CF3: Daily Rate | CG3: Value of days | CH3: USD | CI3: ZIG
A4: AES-E046 | B4: Tarisai | C4: Zinyama | D4: 53-225710V33 | E4: 45747 | F4: Mimosa | G4: Site Manager | H4: J | I4: 9683481Q | J4: =AO4/AQ4 -> 0.46965834 | K4: 3/2025 | L4: 208 | M4: 6.49 | P4: =L4*M4 -> 1349.92 | Q4: =P4*$Q$1 -> 36036.249 | R4: =1700 -> 1700 | S4: =P4*0.3*$S$1*0.5 -> 5405.4374 | U4: =O4*M4*0.1 -> 0 | W4: =Y4*M4*2 -> 0 | X4: =Z4*M4*1.5 -> 0 | AA4: =CD4 -> 0 | AB4: =P4*0.075 -> 101.244 | AC4: =M4*8*AA4 -> 0 | AE4: =AO4/AQ4 -> 0.46965834 | AF4: =P4+R4+T4+U4+V4+W4+X4+AB4+AC4+AD4 -> 3151.164 | AG4: =AF4*0.5 -> 1575.582 | AH4: =((AF4-AG4)*AH1)+S4 -> 47465.756 | AI4: =IF(Q4>18519.27,0.045*18519.27,Q4*0.045) -> 833.36715 | AJ4: =(AI4*0.5)/$AQ$1 -> 15.608991 | AK4: =(AI4*0.4) -> 333.34686 | AL4: 0 | AM4: =(Q4*0.003) -> 108.10875 | AN4: =IF(AD4>320,320,AD4) -> 0 | AO4: =AG4-AN4-AJ4 -> 1559.973 | AP4: =AH4-AK4-AL4-AM4-BB4 -> 47024.301 | AQ4: =AO4+(AP4/$AQ$1) -> 3321.5061 | AR4: =BT4 -> 993.60242 | AS4: 75 | AT4: =AR4-AS4 -> 918.60242 | AU4: =AT4*AE4 -> 431.42929 | AV4: =AU4*0.03 -> 12.942879 | AW4: =(AT4-AU4)*$AQ$1 -> 13005.136 | AX4: =AW4*0.03 -> 390.15407 | AY4: =AO4-AU4-AV4 -> 1115.6008 | AZ4: =AP4-AW4-AX4 -> 33629.011 | BA4: ='Nyaradzo Workings'!K8 -> 1177.3392 | BE4: 0 | BI4: 12.5 | BL4: =AY4-BI4-BG4-BH4-BD4+BJ4 -> 1103.1008 | BM4: =AZ4-BA4-BC4-BE4-BF4+BK4 -> 32451.672 | BN4: =IF(AQ4<100,0,0) -> 0 | BO4: =IF(AQ4<100,"",IF(AQ4<=300,AQ4*0.2-20,)) -> 0 | BP4: =IF(AQ4<300.01,"",IF(AQ4<=1000,AQ4*0.25-35,)) -> 0 | BQ4: =IF(AQ4<1000.01,"",IF(AQ4<=2000,AQ4*0.3-85,)) -> 0 | BR4: =IF(AQ4<2000.01,"",IF(AQ4<=3000,AQ4*0.35-185,)) -> 0 | BS4: =IF(AQ4<3000.01,"",IF(AQ4>3000,AQ4*0.4-335,)) -> 993.60242 | BT4: =SUM(BN4:BS4) -> 993.60242 | BU4: FBC | BV4: Zvishavane | BW4: 8374810963284 | BX4: FBC | BY4: Zvishavane | BZ4: 4591712639586 | CA4: 20.75 | CB4: 2.5 | CC4: 1 | CE4: =CA4+CB4-CC4-CD4 -> 22.25 | CF4: =M4*8 -> 51.92 | CG4: =CE4*CF4 -> 1155.22 | CH4: =CG4*0.4 -> 462.088 | CI4: =(CG4-CH4)*$CI$2 -> 18503.228
A5: AES-E049 | B5: Marvellous | C5: Chakanetsa | D5: 42-350280J52 | E5: =E4 -> 45747 | F5: Mimosa | G5: SHE Officer | H5: 4/11 | I5: 8930103H | J5: =AO5/AQ5 -> 0.37661718 | K5: =K4 -> 3/2025 | L5: 208 | M5: 3.85 | N5: 11 | P5: =L5*M5 -> 800.8 | Q5: =P5*$Q$1 -> 21377.436 | R5: 438 | S5: =P5*0.3*$S$1*0.5 -> 3206.6154 | T5: =N5*M5*8*0.05 -> 16.94 | U5: =O5*M5*0.1 -> 0 | W5: =Y5*M5*2 -> 0 | X5: =Z5*M5*1.5 -> 0 | AA5: =CD5 -> 0 | AB5: =P5*0.075 -> 60.06 | AC5: =M5*8*AA5 -> 0 | AE5: =AO5/AQ5 -> 0.37661718 | AF5: =P5+R5+T5+U5+V5+W5+X5+AB5+AC5+AD5 -> 1315.8 | AG5: =AF5*0.5 -> 657.9 | AH5: =(AF5-AG5)*AH1+(300*AH1)+S5 -> 28777.852 | AI5: =IF(Q5>18519.27,0.045*18519.27,Q5*0.045) -> 833.36715 | AJ5: =(AI5*0.5)/$AQ$1 -> 15.608991 | AK5: =(AI5*0.4) -> 333.34686 | AL5: 0 | AM5: =(Q5*0.003) -> 64.132308 | AN5: =IF(AD5>320,320,AD5) -> 0 | AO5: =AG5-AN5-AJ5 -> 642.29101 | AP5: =AH5-AK5-AL5-AM5-BB5 -> 28380.373 | AQ5: =AO5+(AP5/$AQ$1) -> 1705.4214 | AR5: =BT5 -> 426.62642 | AS5: 0 | AT5: =AR5-AS5 -> 426.62642 | AU5: =AT5*AE5 -> 160.67484 | AV5: =AU5*0.03 -> 4.8202453 | AW5: =(AT5-AU5)*$AQ$1 -> 7099.6041 | AX5: =AW5*0.03 -> 212.98812 | AY5: =AO5-AU5-AV5 -> 476.79592 | AZ5: =AP5-AW5-AX5 -> 21067.78 | BA5: ='Nyaradzo Workings'!K9 -> 711.2292 | BE5: 0 | BI5: 12.5 | BL5: =AY5-BI5-BG5-BH5-BD5+BJ5 -> 464.29592 | BM5: =AZ5-BA5-BC5-BE5-BF5+BK5 -> 20356.551 | BN5: =IF(AQ5<100,0,0) -> 0 | BO5: =IF(AQ5<100,"",IF(AQ5<=300,AQ5*0.2-20,)) -> 0 | BP5: =IF(AQ5<300.01,"",IF(AQ5<=1000,AQ5*0.25-35,)) -> 0 | BQ5: =IF(AQ5<1000.01,"",IF(AQ5<=2000,AQ5*0.3-85,)) -> 426.62642 | BR5: =IF(AQ5<2000.01,"",IF(AQ5<=3000,AQ5*0.35-185,)) | BS5: =IF(AQ5<3000.01,"",IF(AQ5>3000,AQ5*0.4-335,)) | BT5: =SUM(BN5:BS5) -> 426.62642 | BU5: FBC | BV5: Zvishavane | BW5: 6276992244264 | BX5: FBC | BY5: Zvishavane | BZ5: 6563946412917 | CA5: 27.96 | CB5: 2.5 | CE5: =CA5+CB5-CC5-CD5 -> 30.46 | CF5: =M5*8 -> 30.8 | CG5: =CE5*CF5 -> 938.168 | CH5: =CG5*0.4 -> 375.2672 | CI5: =(CG5-CH5)*$CI$2 -> 15026.693
A6: AES-E022 | B6: Obvious | C6: Mpofu | D6: 11-109767Q74 | E6: =E5 -> 45747 | F6: Mimosa | G6: Overseer Miner | H6: 4/11 | I6: 9143903G | J6: =AO6/AQ6 -> 0.46517559 | K6: =K5 -> 3/2025 | L6: 208 | M6: 3.85 | N6: 25 | P6: =L6*M6 -> 800.8 | Q6: =P6*$Q$1 -> 21377.436 | R6: 438 | S6: =P6*0.3*$S$1*0.5 -> 3206.6154 | T6: =N6*M6*8*0.05 -> 38.5 | U6: =O6*M6*0.1 -> 0 | W6: =Y6*M6*2 -> 0 | X6: =Z6*M6*1.5 -> 0 | AA6: =CD6 -> 10 | AB6: 60.06 | AC6: =M6*8*AA6 -> 308 | AE6: =AO6/AQ6 -> 0.46517559 | AF6: =P6+R6+T6+U6+V6+W6+X6+AB6+AC6+AD6 -> 1645.36 | AG6: =AF6*0.5 -> 822.68 | AH6: =(AF6-AG6)*AH1+S6 -> 25168.14 | AI6: =IF(Q6>18519.27,0.045*18519.27,Q6*0.045) -> 833.36715 | AJ6: =(AI6*0.5)/$AQ$1 -> 15.608991 | AK6: =(AI6*0.4) -> 333.34686 | AL6: 0 | AM6: =Q6*0.003 -> 64.132308 | AN6: =IF(AD6>320,320,AD6) -> 0 | AO6: =AG6-AN6-AJ6 -> 807.07101 | AP6: =AH6-AK6-AL6-AM6-BB6 -> 24770.661 | AQ6: =AO6+(AP6/$AQ$1) -> 1734.9814 | AR6: =BT6 -> 435.49442 | AS6: 0 | AT6: =AR6-AS6 -> 435.49442 | AU6: =AT6*AE6 -> 202.58138 | AV6: =AU6*0.03 -> 6.0774413 | AW6: =(AT6-AU6)*$AQ$1 -> 6217.6371 | AX6: =AW6*0.03 -> 186.52911 | AY6: =AO6-AU6-AV6 -> 598.41219 | AZ6: =AP6-AW6-AX6 -> 18366.495 | BA6: ='Nyaradzo Workings'!K10 -> 1260.2092 | BE6: 0 | BI6: 12.5 | BL6: =AY6-BI6-BG6-BH6-BD6+BJ6 -> 585.91219 | BM6: =AZ6-BA6-BC6-BE6-BF6+BK6 -> 17106.286 | BN6: =IF(AQ6<100,0,0) -> 0 | BO6: =IF(AQ6<100,"",IF(AQ6<=300,AQ6*0.2-20,)) -> 0 | BP6: =IF(AQ6<300.01,"",IF(AQ6<=1000,AQ6*0.25-35,)) -> 0 | BQ6: =IF(AQ6<1000.01,"",IF(AQ6<=2000,AQ6*0.3-85,)) -> 435.49442 | BR6: =IF(AQ6<2000.01,"",IF(AQ6<=3000,AQ6*0.35-185,)) | BS6: =IF(AQ6<3000.01,"",IF(AQ6>3000,AQ6*0.4-335,)) | BT6: =SUM(BN6:BS6) -> 435.49442 | BU6: FBC | BV6: VIRTUAL | BW6: 2760919825741 | BX6: FBC | BY6: VIRTUAL | BZ6: 9900087728107 | CA6: 19.35 | CB6: 2.5 | CD6: 10 | CE6: =CA6+CB6-CC6-CD6 -> 11.85 | CF6: =M6*8 -> 30.8 | CG6: =CE6*CF6 -> 364.98 | CH6: =CG6*0.4 -> 145.992 | CI6: =(CG6-CH6)*$CI$2 -> 5845.9066
A7: AES-E035 | B7: Polite | C7: Mudarikwa | D7: 35-238890M10 | E7: =E6 -> 45747 | F7: Mimosa | G7: Admin Clerk | H7: 4/6 | I7: 2130789B | J7: =AO7/AQ7 -> 0.44557586 | K7: =K6 -> 3/2025 | L7: 208 | M7: 3.6 | P7: =L7*M7 -> 748.8 | Q7: =P7*$Q$1 -> 19989.291 | R7: 153 | S7: =P7*0.3*$S$1*0.5 -> 2998.3936 | T7: =N7*M7*8*0.05 -> 0 | U7: =O7*M7*0.1 -> 0 | W7: =Y7*M7*2 -> 0 | X7: =Z7*M7*1.5 -> 0 | AA7: =CD7 -> 0 | AB7: 56.16 | AC7: =M7*8*AA7 -> 0 | AE7: =AO7/AQ7 -> 0.44557586 | AF7: =P7+R7+T7+U7+V7+W7+X7+AB7+AC7+AD7 -> 957.96 | AG7: =AF7*0.5 -> 478.98 | AH7: =(AF7-AG7)*AH1+S7 -> 15784.813 | AI7: =IF(Q7>18519.27,0.045*18519.27,Q7*0.045) -> 833.36715 | AJ7: =(AI7*0.5)/$AQ$1 -> 15.608991 | AK7: =(AI7*0.4) -> 333.34686 | AL7: 0 | AM7: =(Q7*0.003) -> 59.967873 | AN7: =IF(AD7>320,320,AD7) -> 0 | AO7: =AG7-AN7-AJ7 -> 463.37101 | AP7: =AH7-AK7-AL7-AM7-BB7 -> 15391.498 | AQ7: =AO7+(AP7/$AQ$1) -> 1039.9374 | AR7: =BT7 -> 226.98122 | AS7: 0 | AT7: =AR7-AS7 -> 226.98122 | AU7: =AT7*AE7 -> 101.13735 | AV7: =AU7*0.03 -> 3.0341206 | AW7: =(AT7-AU7)*$AQ$1 -> 3359.4147 | AX7: =AW7*0.03 -> 100.78244 | AY7: =AO7-AU7-AV7 -> 359.19953 | AZ7: =AP7-AW7-AX7 -> 11931.301 | BA7: ='Nyaradzo Workings'!K11 -> 1196.4492 | BE7: 0 | BI7: 12.5 | BL7: =AY7-BI7-BG7-BH7-BD7+BJ7 -> 346.69953 | BM7: =AZ7-BA7-BC7-BE7-BF7+BK7 -> 10734.852 | BN7: =IF(AQ7<100,0,0) -> 0 | BO7: =IF(AQ7<100,"",IF(AQ7<=300,AQ7*0.2-20,)) -> 0 | BP7: =IF(AQ7<300.01,"",IF(AQ7<=1000,AQ7*0.25-35,)) -> 0 | BQ7: =IF(AQ7<1000.01,"",IF(AQ7<=2000,AQ7*0.3-85,)) -> 226.98122 | BR7: =IF(AQ7<2000.01,"",IF(AQ7<=3000,AQ7*0.35-185,)) | BS7: =IF(AQ7<3000.01,"",IF(AQ7>3000,AQ7*0.4-335,)) | BT7: =SUM(BN7:BS7) -> 226.98122 | BU7: FBC | BV7: Zvishavane | BW7: 5298743732931 | BX7: FBC | BY7: Zvishavane | BZ7: 6013813941202 | CA7: 7.56 | CB7: 2.5 | CE7: =CA7+CB7-CC7-CD7 -> 10.06 | CF7: =M7*8 -> 28.8 | CG7: =CE7*CF7 -> 289.728 | CH7: =CG7*0.4 -> 115.8912 | CI7: =(CG7-CH7)*$CI$2 -> 4640.5908
A8: AES-E041 | B8: Chenai | C8: Runesu | D8: 22-559469T40 | E8: =E7 -> 45747 | F8: Head Office | G8: Bus Dev Officer | H8: 4/11 | I8: 7754864L | J8: =AO8/AQ8 -> 0.42908737 | K8: =K7 -> 3/2025 | L8: 208 | M8: 4.76 | P8: =L8*M8 -> 990.08 | Q8: =P8*$Q$1 -> 26430.285 | R8: 290 | S8: =P8*0.3*$S$1*0.5 -> 3964.5427 | T8: =N8*M8*8*0.05 -> 0 | U8: =O8*M8*0.1 -> 0 | W8: =Y8*M8*2 -> 0 | X8: =Z8*M8*1.5 -> 0 | AA8: =CD8 -> 0 | AB8: =P8*0.075 -> 74.256 | AC8: =M8*8*AA8 -> 0 | AE8: =AO8/AQ8 -> 0.42908737 | AF8: =P8+R8+T8+U8+V8+W8+X8+AB8+AC8+AD8 -> 1354.336 | AG8: =AF8*0.5 -> 677.168 | AH8: =(AF8-AG8)*AH1+(70*AH1)+S8 -> 23910.267 | AI8: =IF(Q8>18519.27,0.045*18519.27,Q8*0.045) -> 833.36715 | AJ8: =(AI8*0.5)/$AQ$1 -> 15.608991 | AK8: =(AI8*0.4) -> 333.34686 | AL8: 0 | AM8: =Q8*0.003 -> 79.290854 | AN8: =IF(AD8>320,320,AD8) -> 0 | AO8: =AG8-AN8-AJ8 -> 661.55901 | AP8: =AH8-AK8-AL8-AM8-BB8 -> 23497.629 | AQ8: =AO8+(AP8/$AQ$1) -> 1541.7816 | AR8: =BT8 -> 377.53447 | AS8: 0 | AT8: =AR8-AS8 -> 377.53447 | AU8: =AT8*AE8 -> 161.99528 | AV8: =AU8*0.03 -> 4.8598583 | AW8: =(AT8-AU8)*$AQ$1 -> 5753.8404 | AX8: =AW8*0.03 -> 172.61521 | AY8: =AO8-AU8-AV8 -> 494.70387 | AZ8: =AP8-AW8-AX8 -> 17571.174 | BA8: ='Nyaradzo Workings'!K12 -> 959.5492 | BE8: 0 | BL8: =AY8-BI8-BG8-BH8-BD8+BJ8 -> 494.70387 | BM8: =AZ8-BA8-BC8-BE8-BF8+BK8 -> 16611.625 | BN8: =IF(AQ8<100,0,0) -> 0 | BO8: =IF(AQ8<100,"",IF(AQ8<=300,AQ8*0.2-20,)) -> 0 | BP8: =IF(AQ8<300.01,"",IF(AQ8<=1000,AQ8*0.25-35,)) -> 0 | BQ8: =IF(AQ8<1000.01,"",IF(AQ8<=2000,AQ8*0.3-85,)) -> 377.53447 | BR8: =IF(AQ8<2000.01,"",IF(AQ8<=3000,AQ8*0.35-185,)) | BS8: =IF(AQ8<3000.01,"",IF(AQ8>3000,AQ8*0.4-335,)) | BT8: =SUM(BN8:BS8) -> 377.53447 | BU8: FBC | BV8: Zvishavane | BW8: 2823915366343 | BX8: FBC | BY8: Zvishavane | BZ8: 5652026357519 | CA8: 82.86 | CB8: 2.5 | CE8: =CA8+CB8-CC8-CD8 -> 85.36 | CF8: =M8*8 -> 38.08 | CG8: =CE8*CF8 -> 3250.5088 | CH8: =CG8*0.4 -> 1300.2035 | CI8: =(CG8-CH8)*$CI$2 -> 52063.594
A9: AES-E033 | B9: Tafadzwa | C9: Mafukidze | D9: 16-212235T21 | E9: =E8 -> 45747 | F9: Mimosa | G9: Team Leader | H9: 4/7 | I9: 6229731N | J9: =AO9/AQ9 -> 0.46928971 | K9: =K8 -> 3/2025 | L9: 208 | M9: 2.8 | N9: 22 | P9: =L9*M9 -> 582.4 | Q9: =P9*$Q$1 -> 15547.226 | R9: 100 | S9: =P9*0.3*$S$1*0.5 -> 2332.0839 | T9: =N9*M9*8*0.05 -> 24.64 | U9: =O9*M9*0.1 -> 0 | W9: =Y9*M9*2 -> 0 | X9: =Z9*M9*1.5 -> 0 | AA9: =CD9 -> 0 | AC9: =M9*8*AA9 -> 0 | AE9: =AO9/AQ9 -> 0.46928971 | AF9: =P9+R9+T9+U9+V9+W9+X9+AB9+AC9+AD9 -> 707.04 | AG9: =AF9*0.5 -> 353.52 | AH9: =(AF9-AG9)*AH1+S9 -> 11769.336 | AI9: =IF(Q9>18519.27,0.045*18519.27,Q9*0.045) -> 699.62518 | AJ9: =(AI9*0.5)/$AQ$1 -> 13.104 | AK9: =(AI9*0.4) -> 279.85007 | AL9: =Q9*0.075 -> 1166.042 | AM9: =Q9*0.003 -> 46.641679 | AN9: =IF(AD9>320,320,AD9) -> 0 | AO9: =AG9-AN9-AJ9 -> 340.416 | AP9: =AH9-AK9-AL9-AM9-BB9 -> 10276.802 | AQ9: =AO9+(AP9/$AQ$1) -> 725.3856 | AR9: =BT9 -> 146.3464 | AS9: 0 | AT9: =AR9-AS9 -> 146.3464 | AU9: =AT9*AE9 -> 68.67886 | AV9: =AU9*0.03 -> 2.0603658 | AW9: =(AT9-AU9)*$AQ$1 -> 2073.3427 | AX9: =AW9*0.03 -> 62.200282 | AY9: =AO9-AU9-AV9 -> 269.67677 | AZ9: =AP9-AW9-AX9 -> 8141.2589 | BA9: ='Nyaradzo Workings'!K13 -> 698.9992 | BB9: 0 | BE9: 0 | BI9: 12.5 | BL9: =AY9-BI9-BG9-BH9-BD9+BJ9 -> 257.17677 | BM9: =AZ9-BA9-BC9-BE9-BF9+BK9 -> 7442.2597 | BN9: =IF(AQ9<100,0,0) -> 0 | BO9: =IF(AQ9<100,"",IF(AQ9<=300,AQ9*0.2-20,)) -> 0 | BP9: =IF(AQ9<300.01,"",IF(AQ9<=1000,AQ9*0.25-35,)) -> 146.3464 | BQ9: =IF(AQ9<1000.01,"",IF(AQ9<=2000,AQ9*0.3-85,)) | BR9: =IF(AQ9<2000.01,"",IF(AQ9<=3000,AQ9*0.35-185,)) | BS9: =IF(AQ9<3000.01,"",IF(AQ9>3000,AQ9*0.4-335,)) | BT9: =SUM(BN9:BS9) -> 146.3464 | BU9: FBC | BV9: Zvishavane | BW9: 5957561986265 | BX9: FBC | BY9: Zvishavane | BZ9: 4704859533483 | CA9: 16 | CB9: 2.5 | CE9: =CA9+CB9-CC9-CD9 -> 18.5 | CF9: =M9*8 -> 22.4 | CG9: =CE9*CF9 -> 414.4 | CH9: =CG9*0.4 -> 165.76 | CI9: =(CG9-CH9)*$CI$2 -> 6637.4697
A10: AES-E034 | B10: Kudzai | C10: Gwatidzo | D10: 45-313487Y35 | E10: =E9 -> 45747 | F10: Mimosa | G10: Team Leader | H10: 4/7 | I10: 1987737H | J10: =AO10/AQ10 -> 0.47690915 | K10: =K9 -> 3/2025 | L10: 208 | M10: 2.8 | N10: 25 | P10: =L10*M10 -> 582.4 | Q10: =P10*$Q$1 -> 15547.226 | S10: =P10*0.3*$S$1*0.5 -> 2332.0839 | T10: =N10*M10*8*0.05 -> 28 | U10: =O10*M10*0.1 -> 0 | W10: =Y10*M10*2 -> 0 | X10: =Z10*M10*1.5 -> 0 | AA10: =CD10 -> 15 | AC10: =M10*8*AA10 -> 336 | AE10: =AO10/AQ10 -> 0.47690915 | AF10: =P10+R10+T10+U10+V10+W10+X10+AB10+AC10+AD10 -> 946.4 | AG10: =AF10*0.5 -> 473.2 | AH10: =(AF10-AG10)*$AH$1+S10 -> 14964.205 | AI10: =IF(Q10>18519.27,0.045*18519.27,Q10*0.045) -> 699.62518 | AJ10: =(AI10*0.5)/$AQ$1 -> 13.104 | AK10: =(AI10*0.4) -> 279.85007 | AL10: =Q10*0.075 -> 1166.042 | AM10: =Q10*0.003 -> 46.641679 | AN10: =IF(AD10>320,320,AD10) -> 0 | AO10: =AG10-AN10-AJ10 -> 460.096 | AP10: =AH10-AK10-AL10-AM10-BB10 -> 13471.672 | AQ10: =AO10+(AP10/$AQ$1) -> 964.7456 | AR10: =BT10 -> 206.1864 | AS10: 0 | AT10: =AR10-AS10 -> 206.1864 | AU10: =AT10*AE10 -> 98.33218 | AV10: =AU10*0.03 -> 2.9499654 | AW10: =(AT10-AU10)*$AQ$1 -> 2879.1792 | AX10: =AW10*0.03 -> 86.375376 | AY10: =AO10-AU10-AV10 -> 358.81385 | AZ10: =AP10-AW10-AX10 -> 10506.117 | BA10: ='Nyaradzo Workings'!K14 -> 901.0247 | BB10: 0 | BE10: 0 | BL10: =AY10-BI10-BG10-BH10-BD10+BJ10 -> 358.81385 | BM10: =AZ10-BA10-BC10-BE10-BF10+BK10 -> 9605.0923 | BN10: =IF(AQ10<100,0,0) -> 0 | BO10: =IF(AQ10<100,"",IF(AQ10<=300,AQ10*0.2-20,)) -> 0 | BP10: =IF(AQ10<300.01,"",IF(AQ10<=1000,AQ10*0.25-35,)) -> 206.1864 | BQ10: =IF(AQ10<1000.01,"",IF(AQ10<=2000,AQ10*0.3-85,)) | BR10: =IF(AQ10<2000.01,"",IF(AQ10<=3000,AQ10*0.35-185,)) | BS10: =IF(AQ10<3000.01,"",IF(AQ10>3000,AQ10*0.4-335,)) | BT10: =SUM(BN10:BS10) -> 206.1864 | BU10: FBC | BV10: Zvishavane | BW10: 9596400274673 | BX10: FBC | BY10: Zvishavane | BZ10: 2623715817487 | CA10: 18.03 | CB10: 2.5 | CD10: 15 | CE10: =CA10+CB10-CC10-CD10 -> 5.53 | CF10: =M10*8 -> 22.4 | CG10: =CE10*CF10 -> 123.872 | CH10: =CG10*0.4 -> 49.5488 | CI10: =(CG10-CH10)*$CI$2 -> 1984.0653
A11: AES-E036 | B11: Dadirai | C11: Nyakudya | D11: 56-969634J07 | E11: =E10 -> 45747 | F11: Mimosa | G11: Service Assitant | H11: 4/3 | I11: 5672073Y | J11: =AO11/AQ11 -> 0.46456945 | K11: =K10 -> 3/2025 | L11: 208 | M11: 1.62 | N11: 25 | P11: =L11*M11 -> 336.96 | Q11: =P11*$Q$1 -> 8995.1809 | S11: =P11*0.3*$S$1*0.5 -> 1349.2771 | T11: =N11*M11*8*0.05 -> 16.2 | U11: =O11*M11*0.1 -> 0 | W11: =Y11*M11*2 -> 0 | X11: =Z11*M11*1.5 -> 0 | AA11: =CD11 -> 0 | AC11: =M11*8*AA11 -> 0 | AE11: =AO11/AQ11 -> 0.46456945 | AF11: =P11+R11+T11+U11+V11+W11+X11+AB11+AC11+AD11 -> 353.16 | AG11: =AF11*0.5 -> 176.58 | AH11: =(AF11-AG11)*$AH$1+S11 -> 6063.0979 | AI11: =IF(Q11>18519.27,0.045*18519.27,Q11*0.045) -> 404.78314 | AJ11: =(AI11*0.5)/$AQ$1 -> 7.5816 | AK11: =(AI11*0.4) -> 161.91326 | AL11: =Q11*0.075 -> 674.63857 | AM11: =Q11*0.003 -> 26.985543 | AN11: =IF(AD11>320,320,AD11) -> 0 | AO11: =AG11-AN11-AJ11 -> 168.9984 | AP11: =AH11-AK11-AL11-AM11-BB11 -> 5199.5605 | AQ11: =AO11+(AP11/$AQ$1) -> 363.77424 | AR11: =BT11 -> 55.94356 | AS11: 0 | AT11: =AR11-AS11 -> 55.94356 | AU11: =AT11*AE11 -> 25.989669 | AV11: =AU11*0.03 -> 0.77969007 | AW11: =(AT11-AU11)*$AQ$1 -> 799.62211 | AX11: =AW11*0.03 -> 23.988663 | AY11: =AO11-AU11-AV11 -> 142.22904 | AZ11: =AP11-AW11-AX11 -> 4375.9498 | BA11: ='Nyaradzo Workings'!K15 -> 785.3847 | BB11: 0 | BL11: =AY11-BI11-BG11-BH11-BD11+BJ11 -> 142.22904 | BM11: =AZ11-BA11-BC11-BE11-BF11+BK11 -> 3590.5651 | BN11: =IF(AQ11<100,0,0) -> 0 | BO11: =IF(AQ11<100,"",IF(AQ11<=300,AQ11*0.2-20,)) -> 0 | BP11: =IF(AQ11<300.01,"",IF(AQ11<=1000,AQ11*0.25-35,)) -> 55.94356 | BQ11: =IF(AQ11<1000.01,"",IF(AQ11<=2000,AQ11*0.3-85,)) | BR11: =IF(AQ11<2000.01,"",IF(AQ11<=3000,AQ11*0.35-185,)) | BS11: =IF(AQ11<3000.01,"",IF(AQ11>3000,AQ11*0.4-335,)) | BT11: =SUM(BN11:BS11) -> 55.94356 | BU11: FBC | BV11: Zvishavane | BW11: 6866940554958 | BX11: FBC | BY11: Zvishavane | BZ11: 3301119435213 | CA11: 13.82 | CB11: 2.5 | CE11: =CA11+CB11-CC11-CD11 -> 16.32 | CF11: =M11*8 -> 12.96 | CG11: =CE11*CF11 -> 211.5072 | CH11: =CG11*0.4 -> 84.60288 | CI11: =(CG11-CH11)*$CI$2 -> 3387.7235
A12: AES-E037 | B12: Tarisai | C12: Chidzambwa | D12: 35-269430Q72 | E12: =E11 -> 45747 | F12: Mimosa | G12: Service Assitant | H12: 4/3 | I12: 4860684V | J12: =AO12/AQ12 -> 0.46456945 | K12: =K11 -> 3/2025 | L12: 208 | M12: 1.62 | N12: 25 | P12: =L12*M12 -> 336.96 | Q12: =P12*$Q$1 -> 8995.1809 | S12: =P12*0.3*$S$1*0.5 -> 1349.2771 | T12: =N12*M12*8*0.05 -> 16.2 | U12: =O12*M12*0.1 -> 0 | W12: =Y12*M12*2 -> 0 | X12: =Z12*M12*1.5 -> 0 | AA12: =CD12 -> 0 | AC12: =M12*8*AA12 -> 0 | AE12: =AO12/AQ12 -> 0.46456945 | AF12: =P12+R12+T12+U12+V12+W12+X12+AB12+AC12+AD12 -> 353.16 | AG12: =AF12*0.5 -> 176.58 | AH12: =(AF12-AG12)*$AH$1+S12 -> 6063.0979 | AI12: =IF(Q12>18519.27,0.045*18519.27,Q12*0.045) -> 404.78314 | AJ12: =(AI12*0.5)/$AQ$1 -> 7.5816 | AK12: =(AI12*0.4) -> 161.91326 | AL12: =Q12*0.075 -> 674.63857 | AM12: =Q12*0.003 -> 26.985543 | AN12: =IF(AD12>320,320,AD12) -> 0 | AO12: =AG12-AN12-AJ12 -> 168.9984 | AP12: =AH12-AK12-AL12-AM12-BB12 -> 5199.5605 | AQ12: =AO12+(AP12/$AQ$1) -> 363.77424 | AR12: =BT12 -> 55.94356 | AS12: 0 | AT12: =AR12-AS12 -> 55.94356 | AU12: =AT12*AE12 -> 25.989669 | AV12: =AU12*0.03 -> 0.77969007 | AW12: =(AT12-AU12)*$AQ$1 -> 799.62211 | AX12: =AW12*0.03 -> 23.988663 | AY12: =AO12-AU12-AV12 -> 142.22904 | AZ12: =AP12-AW12-AX12 -> 4375.9498 | BA12: 0 | BB12: 0 | BL12: =AY12-BI12-BG12-BH12-BD12+BJ12 -> 142.22904 | BM12: =AZ12-BA12-BC12-BE12-BF12+BK12 -> 4375.9498 | BN12: =IF(AQ12<100,0,0) -> 0 | BO12: =IF(AQ12<100,"",IF(AQ12<=300,AQ12*0.2-20,)) -> 0 | BP12: =IF(AQ12<300.01,"",IF(AQ12<=1000,AQ12*0.25-35,)) -> 55.94356 | BQ12: =IF(AQ12<1000.01,"",IF(AQ12<=2000,AQ12*0.3-85,)) | BR12: =IF(AQ12<2000.01,"",IF(AQ12<=3000,AQ12*0.35-185,)) | BS12: =IF(AQ12<3000.01,"",IF(AQ12>3000,AQ12*0.4-335,)) | BT12: =SUM(BN12:BS12) -> 55.94356 | BU12: FBC | BV12: Zvishavane | BW12: 8523518553916 | BX12: FBC | BY12: Zvishavane | BZ12: 1169912801200 | CA12: 20 | CB12: 2.5 | CE12: =CA12+CB12-CC12-CD12 -> 22.5 | CF12: =M12*8 -> 12.96 | CG12: =CE12*CF12 -> 291.6 | CH12: =CG12*0.4 -> 116.64 | CI12: =(CG12-CH12)*$CI$2 -> 4670.5747
A13: AES-E015 | B13: Believe | C13: Mhererwa | D13: 16-178898Z21 | E13: =E12 -> 45747 | F13: Mimosa | G13: Service Assitant | H13: 4/3 | I13: 3351868P | J13: =AO13/AQ13 -> 0.43829694 | K13: =K12 -> 3/2025 | L13: 208 | M13: 1.62 | N13: 24 | P13: =L13*M13 -> 336.96 | Q13: =P13*$Q$1 -> 8995.1809 | S13: =P13*0.3*$S$1*0.5 -> 1349.2771 | T13: =N13*M13*8*0.05 -> 15.552 | U13: =O13*M13*0.1 -> 0 | W13: =Y13*M13*2 -> 0 | X13: =Z13*M13*1.5 -> 0 | AA13: =CD13 -> 0 | AB13: =P13*0.075 -> 25.272 | AC13: =M13*8*AA13 -> 0 | AE13: =AO13/AQ13 -> 0.43829694 | AF13: =P13+R13+T13+U13+V13+W13+X13+AB13+AC13+AD13 -> 377.784 | AG13: =AF13*0.5 -> 188.892 | AH13: =(AF13-AG13)*$AH$1+S13 -> 6391.768 | AI13: =IF(Q13>18519.27,0.045*18519.27,Q13*0.045) -> 404.78314 | AJ13: =(AI13*0.5)/$AQ$1 -> 7.5816 | AK13: =(AI13*0.4) -> 161.91326 | AL13: 0 | AM13: =Q13*0.003 -> 26.985543 | AN13: =IF(AD13>320,320,AD13) -> 0 | AO13: =AG13-AN13-AJ13 -> 181.3104 | AP13: =AH13-AK13-AL13-AM13-BB13 -> 6202.8692 | AQ13: =AO13+(AP13/$AQ$1) -> 413.67024 | AR13: =BT13 -> 68.41756 | AS13: 0 | AT13: =AR13-AS13 -> 68.41756 | AU13: =AT13*AE13 -> 29.987207 | AV13: =AU13*0.03 -> 0.89961621 | AW13: =(AT13-AU13)*$AQ$1 -> 1025.9021 | AX13: =AW13*0.03 -> 30.777063 | AY13: =AO13-AU13-AV13 -> 150.42358 | AZ13: =AP13-AW13-AX13 -> 5146.19 | BA13: 0 | BB13: 0 | BG13: 120 | BL13: =AY13-BI13-BG13-BH13-BD13+BJ13 -> 30.423577 | BM13: =AZ13-BA13-BC13-BE13-BF13+BK13 -> 5146.19 | BN13: =IF(AQ13<100,0,0) -> 0 | BO13: =IF(AQ13<100,"",IF(AQ13<=300,AQ13*0.2-20,)) -> 0 | BP13: =IF(AQ13<300.01,"",IF(AQ13<=1000,AQ13*0.25-35,)) -> 68.41756 | BQ13: =IF(AQ13<1000.01,"",IF(AQ13<=2000,AQ13*0.3-85,)) | BR13: =IF(AQ13<2000.01,"",IF(AQ13<=3000,AQ13*0.35-185,)) | BS13: =IF(AQ13<3000.01,"",IF(AQ13>3000,AQ13*0.4-335,)) | BT13: =SUM(BN13:BS13) -> 68.41756 | BU13: FBC | BV13: Zvishavane | BW13: 1633703484987 | BX13: FBC | BY13: Zvishavane | BZ13: 7497575109867 | CA13: 4.02 | CB13: 2.5 | CC13: 1 | CE13: =CA13+CB13-CC13-CD13 -> 5.52 | CF13: =M13*8 -> 12.96 | CG13: =CE13*CF13 -> 71.5392 | CH13: =CG13*0.4 -> 28.61568 | CI13: =(CG13-CH13)*$CI$2 -> 1145.8477
A14: AES-E016 | B14: Shingai | C14: Rusike | D14: 76-679364E57 | E14: =E13 -> 45747 | F14: Mimosa | G14: Service Assitant | H14: 4/3 | I14: 4078418J | J14: =AO14/AQ14 -> 0.43839344 | K14: =K13 -> 3/2025 | L14: 208 | M14: 1.62 | N14: 25 | P14: =L14*M14 -> 336.96 | Q14: =P14*$Q$1 -> 8995.1809 | S14: =P14*0.3*$S$1*0.5 -> 1349.2771 | T14: =N14*M14*8*0.05 -> 16.2 | U14: =O14*M14*0.1 -> 0 | W14: =Y14*M14*2 -> 0 | X14: =Z14*M14*1.5 -> 0 | AA14: =CD14 -> 0 | AB14: =P14*0.075 -> 25.272 | AC14: =M14*8*AA14 -> 0 | AE14: =AO14/AQ14 -> 0.43839344 | AF14: =P14+R14+T14+U14+V14+W14+X14+AB14+AC14+AD14 -> 378.432 | AG14: =AF14*0.5 -> 189.216 | AH14: =(AF14-AG14)*$AH$1+S14 -> 6400.4172 | AI14: =IF(Q14>18519.27,0.045*18519.27,Q14*0.045) -> 404.78314 | AJ14: =(AI14*0.5)/$AQ$1 -> 7.5816 | AK14: =(AI14*0.4) -> 161.91326 | AL14: 0 | AM14: =Q14*0.003 -> 26.985543 | AN14: =IF(AD14>320,320,AD14) -> 0 | AO14: =AG14-AN14-AJ14 -> 181.6344 | AP14: =AH14-AK14-AL14-AM14-BB14 -> 6211.5184 | AQ14: =AO14+(AP14/$AQ$1) -> 414.31824 | AR14: =BT14 -> 68.57956 | AS14: 0 | AT14: =AR14-AS14 -> 68.57956 | AU14: =AT14*AE14 -> 30.064829 | AV14: =AU14*0.03 -> 0.90194488 | AW14: =(AT14-AU14)*$AQ$1 -> 1028.1546 | AX14: =AW14*0.03 -> 30.844637 | AY14: =AO14-AU14-AV14 -> 150.66763 | AZ14: =AP14-AW14-AX14 -> 5152.5192 | BA14: ='Nyaradzo Workings'!K16 -> 404.5147 | BB14: 0 | BI14: 12.5 | BL14: =AY14-BI14-BG14-BH14-BD14+BJ14 -> 138.16763 | BM14: =AZ14-BA14-BC14-BE14-BF14+BK14 -> 4748.0045 | BN14: =IF(AQ14<100,0,0) -> 0 | BO14: =IF(AQ14<100,"",IF(AQ14<=300,AQ14*0.2-20,)) -> 0 | BP14: =IF(AQ14<300.01,"",IF(AQ14<=1000,AQ14*0.25-35,)) -> 68.57956 | BQ14: =IF(AQ14<1000.01,"",IF(AQ14<=2000,AQ14*0.3-85,)) | BR14: =IF(AQ14<2000.01,"",IF(AQ14<=3000,AQ14*0.35-185,)) | BS14: =IF(AQ14<3000.01,"",IF(AQ14>3000,AQ14*0.4-335,)) | BT14: =SUM(BN14:BS14) -> 68.57956 | BU14: FBC | BV14: Zvishavane | BW14: 1734986781954 | BX14: FBC | BY14: Zvishavane | BZ14: 7413710132455 | CA14: 15.76 | CB14: 2.5 | CE14: =CA14+CB14-CC14-CD14 -> 18.26 | CF14: =M14*8 -> 12.96 | CG14: =CE14*CF14 -> 236.6496 | CH14: =CG14*0.4 -> 94.65984 | CI14: =(CG14-CH14)*$CI$2 -> 3790.4308
A15: AES-E018 | B15: Gamuchirai | C15: Chirenda | D15: 07-475190G33 | E15: =E14 -> 45747 | F15: Mimosa | G15: Service Assitant | H15: 4/3 | I15: 8761611H | J15: =AO15/AQ15 -> 0.43839344 | K15: =K14 -> 3/2025 | L15: 208 | M15: 1.62 | N15: 25 | P15: =L15*M15 -> 336.96 | Q15: =P15*$Q$1 -> 8995.1809 | S15: =P15*0.3*$S$1*0.5 -> 1349.2771 | T15: =N15*M15*8*0.05 -> 16.2 | U15: =O15*M15*0.1 -> 0 | W15: =Y15*M15*2 -> 0 | X15: =Z15*M15*1.5 -> 0 | AA15: =CD15 -> 0 | AB15: =P15*0.075 -> 25.272 | AC15: =M15*8*AA15 -> 0 | AE15: =AO15/AQ15 -> 0.43839344 | AF15: =P15+R15+T15+U15+V15+W15+X15+AB15+AC15+AD15 -> 378.432 | AG15: =AF15*0.5 -> 189.216 | AH15: =(AF15-AG15)*$AH$1+S15 -> 6400.4172 | AI15: =IF(Q15>18519.27,0.045*18519.27,Q15*0.045) -> 404.78314 | AJ15: =(AI15*0.5)/$AQ$1 -> 7.5816 | AK15: =(AI15*0.4) -> 161.91326 | AL15: 0 | AM15: =Q15*0.003 -> 26.985543 | AN15: =IF(AD15>320,320,AD15) -> 0 | AO15: =AG15-AN15-AJ15 -> 181.6344 | AP15: =AH15-AK15-AL15-AM15-BB15 -> 6211.5184 | AQ15: =AO15+(AP15/$AQ$1) -> 414.31824 | AR15: =BT15 -> 68.57956 | AS15: 0 | AT15: =AR15-AS15 -> 68.57956 | AU15: =AT15*AE15 -> 30.064829 | AV15: =AU15*0.03 -> 0.90194488 | AW15: =(AT15-AU15)*$AQ$1 -> 1028.1546 | AX15: =AW15*0.03 -> 30.844637 | AY15: =AO15-AU15-AV15 -> 150.66763 | AZ15: =AP15-AW15-AX15 -> 5152.5192 | BA15: ='Nyaradzo Workings'!K18 -> 472.7647 | BB15: 0 | BI15: 12.5 | BL15: =AY15-BI15-BG15-BH15-BD15+BJ15 -> 138.16763 | BM15: =AZ15-BA15-BC15-BE15-BF15+BK15 -> 4679.7545 | BN15: =IF(AQ15<100,0,0) -> 0 | BO15: =IF(AQ15<100,"",IF(AQ15<=300,AQ15*0.2-20,)) -> 0 | BP15: =IF(AQ15<300.01,"",IF(AQ15<=1000,AQ15*0.25-35,)) -> 68.57956 | BQ15: =IF(AQ15<1000.01,"",IF(AQ15<=2000,AQ15*0.3-85,)) | BR15: =IF(AQ15<2000.01,"",IF(AQ15<=3000,AQ15*0.35-185,)) | BS15: =IF(AQ15<3000.01,"",IF(AQ15>3000,AQ15*0.4-335,)) | BT15: =SUM(BN15:BS15) -> 68.57956 | BU15: FBC | BV15: Zvishavane | BW15: 2811045688826 | BX15: FBC | BY15: Zvishavane | BZ15: 8150582443075 | CA15: 16.81 | CB15: 2.5 | CE15: =CA15+CB15-CC15-CD15 -> 19.31 | CF15: =M15*8 -> 12.96 | CG15: =CE15*CF15 -> 250.2576 | CH15: =CG15*0.4 -> 100.10304 | CI15: =(CG15-CH15)*$CI$2 -> 4008.391
A16: AES-E013 | B16: Chido | C16: Chigumba | D16: 21-348237F24 | E16: =E15 -> 45747 | F16: Mimosa | G16: Service Assitant | H16: 4/3 | I16: 2264748Q | J16: =AO16/AQ16 -> 0.43829694 | K16: =K15 -> 3/2025 | L16: 208 | M16: 1.62 | N16: 24 | P16: =L16*M16 -> 336.96 | Q16: =P16*$Q$1 -> 8995.1809 | S16: =P16*0.3*$S$1*0.5 -> 1349.2771 | T16: =N16*M16*8*0.05 -> 15.552 | U16: =O16*M16*0.1 -> 0 | W16: =Y16*M16*2 -> 0 | X16: =Z16*M16*1.5 -> 0 | AA16: =CD16 -> 0 | AB16: =P16*0.075 -> 25.272 | AC16: =M16*8*AA16 -> 0 | AE16: =AO16/AQ16 -> 0.43829694 | AF16: =P16+R16+T16+U16+V16+W16+X16+AB16+AC16+AD16 -> 377.784 | AG16: =AF16*0.5 -> 188.892 | AH16: =(AF16-AG16)*$AH$1+S16 -> 6391.768 | AI16: =IF(Q16>18519.27,0.045*18519.27,Q16*0.045) -> 404.78314 | AJ16: =(AI16*0.5)/$AQ$1 -> 7.5816 | AK16: =(AI16*0.4) -> 161.91326 | AL16: 0 | AM16: =Q16*0.003 -> 26.985543 | AN16: =IF(AD16>320,320,AD16) -> 0 | AO16: =AG16-AN16-AJ16 -> 181.3104 | AP16: =AH16-AK16-AL16-AM16-BB16 -> 6202.8692 | AQ16: =AO16+(AP16/$AQ$1) -> 413.67024 | AR16: =BT16 -> 68.41756 | AS16: 0 | AT16: =AR16-AS16 -> 68.41756 | AU16: =AT16*AE16 -> 29.987207 | AV16: =AU16*0.03 -> 0.89961621 | AW16: =(AT16-AU16)*$AQ$1 -> 1025.9021 | AX16: =AW16*0.03 -> 30.777063 | AY16: =AO16-AU16-AV16 -> 150.42358 | AZ16: =AP16-AW16-AX16 -> 5146.19 | BA16: ='Nyaradzo Workings'!K19 -> 316.4547 | BB16: 0 | BL16: =AY16-BI16-BG16-BH16-BD16+BJ16 -> 150.42358 | BM16: =AZ16-BA16-BC16-BE16-BF16+BK16 -> 4829.7353 | BN16: =IF(AQ16<100,0,0) -> 0 | BO16: =IF(AQ16<100,"",IF(AQ16<=300,AQ16*0.2-20,)) -> 0 | BP16: =IF(AQ16<300.01,"",IF(AQ16<=1000,AQ16*0.25-35,)) -> 68.41756 | BQ16: =IF(AQ16<1000.01,"",IF(AQ16<=2000,AQ16*0.3-85,)) | BR16: =IF(AQ16<2000.01,"",IF(AQ16<=3000,AQ16*0.35-185,)) | BS16: =IF(AQ16<3000.01,"",IF(AQ16>3000,AQ16*0.4-335,)) | BT16: =SUM(BN16:BS16) -> 68.41756 | BU16: FBC | BV16: Zvishavane | BW16: 8253690449424 | BX16: FBC | BY16: Zvishavane | BZ16: 4152612451898 | CA16: 23.62 | CB16: 2.5 | CC16: 1 | CE16: =CA16+CB16-CC16-CD16 -> 25.12 | CF16: =M16*8 -> 12.96 | CG16: =CE16*CF16 -> 325.5552 | CH16: =CG16*0.4 -> 130.22208 | CI16: =(CG16-CH16)*$CI$2 -> 5214.4372
A17: AES-E045 | B17: Tinotenda | C17: Nyagura | D17: 44-920391P33 | E17: =E16 -> 45747 | F17: Mimosa | G17: Bricklayer | H17: 4/5 | I17: 6543670C | J17: =AO17/AQ17 -> 0.45319333 | K17: =K16 -> 3/2025 | L17: 208 | M17: 1.8 | N17: 23 | P17: =L17*M17 -> 374.4 | Q17: =P17*$Q$1 -> 9994.6454 | R17: 3 | S17: =P17*0.3*$S$1*0.5 -> 1499.1968 | T17: =N17*M17*8*0.05 -> 16.56 | U17: =O17*M17*0.1 -> 0 | W17: =Y17*M17*2 -> 0 | X17: =Z17*M17*1.5 -> 0 | AA17: =CD17 -> 10 | AB17: =P17*0.075 -> 28.08 | AC17: =M17*8*AA17 -> 144 | AE17: =AO17/AQ17 -> 0.45319333 | AF17: =P17+R17+T17+U17+V17+W17+X17+AB17+AC17+AD17 -> 566.04 | AG17: =AF17*0.5 -> 283.02 | AH17: =(AF17-AG17)*$AH$1+S17 -> 9054.444 | AI17: =IF(Q17>18519.27,0.045*18519.27,Q17*0.045) -> 449.75904 | AJ17: =(AI17*0.5)/$AQ$1 -> 8.424 | AK17: =(AI17*0.4) -> 179.90362 | AL17: 0 | AM17: =Q17*0.003 -> 29.983936 | AN17: =IF(AD17>320,320,AD17) -> 0 | AO17: =AG17-AN17-AJ17 -> 274.596 | AP17: =AH17-AK17-AL17-AM17-BB17 -> 8844.5565 | AQ17: =AO17+(AP17/$AQ$1) -> 605.9136 | AR17: =BT17 -> 116.4784 | AS17: 0 | AT17: =AR17-AS17 -> 116.4784 | AU17: =AT17*AE17 -> 52.787234 | AV17: =AU17*0.03 -> 1.583617 | AW17: =(AT17-AU17)*$AQ$1 -> 1700.2421 | AX17: =AW17*0.03 -> 51.007262 | AY17: =AO17-AU17-AV17 -> 220.22515 | AZ17: =AP17-AW17-AX17 -> 7093.3071 | BA17: 0 | BB17: 0 | BI17: 12.5 | BL17: =AY17-BI17-BG17-BH17-BD17+BJ17 -> 207.72515 | BM17: =AZ17-BA17-BC17-BE17-BF17+BK17 -> 7093.3071 | BN17: =IF(AQ17<100,0,0) -> 0 | BO17: =IF(AQ17<100,"",IF(AQ17<=300,AQ17*0.2-20,)) -> 0 | BP17: =IF(AQ17<300.01,"",IF(AQ17<=1000,AQ17*0.25-35,)) -> 116.4784 | BQ17: =IF(AQ17<1000.01,"",IF(AQ17<=2000,AQ17*0.3-85,)) | BR17: =IF(AQ17<2000.01,"",IF(AQ17<=3000,AQ17*0.35-185,)) | BS17: =IF(AQ17<3000.01,"",IF(AQ17>3000,AQ17*0.4-335,)) | BT17: =SUM(BN17:BS17) -> 116.4784 | BU17: FBC | BV17: Zvishavane | BW17: 3801464598795 | BX17: FBC | BY17: Zvishavane | BZ17: 7726383052711 | CA17: 29.42 | CB17: 2.5 | CD17: 10 | CE17: =CA17+CB17-CC17-CD17 -> 21.92 | CF17: =M17*8 -> 14.4 | CG17: =CE17*CF17 -> 315.648 | CH17: =CG17*0.4 -> 126.2592 | CI17: =(CG17-CH17)*$CI$2 -> 5055.753
A18: AES-E048 | B18: Nomatter | C18: Nhira | D18: 06-593554H27 | E18: =E17 -> 45747 | F18: Mimosa | G18: Team Leader Con | H18: 4/7 | I18: 2191066Z | J18: =AO18/AQ18 -> 0.46467508 | K18: =K17 -> 3/2025 | L18: 208 | M18: 2.8 | N18: 24 | P18: =L18*M18 -> 582.4 | Q18: =P18*$Q$1 -> 15547.226 | R18: 3 | S18: =P18*0.3*$S$1*0.5 -> 2332.0839 | T18: =N18*M18*8*0.05 -> 26.88 | U18: =O18*M18*0.1 -> 0 | W18: =Y18*M18*2 -> 0 | X18: =Z18*M18*1.5 -> 0 | AA18: =CD18 -> 0 | AC18: =M18*8*AA18 -> 0 | AE18: =AO18/AQ18 -> 0.46467508 | AF18: =P18+R18+T18+U18+V18+W18+X18+AB18+AC18+AD18 -> 612.28 | AG18: =AF18*0.5 -> 306.14 | AH18: =(AF18-AG18)*$AH$1+S18 -> 10504.522 | AI18: =IF(Q18>18519.27,0.045*18519.27,Q18*0.045) -> 699.62518 | AJ18: =(AI18*0.5)/$AQ$1 -> 13.104 | AK18: =(AI18*0.4) -> 279.85007 | AL18: =Q18*0.075 -> 1166.042 | AM18: =Q18*0.003 -> 46.641679 | AN18: =IF(AD18>320,320,AD18) -> 0 | AO18: =AG18-AN18-AJ18 -> 293.036 | AP18: =AH18-AK18-AL18-AM18-BB18 -> 9011.9881 | AQ18: =AO18+(AP18/$AQ$1) -> 630.6256 | AR18: =BT18 -> 122.6564 | AS18: 0 | AT18: =AR18-AS18 -> 122.6564 | AU18: =AT18*AE18 -> 56.995372 | AV18: =AU18*0.03 -> 1.7098612 | AW18: =(AT18-AU18)*$AQ$1 -> 1752.8277 | AX18: =AW18*0.03 -> 52.584831 | AY18: =AO18-AU18-AV18 -> 234.33077 | AZ18: =AP18-AW18-AX18 -> 7206.5756 | BA18: 0 | BB18: 0 | BC18: =20*AQ1 -> 533.902 | BI18: 12.5 | BL18: =AY18-BI18-BG18-BH18-BD18+BJ18 -> 221.83077 | BM18: =AZ18-BA18-BC18-BE18-BF18+BK18 -> 6672.6736 | BN18: =IF(AQ18<100,0,0) -> 0 | BO18: =IF(AQ18<100,"",IF(AQ18<=300,AQ18*0.2-20,)) -> 0 | BP18: =IF(AQ18<300.01,"",IF(AQ18<=1000,AQ18*0.25-35,)) -> 122.6564 | BQ18: =IF(AQ18<1000.01,"",IF(AQ18<=2000,AQ18*0.3-85,)) | BR18: =IF(AQ18<2000.01,"",IF(AQ18<=3000,AQ18*0.35-185,)) | BS18: =IF(AQ18<3000.01,"",IF(AQ18>3000,AQ18*0.4-335,)) | BT18: =SUM(BN18:BS18) -> 122.6564 | BU18: FBC | BV18: Zvishavane | BW18: 7152370155220 | BX18: FBC | BY18: Zvishavane | BZ18: 4922282656442 | CA18: 29.13 | CB18: 2.5 | CC18: 1 | CE18: =CA18+CB18-CC18-CD18 -> 30.63 | CF18: =M18*8 -> 22.4 | CG18: =CE18*CF18 -> 686.112 | CH18: =CG18*0.4 -> 274.4448 | CI18: =(CG18-CH18)*$CI$2 -> 10989.497
A19: AES-E043 | B19: Zvikomborero | C19: Mpofu | D19: 05-792094G53 | E19: =E18 -> 45747 | F19: Mimosa | G19: Service Assitant | H19: 4/3 | I19: 9626108H | J19: =AO19/AQ19 -> 0.47387638 | K19: =K18 -> 3/2025 | L19: 208 | M19: 1.62 | N19: 25 | P19: =L19*M19 -> 336.96 | Q19: =P19*$Q$1 -> 8995.1809 | S19: =P19*0.3*$S$1*0.5 -> 1349.2771 | T19: =N19*M19*8*0.05 -> 16.2 | U19: =O19*M19*0.1 -> 0 | W19: =Y19*M19*2 -> 0 | X19: =Z19*M19*1.5 -> 0 | AA19: =CD19 -> 10 | AC19: =M19*8*AA19 -> 129.6 | AE19: =AO19/AQ19 -> 0.47387638 | AF19: =P19+R19+T19+U19+V19+W19+X19+AB19+AC19+AD19 -> 482.76 | AG19: =AF19*0.5 -> 241.38 | AH19: =(AF19-AG19)*$AH$1+S19 -> 7792.9404 | AI19: =IF(Q19>18519.27,0.045*18519.27,Q19*0.045) -> 404.78314 | AJ19: =(AI19*0.5)/$AQ$1 -> 7.5816 | AK19: =(AI19*0.4) -> 161.91326 | AL19: =Q19*0.075 -> 674.63857 | AM19: =Q19*0.003 -> 26.985543 | AN19: =IF(AD19>320,320,AD19) -> 0 | AO19: =AG19-AN19-AJ19 -> 233.7984 | AP19: =AH19-AK19-AL19-AM19-BB19 -> 6929.403 | AQ19: =AO19+(AP19/$AQ$1) -> 493.37424 | AR19: =BT19 -> 88.34356 | AS19: 0 | AT19: =AR19-AS19 -> 88.34356 | AU19: =AT19*AE19 -> 41.863927 | AV19: =AU19*0.03 -> 1.2559178 | AW19: =(AT19-AU19)*$AQ$1 -> 1240.7785 | AX19: =AW19*0.03 -> 37.223354 | AY19: =AO19-AU19-AV19 -> 190.67856 | AZ19: =AP19-AW19-AX19 -> 5651.4012 | BA19: ='Nyaradzo Workings'!K20 -> 472.7647 | BB19: 0 | BL19: =AY19-BI19-BG19-BH19-BD19+BJ19 -> 190.67856 | BM19: =AZ19-BA19-BC19-BE19-BF19+BK19 -> 5178.6365 | BN19: =IF(AQ19<100,0,0) -> 0 | BO19: =IF(AQ19<100,"",IF(AQ19<=300,AQ19*0.2-20,)) -> 0 | BP19: =IF(AQ19<300.01,"",IF(AQ19<=1000,AQ19*0.25-35,)) -> 88.34356 | BQ19: =IF(AQ19<1000.01,"",IF(AQ19<=2000,AQ19*0.3-85,)) | BR19: =IF(AQ19<2000.01,"",IF(AQ19<=3000,AQ19*0.35-185,)) | BS19: =IF(AQ19<3000.01,"",IF(AQ19>3000,AQ19*0.4-335,)) | BT19: =SUM(BN19:BS19) -> 88.34356 | BU19: FBC | BV19: Zvishavane | BW19: 5901967559084 | BX19: FBC | BY19: Zvishavane | BZ19: 2223483079689 | CA19: 17.29 | CB19: 2.5 | CD19: 10 | CE19: =CA19+CB19-CC19-CD19 -> 9.79 | CF19: =M19*8 -> 12.96 | CG19: =CE19*CF19 -> 126.8784 | CH19: =CG19*0.4 -> 50.75136 | CI19: =(CG19-CH19)*$CI$2 -> 2032.2189
A20: AES-E044 | B20: Anesu | C20: Chidzambwa | D20: 37-468203X67 | E20: =E19 -> 45747 | F20: Mimosa | G20: Team Leader Tran | H20: 4/7 | I20: 4694634A | J20: =AO20/AQ20 -> 0.48144555 | K20: =K19 -> 3/2025 | L20: 136 | M20: 2.8 | N20: 15 | O20: 116 | P20: =L20*M20 -> 380.8 | Q20: =P20*$Q$1 -> 10165.494 | S20: =P20*0.3*$S$1*0.5 -> 1524.8241 | T20: =N20*M20*8*0.05 -> 16.8 | U20: =O20*M20*0.1 -> 32.48 | W20: =Y20*M20*2 -> 0 | X20: =Z20*M20*1.5 -> 0 | AA20: =CD20 -> 15.31 | AC20: =M20*8*AA20 -> 342.944 | AE20: =AO20/AQ20 -> 0.48144555 | AF20: =P20+R20+T20+U20+V20+W20+X20+AB20+AC20+AD20 -> 773.024 | AG20: =AF20*0.5 -> 386.512 | AH20: =(AF20-AG20)*$AH$1+S20 -> 11842.801 | AI20: =IF(Q20>18519.27,0.045*18519.27,Q20*0.045) -> 457.44723 | AJ20: =(AI20*0.5)/$AQ$1 -> 8.568 | AK20: =(AI20*0.4) -> 182.97889 | AL20: =Q20*0.075 -> 762.41206 | AM20: =Q20*0.003 -> 30.496482 | AN20: =IF(AD20>320,320,AD20) -> 0 | AO20: =AG20-AN20-AJ20 -> 377.944 | AP20: =AH20-AK20-AL20-AM20-BB20 -> 10866.913 | AQ20: =AO20+(AP20/$AQ$1) -> 785.0192 | AR20: =BT20 -> 161.2548 | AS20: 0 | AT20: =AR20-AS20 -> 161.2548 | AU20: =AT20*AE20 -> 77.635406 | AV20: =AU20*0.03 -> 2.3290622 | AW20: =(AT20-AU20)*$AQ$1 -> 2232.2281 | AX20: =AW20*0.03 -> 66.966843 | AY20: =AO20-AU20-AV20 -> 297.97953 | AZ20: =AP20-AW20-AX20 -> 8567.7182 | BA20: ='Nyaradzo Workings'!K21 -> 553.5847 | BB20: 0 | BL20: =AY20-BI20-BG20-BH20-BD20+BJ20 -> 297.97953 | BM20: =AZ20-BA20-BC20-BE20-BF20+BK20 -> 8014.1335 | BN20: =IF(AQ20<100,0,0) -> 0 | BO20: =IF(AQ20<100,"",IF(AQ20<=300,AQ20*0.2-20,)) -> 0 | BP20: =IF(AQ20<300.01,"",IF(AQ20<=1000,AQ20*0.25-35,)) -> 161.2548 | BQ20: =IF(AQ20<1000.01,"",IF(AQ20<=2000,AQ20*0.3-85,)) | BR20: =IF(AQ20<2000.01,"",IF(AQ20<=3000,AQ20*0.35-185,)) | BS20: =IF(AQ20<3000.01,"",IF(AQ20>3000,AQ20*0.4-335,)) | BT20: =SUM(BN20:BS20) -> 161.2548 | BU20: FBC | BV20: Zvishavane | BW20: 6826278682407 | BX20: FBC | BY20: Zvishavane | BZ20: 1489365297273 | CA20: 12.81 | CB20: 2.5 | CD20: 15.31 | CE20: =CA20+CB20-CC20-CD20 -> 0 | CF20: =M20*8 -> 22.4 | CG20: =CE20*CF20 -> 0 | CH20: =CG20*0.4 -> 0 | CI20: =(CG20-CH20)*$CI$2 -> 0
A21: AES-E047 | B21: Innocent | C21: Chihota | D21: 16-373903F76 | E21: =E20 -> 45747 | F21: Mimosa | G21: Team Leader | H21: 4/7 | I21: 4769795C | J21: =AO21/AQ21 -> 0.46333151 | K21: =K20 -> 3/2025 | L21: 208 | M21: 2.8 | N21: 25 | O21: 20 | P21: =L21*M21 -> 582.4 | Q21: =P21*$Q$1 -> 15547.226 | S21: =P21*0.3*$S$1*0.5 -> 2332.0839 | T21: =N21*M21*8*0.05 -> 28 | U21: =O21*M21*0.1 -> 5.6 | V21: =145.42 -> 145.42 | W21: =Y21*M21*2 -> 0 | X21: =Z21*M21*1.5 -> 0 | AA21: =CD21 -> 15 | AB21: =P21*0.075 -> 43.68 | AC21: =M21*8*AA21 -> 336 | AE21: =AO21/AQ21 -> 0.46333151 | AF21: =P21+R21+T21+U21+V21+W21+X21+AB21+AC21+AD21 -> 1141.1 | AG21: =AF21*0.5 -> 570.55 | AH21: =(AF21-AG21)*$AH$1+S21 -> 17562.973 | AI21: =IF(Q21>18519.27,0.045*18519.27,Q21*0.045) -> 699.62518 | AJ21: =(AI21*0.5)/$AQ$1 -> 13.104 | AK21: =(AI21*0.4) -> 279.85007 | AL21: 0 | AM21: =Q21*0.003 -> 46.641679 | AN21: =IF(AD21>320,320,AD21) -> 0 | AO21: =AG21-AN21-AJ21 -> 557.446 | AP21: =AH21-AK21-AL21-AM21-BB21 -> 17236.481 | AQ21: =AO21+(AP21/$AQ$1) -> 1203.1256 | AR21: =BT21 -> 275.93768 | AS21: 0 | AT21: =AR21-AS21 -> 275.93768 | AU21: =AT21*AE21 -> 127.85062 | AV21: =AU21*0.03 -> 3.8355187 | AW21: =(AT21-AU21)*$AQ$1 -> 3953.1988 | AX21: =AW21*0.03 -> 118.59596 | AY21: =AO21-AU21-AV21 -> 425.75986 | AZ21: =AP21-AW21-AX21 -> 13164.687 | BA21: ='Nyaradzo Workings'!K22 -> 316.4547 | BI21: 12.5 | BL21: =AY21-BI21-BG21-BH21-BD21+BJ21 -> 413.25986 | BM21: =AZ21-BA21-BC21-BE21-BF21+BK21 -> 12848.232 | BN21: =IF(AQ21<100,0,0) -> 0 | BO21: =IF(AQ21<100,"",IF(AQ21<=300,AQ21*0.2-20,)) -> 0 | BP21: =IF(AQ21<300.01,"",IF(AQ21<=1000,AQ21*0.25-35,)) -> 0 | BQ21: =IF(AQ21<1000.01,"",IF(AQ21<=2000,AQ21*0.3-85,)) -> 275.93768 | BR21: =IF(AQ21<2000.01,"",IF(AQ21<=3000,AQ21*0.35-185,)) | BS21: =IF(AQ21<3000.01,"",IF(AQ21>3000,AQ21*0.4-335,)) | BT21: =SUM(BN21:BS21) -> 275.93768 | BU21: FBC | BV21: Zvishavane | BW21: 1671155067525 | BX21: FBC | BY21: Zvishavane | BZ21: 7079245160972 | CA21: 21.63 | CB21: 2.5 | CD21: 15 | CE21: =CA21+CB21-CC21-CD21 -> 9.13 | CF21: =M21*8 -> 22.4 | CG21: =CE21*CF21 -> 204.512 | CH21: =CG21*0.4 -> 81.8048 | CI21: =(CG21-CH21)*$CI$2 -> 3275.681
A22: AES-E038 | B22: Munyaradzi | C22: Zhou | D22: 42-557592W67 | E22: =E21 -> 45747 | F22: Mimosa | G22: Service Assitant | H22: 4/3 | I22: 8935169P | J22: =AO22/AQ22 -> 0.43839344 | K22: =K21 -> 3/2025 | L22: 208 | M22: 1.62 | N22: 25 | P22: =L22*M22 -> 336.96 | Q22: =P22*$Q$1 -> 8995.1809 | S22: =P22*0.3*$S$1*0.5 -> 1349.2771 | T22: =N22*M22*8*0.05 -> 16.2 | U22: =O22*M22*0.1 -> 0 | W22: =Y22*M22*2 -> 0 | X22: =Z22*M22*1.5 -> 0 | AA22: =CD22 -> 0 | AB22: =P22*0.075 -> 25.272 | AC22: =M22*8*AA22 -> 0 | AE22: =AO22/AQ22 -> 0.43839344 | AF22: =P22+R22+T22+U22+V22+W22+X22+AB22+AC22+AD22 -> 378.432 | AG22: =AF22*0.5 -> 189.216 | AH22: =(AF22-AG22)*$AH$1+S22 -> 6400.4172 | AI22: =IF(Q22>18519.27,0.045*18519.27,Q22*0.045) -> 404.78314 | AJ22: =(AI22*0.5)/$AQ$1 -> 7.5816 | AK22: =(AI22*0.4) -> 161.91326 | AL22: 0 | AM22: =Q22*0.003 -> 26.985543 | AN22: =IF(AD22>320,320,AD22) -> 0 | AO22: =AG22-AN22-AJ22 -> 181.6344 | AP22: =AH22-AK22-AL22-AM22-BB22 -> 6211.5184 | AQ22: =AO22+(AP22/$AQ$1) -> 414.31824 | AR22: =BT22 -> 68.57956 | AS22: 0 | AT22: =AR22-AS22 -> 68.57956 | AU22: =AT22*AE22 -> 30.064829 | AV22: =AU22*0.03 -> 0.90194488 | AW22: =(AT22-AU22)*$AQ$1 -> 1028.1546 | AX22: =AW22*0.03 -> 30.844637 | AY22: =AO22-AU22-AV22 -> 150.66763 | AZ22: =AP22-AW22-AX22 -> 5152.5192 | BA22: ='Nyaradzo Workings'!K23 -> 577.7647 | BI22: 12.5 | BL22: =AY22-BI22-BG22-BH22-BD22+BJ22 -> 138.16763 | BM22: =AZ22-BA22-BC22-BE22-BF22+BK22 -> 4574.7545 | BN22: =IF(AQ22<100,0,0) -> 0 | BO22: =IF(AQ22<100,"",IF(AQ22<=300,AQ22*0.2-20,)) -> 0 | BP22: =IF(AQ22<300.01,"",IF(AQ22<=1000,AQ22*0.25-35,)) -> 68.57956 | BQ22: =IF(AQ22<1000.01,"",IF(AQ22<=2000,AQ22*0.3-85,)) | BR22: =IF(AQ22<2000.01,"",IF(AQ22<=3000,AQ22*0.35-185,)) | BS22: =IF(AQ22<3000.01,"",IF(AQ22>3000,AQ22*0.4-335,)) | BT22: =SUM(BN22:BS22) -> 68.57956 | BU22: FBC | BV22: Zvishavane | BW22: 7773660120665 | BX22: FBC | BY22: Zvishavane | BZ22: 5480467271853 | CA22: 19.03 | CB22: 2.5 | CE22: =CA22+CB22-CC22-CD22 -> 21.53 | CF22: =M22*8 -> 12.96 | CG22: =CE22*CF22 -> 279.0288 | CH22: =CG22*0.4 -> 111.61152 | CI22: =(CG22-CH22)*$CI$2 -> 4469.221
A23: AES-E040 | B23: Takudzwa | C23: Nyandoro | D23: 07-843215P02 | E23: =E22 -> 45747 | F23: Mimosa | G23: Service Assitant | H23: 4/3 | I23: 4194548D | J23: =AO23/AQ23 -> 0.43839344 | K23: =K22 -> 3/2025 | L23: 208 | M23: 1.62 | N23: 25 | P23: =L23*M23 -> 336.96 | Q23: =P23*$Q$1 -> 8995.1809 | S23: =P23*0.3*$S$1*0.5 -> 1349.2771 | T23: =N23*M23*8*0.05 -> 16.2 | U23: =O23*M23*0.1 -> 0 | W23: =Y23*M23*2 -> 0 | X23: =Z23*M23*1.5 -> 0 | AA23: =CD23 -> 0 | AB23: =P23*0.075 -> 25.272 | AC23: =M23*8*AA23 -> 0 | AE23: =AO23/AQ23 -> 0.43839344 | AF23: =P23+R23+T23+U23+V23+W23+X23+AB23+AC23+AD23 -> 378.432 | AG23: =AF23*0.5 -> 189.216 | AH23: =(AF23-AG23)*$AH$1+S23 -> 6400.4172 | AI23: =IF(Q23>18519.27,0.045*18519.27,Q23*0.045) -> 404.78314 | AJ23: =(AI23*0.5)/$AQ$1 -> 7.5816 | AK23: =(AI23*0.4) -> 161.91326 | AL23: 0 | AM23: =Q23*0.003 -> 26.985543 | AN23: =IF(AD23>320,320,AD23) -> 0 | AO23: =AG23-AN23-AJ23 -> 181.6344 | AP23: =AH23-AK23-AL23-AM23-BB23 -> 6211.5184 | AQ23: =AO23+(AP23/$AQ$1) -> 414.31824 | AR23: =BT23 -> 68.57956 | AS23: 0 | AT23: =AR23-AS23 -> 68.57956 | AU23: =AT23*AE23 -> 30.064829 | AV23: =AU23*0.03 -> 0.90194488 | AW23: =(AT23-AU23)*$AQ$1 -> 1028.1546 | AX23: =AW23*0.03 -> 30.844637 | AY23: =AO23-AU23-AV23 -> 150.66763 | AZ23: =AP23-AW23-AX23 -> 5152.5192 | BA23: 0 | BB23: 0 | BL23: =AY23-BI23-BG23-BH23-BD23+BJ23 -> 150.66763 | BM23: =AZ23-BA23-BC23-BE23-BF23+BK23 -> 5152.5192 | BN23: =IF(AQ23<100,0,0) -> 0 | BO23: =IF(AQ23<100,"",IF(AQ23<=300,AQ23*0.2-20,)) -> 0 | BP23: =IF(AQ23<300.01,"",IF(AQ23<=1000,AQ23*0.25-35,)) -> 68.57956 | BQ23: =IF(AQ23<1000.01,"",IF(AQ23<=2000,AQ23*0.3-85,)) | BR23: =IF(AQ23<2000.01,"",IF(AQ23<=3000,AQ23*0.35-185,)) | BS23: =IF(AQ23<3000.01,"",IF(AQ23>3000,AQ23*0.4-335,)) | BT23: =SUM(BN23:BS23) -> 68.57956 | BU23: FBC | BV23: Zvishavane | BW23: 7404642497786 | BX23: FBC | BY23: Zvishavane | BZ23: 2230213054883 | CA23: 18.44 | CB23: 2.5 | CE23: =CA23+CB23-CC23-CD23 -> 20.94 | CF23: =M23*8 -> 12.96 | CG23: =CE23*CF23 -> 271.3824 | CH23: =CG23*0.4 -> 108.55296 | CI23: =(CG23-CH23)*$CI$2 -> 4346.7482
A24: AES-E039 | B24: Chiedza | C24: Mucheki | D24: 44-753425L17 | E24: =E23 -> 45747 | F24: Mimosa | G24: Service Assitant | H24: 4/3 | I24: 2626229Y | J24: =AO24/AQ24 -> 0.44210588 | K24: =K23 -> 3/2025 | L24: 208 | M24: 1.62 | N24: 26 | P24: =L24*M24 -> 336.96 | Q24: =P24*$Q$1 -> 8995.1809 | S24: =P24*0.3*$S$1*0.5 -> 1349.2771 | T24: =N24*M24*8*0.05 -> 16.848 | U24: =O24*M24*0.1 -> 0 | W24: =Y24*M24*2 -> 25.92 | X24: =Z24*M24*1.5 -> 0 | Y24: 8 | AA24: =CD24 -> 0 | AB24: =P24*0.075 -> 25.272 | AC24: =M24*8*AA24 -> 0 | AE24: =AO24/AQ24 -> 0.44210588 | AF24: =P24+R24+T24+U24+V24+W24+X24+AB24+AC24+AD24 -> 405 | AG24: =AF24*0.5 -> 202.5 | AH24: =(AF24-AG24)*$AH$1+S24 -> 6755.0349 | AI24: =IF(Q24>18519.27,0.045*18519.27,Q24*0.045) -> 404.78314 | AJ24: =(AI24*0.5)/$AQ$1 -> 7.5816 | AK24: =(AI24*0.4) -> 161.91326 | AL24: 0 | AM24: =Q24*0.003 -> 26.985543 | AN24: =IF(AD24>320,320,AD24) -> 0 | AO24: =AG24-AN24-AJ24 -> 194.9184 | AP24: =AH24-AK24-AL24-AM24-BB24 -> 6566.1361 | AQ24: =AO24+(AP24/$AQ$1) -> 440.88624 | AR24: =BT24 -> 75.22156 | AS24: 0 | AT24: =AR24-AS24 -> 75.22156 | AU24: =AT24*AE24 -> 33.255894 | AV24: =AU24*0.03 -> 0.99767682 | AW24: =(AT24-AU24)*$AQ$1 -> 1120.2776 | AX24: =AW24*0.03 -> 33.608329 | AY24: =AO24-AU24-AV24 -> 160.66483 | AZ24: =AP24-AW24-AX24 -> 5412.2501 | BA24: ='Nyaradzo Workings'!K24 -> 734.0747 | BB24: 0 | BI24: 12.5 | BL24: =AY24-BI24-BG24-BH24-BD24+BJ24 -> 148.16483 | BM24: =AZ24-BA24-BC24-BE24-BF24+BK24 -> 4678.1754 | BN24: =IF(AQ24<100,0,0) -> 0 | BO24: =IF(AQ24<100,"",IF(AQ24<=300,AQ24*0.2-20,)) -> 0 | BP24: =IF(AQ24<300.01,"",IF(AQ24<=1000,AQ24*0.25-35,)) -> 75.22156 | BQ24: =IF(AQ24<1000.01,"",IF(AQ24<=2000,AQ24*0.3-85,)) | BR24: =IF(AQ24<2000.01,"",IF(AQ24<=3000,AQ24*0.35-185,)) | BS24: =IF(AQ24<3000.01,"",IF(AQ24>3000,AQ24*0.4-335,)) | BT24: =SUM(BN24:BS24) -> 75.22156 | BU24: FBC | BV24: Zvishavane | BW24: 9921936948112 | BX24: FBC | BY24: Zvishavane | BZ24: 6739830341653 | CA24: 15.04 | CB24: 2.5 | CE24: =CA24+CB24-CC24-CD24 -> 17.54 | CF24: =M24*8 -> 12.96 | CG24: =CE24*CF24 -> 227.3184 | CH24: =CG24*0.4 -> 90.92736 | CI24: =(CG24-CH24)*$CI$2 -> 3640.9725
A25: AES-E010 | B25: Farai | C25: Dhliwayo | D25: 53-831076K72 | E25: =E24 -> 45747 | F25: Mimosa | G25: Service Assitant | H25: 4/3 | I25: 6672134A | J25: =AO25/AQ25 -> 0.4419352 | K25: =K24 -> 3/2025 | L25: 208 | M25: 1.62 | N25: 24 | P25: =L25*M25 -> 336.96 | Q25: =P25*$Q$1 -> 8995.1809 | S25: =P25*0.3*$S$1*0.5 -> 1349.2771 | T25: =N25*M25*8*0.05 -> 15.552 | U25: =O25*M25*0.1 -> 0 | W25: =Y25*M25*2 -> 25.92 | X25: =Z25*M25*1.5 -> 0 | Y25: 8 | AA25: =CD25 -> 0 | AB25: =P25*0.075 -> 25.272 | AC25: =M25*8*AA25 -> 0 | AE25: =AO25/AQ25 -> 0.4419352 | AF25: =P25+R25+T25+U25+V25+W25+X25+AB25+AC25+AD25 -> 403.704 | AG25: =AF25*0.5 -> 201.852 | AH25: =(AF25-AG25)*$AH$1+S25 -> 6737.7365 | AI25: =IF(Q25>18519.27,0.045*18519.27,Q25*0.045) -> 404.78314 | AJ25: =(AI25*0.5)/$AQ$1 -> 7.5816 | AK25: =(AI25*0.4) -> 161.91326 | AL25: 0 | AM25: =Q25*0.003 -> 26.985543 | AN25: =IF(AD25>320,320,AD25) -> 0 | AO25: =AG25-AN25-AJ25 -> 194.2704 | AP25: =AH25-AK25-AL25-AM25-BB25 -> 6548.8377 | AQ25: =AO25+(AP25/$AQ$1) -> 439.59024 | AR25: =BT25 -> 74.89756 | AS25: 0 | AT25: =AR25-AS25 -> 74.89756 | AU25: =AT25*AE25 -> 33.099868 | AV25: =AU25*0.03 -> 0.99299604 | AW25: =(AT25-AU25)*$AQ$1 -> 1115.7936 | AX25: =AW25*0.03 -> 33.473807 | AY25: =AO25-AU25-AV25 -> 160.17754 | AZ25: =AP25-AW25-AX25 -> 5399.5703 | BA25: ='Nyaradzo Workings'!K25 -> 316.4547 | BB25: 0 | BL25: =AY25-BI25-BG25-BH25-BD25+BJ25 -> 160.17754 | BM25: =AZ25-BA25-BC25-BE25-BF25+BK25 -> 5083.1156 | BN25: =IF(AQ25<100,0,0) -> 0 | BO25: =IF(AQ25<100,"",IF(AQ25<=300,AQ25*0.2-20,)) -> 0 | BP25: =IF(AQ25<300.01,"",IF(AQ25<=1000,AQ25*0.25-35,)) -> 74.89756 | BQ25: =IF(AQ25<1000.01,"",IF(AQ25<=2000,AQ25*0.3-85,)) | BR25: =IF(AQ25<2000.01,"",IF(AQ25<=3000,AQ25*0.35-185,)) | BS25: =IF(AQ25<3000.01,"",IF(AQ25>3000,AQ25*0.4-335,)) | BT25: =SUM(BN25:BS25) -> 74.89756 | BU25: FBC | BV25: Zvishavane | BW25: 4372096024310 | BX25: FBC | BY25: Zvishavane | BZ25: 7669828074599 | CA25: 23.56 | CB25: 2.5 | CE25: =CA25+CB25-CC25-CD25 -> 26.06 | CF25: =M25*8 -> 12.96 | CG25: =CE25*CF25 -> 337.7376 | CH25: =CG25*0.4 -> 135.09504 | CI25: =(CG25-CH25)*$CI$2 -> 5409.5634
A26: AES-E011 | B26: Kundai | C26: Chataika | D26: 24-745414V40 | E26: =E25 -> 45747 | F26: Mimosa | G26: Service Assitant | H26: 4/3 | I26: 2833230H | J26: =AO26/AQ26 -> 0.45953276 | K26: =K25 -> 3/2025 | L26: 208 | M26: 1.62 | N26: 25 | O26: 136 | P26: =L26*M26 -> 336.96 | Q26: =P26*$Q$1 -> 8995.1809 | S26: =P26*0.3*$S$1*0.5 -> 1349.2771 | T26: =N26*M26*8*0.05 -> 16.2 | U26: =O26*M26*0.1 -> 22.032 | W26: =Y26*M26*2 -> 0 | X26: =Z26*M26*1.5 -> 0 | AA26: =CD26 -> 15 | AB26: =P26*0.075 -> 25.272 | AC26: =M26*8*AA26 -> 194.4 | AE26: =AO26/AQ26 -> 0.45953276 | AF26: =P26+R26+T26+U26+V26+W26+X26+AB26+AC26+AD26 -> 594.864 | AG26: =AF26*0.5 -> 297.432 | AH26: =(AF26-AG26)*$AH$1+S26 -> 9289.2541 | AI26: =IF(Q26>18519.27,0.045*18519.27,Q26*0.045) -> 404.78314 | AJ26: =(AI26*0.5)/$AQ$1 -> 7.5816 | AK26: =(AI26*0.4) -> 161.91326 | AL26: 0 | AM26: =Q26*0.003 -> 26.985543 | AN26: =IF(AD26>320,320,AD26) -> 0 | AO26: =AG26-AN26-AJ26 -> 289.8504 | AP26: =AH26-AK26-AL26-AM26-BB26 -> 9100.3553 | AQ26: =AO26+(AP26/$AQ$1) -> 630.75024 | AR26: =BT26 -> 122.68756 | AS26: 0 | AT26: =AR26-AS26 -> 122.68756 | AU26: =AT26*AE26 -> 56.378953 | AV26: =AU26*0.03 -> 1.6913686 | AW26: =(AT26-AU26)*$AQ$1 -> 1770.1149 | AX26: =AW26*0.03 -> 53.103447 | AY26: =AO26-AU26-AV26 -> 231.78008 | AZ26: =AP26-AW26-AX26 -> 7277.137 | BA26: ='Nyaradzo Workings'!K26 -> 316.4547 | BB26: 0 | BL26: =AY26-BI26-BG26-BH26-BD26+BJ26 -> 231.78008 | BM26: =AZ26-BA26-BC26-BE26-BF26+BK26 -> 6960.6823 | BN26: =IF(AQ26<100,0,0) -> 0 | BO26: =IF(AQ26<100,"",IF(AQ26<=300,AQ26*0.2-20,)) -> 0 | BP26: =IF(AQ26<300.01,"",IF(AQ26<=1000,AQ26*0.25-35,)) -> 122.68756 | BQ26: =IF(AQ26<1000.01,"",IF(AQ26<=2000,AQ26*0.3-85,)) | BR26: =IF(AQ26<2000.01,"",IF(AQ26<=3000,AQ26*0.35-185,)) | BS26: =IF(AQ26<3000.01,"",IF(AQ26>3000,AQ26*0.4-335,)) | BT26: =SUM(BN26:BS26) -> 122.68756 | BU26: FBC | BV26: Zvishavane | BW26: 1007875789648 | BX26: FBC | BY26: Zvishavane | BZ26: 6047891705783 | CA26: 17.11 | CB26: 2.5 | CD26: 15 | CE26: =CA26+CB26-CC26-CD26 -> 4.61 | CF26: =M26*8 -> 12.96 | CG26: =CE26*CF26 -> 59.7456 | CH26: =CG26*0.4 -> 23.89824 | CI26: =(CG26-CH26)*$CI$2 -> 956.94886
A27: AES-E014 | B27: Mufaro | C27: Nemukuyu | D27: 28-550770V79 | E27: =E26 -> 45747 | F27: Mimosa | G27: G/ Machine Op | H27: 4/4 | I27: 2642635B | J27: =AO27/AQ27 -> 0.43829694 | K27: =K26 -> 3/2025 | L27: 208 | M27: 1.76 | N27: 24 | P27: =L27*M27 -> 366.08 | Q27: =P27*$Q$1 -> 9772.5422 | S27: =P27*0.3*$S$1*0.5 -> 1465.8813 | T27: =N27*M27*8*0.05 -> 16.896 | U27: =O27*M27*0.1 -> 0 | W27: =Y27*M27*2 -> 0 | X27: =Z27*M27*1.5 -> 0 | AA27: =CD27 -> 0 | AB27: =P27*0.075 -> 27.456 | AC27: =M27*8*AA27 -> 0 | AE27: =AO27/AQ27 -> 0.43829694 | AF27: =P27+R27+T27+U27+V27+W27+X27+AB27+AC27+AD27 -> 410.432 | AG27: =AF27*0.5 -> 205.216 | AH27: =(AF27-AG27)*$AH$1+S27 -> 6944.143 | AI27: =IF(Q27>18519.27,0.045*18519.27,Q27*0.045) -> 439.7644 | AJ27: =(AI27*0.5)/$AQ$1 -> 8.2368 | AK27: =(AI27*0.4) -> 175.90576 | AL27: 0 | AM27: =Q27*0.003 -> 29.317627 | AN27: =IF(AD27>320,320,AD27) -> 0 | AO27: =AG27-AN27-AJ27 -> 196.9792 | AP27: =AH27-AK27-AL27-AM27-BB27 -> 6738.9196 | AQ27: =AO27+(AP27/$AQ$1) -> 449.41952 | AR27: =BT27 -> 77.35488 | AS27: 0 | AT27: =AR27-AS27 -> 77.35488 | AU27: =AT27*AE27 -> 33.904407 | AV27: =AU27*0.03 -> 1.0171322 | AW27: =(AT27-AU27)*$AQ$1 -> 1159.9147 | AX27: =AW27*0.03 -> 34.797442 | AY27: =AO27-AU27-AV27 -> 162.05766 | AZ27: =AP27-AW27-AX27 -> 5544.2074 | BA27: 0 | BB27: 0 | BI27: 12.5 | BL27: =AY27-BI27-BG27-BH27-BD27+BJ27 -> 149.55766 | BM27: =AZ27-BA27-BC27-BE27-BF27+BK27 -> 5544.2074 | BN27: =IF(AQ27<100,0,0) -> 0 | BO27: =IF(AQ27<100,"",IF(AQ27<=300,AQ27*0.2-20,)) -> 0 | BP27: =IF(AQ27<300.01,"",IF(AQ27<=1000,AQ27*0.25-35,)) -> 77.35488 | BQ27: =IF(AQ27<1000.01,"",IF(AQ27<=2000,AQ27*0.3-85,)) | BR27: =IF(AQ27<2000.01,"",IF(AQ27<=3000,AQ27*0.35-185,)) | BS27: =IF(AQ27<3000.01,"",IF(AQ27>3000,AQ27*0.4-335,)) | BT27: =SUM(BN27:BS27) -> 77.35488 | BU27: FBC | BV27: Zvishavane | BW27: 6667873802666 | BX27: FBC | BY27: Zvishavane | BZ27: 8771592947529 | CA27: 0.5 | CB27: 2.5 | CE27: =CA27+CB27-CC27-CD27 -> 3 | CF27: =M27*8 -> 14.08 | CG27: =CE27*CF27 -> 42.24 | CH27: =CG27*0.4 -> 16.896 | CI27: =(CG27-CH27)*$CI$2 -> 676.56061
A28: AES-E019 | B28: Rufaro | C28: Mashingaidze | D28: 58-808446G67 | E28: =E27 -> 45747 | F28: Mimosa | G28: Service Assitant | H28: 4/3 | I28: 1247595C | J28: =AO28/AQ28 -> 0.45489936 | K28: =K27 -> 3/2025 | L28: 208 | M28: 1.62 | N28: 25 | O28: 136 | P28: =L28*M28 -> 336.96 | Q28: =P28*$Q$1 -> 8995.1809 | S28: =P28*0.3*$S$1*0.5 -> 1349.2771 | T28: =N28*M28*8*0.05 -> 16.2 | U28: =O28*M28*0.1 -> 22.032 | W28: =Y28*M28*2 -> 0 | X28: =Z28*M28*1.5 -> 0 | AA28: =CD28 -> 10 | AB28: =P28*0.075 -> 25.272 | AC28: =M28*8*AA28 -> 129.6 | AE28: =AO28/AQ28 -> 0.45489936 | AF28: =P28+R28+T28+U28+V28+W28+X28+AB28+AC28+AD28 -> 530.064 | AG28: =AF28*0.5 -> 265.032 | AH28: =(AF28-AG28)*$AH$1+S28 -> 8424.3329 | AI28: =IF(Q28>18519.27,0.045*18519.27,Q28*0.045) -> 404.78314 | AJ28: =(AI28*0.5)/$AQ$1 -> 7.5816 | AK28: =(AI28*0.4) -> 161.91326 | AL28: 0 | AM28: =Q28*0.003 -> 26.985543 | AN28: =IF(AD28>320,320,AD28) -> 0 | AO28: =AG28-AN28-AJ28 -> 257.4504 | AP28: =AH28-AK28-AL28-AM28-BB28 -> 8235.4341 | AQ28: =AO28+(AP28/$AQ$1) -> 565.95024 | AR28: =BT28 -> 106.48756 | AS28: 0 | AT28: =AR28-AS28 -> 106.48756 | AU28: =AT28*AE28 -> 48.441123 | AV28: =AU28*0.03 -> 1.4532337 | AW28: =(AT28-AU28)*$AQ$1 -> 1549.5555 | AX28: =AW28*0.03 -> 46.486664 | AY28: =AO28-AU28-AV28 -> 207.55604 | AZ28: =AP28-AW28-AX28 -> 6639.392 | BA28: ='Nyaradzo Workings'!K27 -> 316.4547 | BB28: 0 | BL28: =AY28-BI28-BG28-BH28-BD28+BJ28 -> 207.55604 | BM28: =AZ28-BA28-BC28-BE28-BF28+BK28 -> 6322.9373 | BN28: =IF(AQ28<100,0,0) -> 0 | BO28: =IF(AQ28<100,"",IF(AQ28<=300,AQ28*0.2-20,)) -> 0 | BP28: =IF(AQ28<300.01,"",IF(AQ28<=1000,AQ28*0.25-35,)) -> 106.48756 | BQ28: =IF(AQ28<1000.01,"",IF(AQ28<=2000,AQ28*0.3-85,)) | BR28: =IF(AQ28<2000.01,"",IF(AQ28<=3000,AQ28*0.35-185,)) | BS28: =IF(AQ28<3000.01,"",IF(AQ28>3000,AQ28*0.4-335,)) | BT28: =SUM(BN28:BS28) -> 106.48756 | BU28: FBC | BV28: Zvishavane | BW28: 5991116192008 | BX28: FBC | BY28: Zvishavane | BZ28: 2642117129691 | CA28: 11.84 | CB28: 2.5 | CD28: 10 | CE28: =CA28+CB28-CC28-CD28 -> 4.34 | CF28: =M28*8 -> 12.96 | CG28: =CE28*CF28 -> 56.2464 | CH28: =CG28*0.4 -> 22.49856 | CI28: =(CG28-CH28)*$CI$2 -> 900.90196
A29: AES-E017 | B29: Ropafadzo | C29: Mangwende | D29: 32-805477K30 | E29: =E28 -> 45747 | F29: Mimosa | G29: Service Assitant | H29: 4/3 | I29: 8106470P | J29: =AO29/AQ29 -> 0.437315 | K29: =K28 -> 3/2025 | L29: 208 | M29: 1.62 | N29: 14 | P29: =L29*M29 -> 336.96 | Q29: =P29*$Q$1 -> 8995.1809 | S29: =P29*0.3*$S$1*0.5 -> 1349.2771 | T29: =N29*M29*8*0.05 -> 9.072 | U29: =O29*M29*0.1 -> 0 | W29: =Y29*M29*2 -> 0 | X29: =Z29*M29*1.5 -> 0 | AA29: =CD29 -> 0 | AB29: =P29*0.075 -> 25.272 | AC29: =M29*8*AA29 -> 0 | AE29: =AO29/AQ29 -> 0.437315 | AF29: =P29+R29+T29+U29+V29+W29+X29+AB29+AC29+AD29 -> 371.304 | AG29: =AF29*0.5 -> 185.652 | AH29: =(AF29-AG29)*$AH$1+S29 -> 6305.2758 | AI29: =IF(Q29>18519.27,0.045*18519.27,Q29*0.045) -> 404.78314 | AJ29: =(AI29*0.5)/$AQ$1 -> 7.5816 | AK29: =(AI29*0.4) -> 161.91326 | AL29: 0 | AM29: =Q29*0.003 -> 26.985543 | AN29: =IF(AD29>320,320,AD29) -> 0 | AO29: =AG29-AN29-AJ29 -> 178.0704 | AP29: =AH29-AK29-AL29-AM29-BB29 -> 6116.377 | AQ29: =AO29+(AP29/$AQ$1) -> 407.19024 | AR29: =BT29 -> 66.79756 | AS29: 0 | AT29: =AR29-AS29 -> 66.79756 | AU29: =AT29*AE29 -> 29.211575 | AV29: =AU29*0.03 -> 0.87634725 | AW29: =(AT29-AU29)*$AQ$1 -> 1003.3616 | AX29: =AW29*0.03 -> 30.100849 | AY29: =AO29-AU29-AV29 -> 147.98248 | AZ29: =AP29-AW29-AX29 -> 5082.9146 | BA29: 0 | BB29: 0 | BC29: =20000/2499.9263 -> 8.0002358 | BI29: 12.5 | BL29: =AY29-BI29-BG29-BH29-BD29+BJ29 -> 135.48248 | BM29: =AZ29-BA29-BC29-BE29-BF29+BK29 -> 5074.9143 | BN29: =IF(AQ29<100,0,0) -> 0 | BO29: =IF(AQ29<100,"",IF(AQ29<=300,AQ29*0.2-20,)) -> 0 | BP29: =IF(AQ29<300.01,"",IF(AQ29<=1000,AQ29*0.25-35,)) -> 66.79756 | BQ29: =IF(AQ29<1000.01,"",IF(AQ29<=2000,AQ29*0.3-85,)) | BR29: =IF(AQ29<2000.01,"",IF(AQ29<=3000,AQ29*0.35-185,)) | BS29: =IF(AQ29<3000.01,"",IF(AQ29>3000,AQ29*0.4-335,)) | BT29: =SUM(BN29:BS29) -> 66.79756 | BU29: FBC | BV29: Zvishavane | BW29: 4503862507510 | BX29: FBC | BY29: Zvishavane | BZ29: 1430129610059 | CA29: 13.1 | CB29: 2.5 | CE29: =CA29+CB29-CC29-CD29 -> 15.6 | CF29: =M29*8 -> 12.96 | CG29: =CE29*CF29 -> 202.176 | CH29: =CG29*0.4 -> 80.8704 | CI29: =(CG29-CH29)*$CI$2 -> 3238.2651
A30: AES-E042 | B30: Vimbai | C30: Mpofu | D30: 07-356736R11 | E30: =E29 -> 45747 | F30: Mimosa | G30: UV Operator | H30: 4/4 | I30: 8231838M | J30: =AO30/AQ30 -> 0.44126518 | K30: =K29 -> 3/2025 | L30: 208 | M30: 1.76 | N30: 23 | O30: 116 | P30: =L30*M30 -> 366.08 | Q30: =P30*$Q$1 -> 9772.5422 | R30: =3 -> 3 | S30: =P30*0.3*$S$1*0.5 -> 1465.8813 | T30: =N30*M30*8*0.05 -> 16.192 | U30: =O30*M30*0.1 -> 20.416 | W30: =Y30*M30*2 -> 0 | X30: =Z30*M30*1.5 -> 0 | AA30: =CD30 -> 0 | AB30: =P30*0.075 -> 27.456 | AC30: =M30*8*AA30 -> 0 | AE30: =AO30/AQ30 -> 0.44126518 | AF30: =P30+R30+T30+U30+V30+W30+X30+AB30+AC30+AD30 -> 433.144 | AG30: =AF30*0.5 -> 216.572 | AH30: =(AF30-AG30)*$AH$1+S30 -> 7247.2925 | AI30: =IF(Q30>18519.27,0.045*18519.27,Q30*0.045) -> 439.7644 | AJ30: =(AI30*0.5)/$AQ$1 -> 8.2368 | AK30: =(AI30*0.4) -> 175.90576 | AL30: 0 | AM30: =Q30*0.003 -> 29.317627 | AN30: =IF(AD30>320,320,AD30) -> 0 | AO30: =AG30-AN30-AJ30 -> 208.3352 | AP30: =AH30-AK30-AL30-AM30-BB30 -> 7042.0691 | AQ30: =AO30+(AP30/$AQ$1) -> 472.13152 | AR30: =BT30 -> 83.03288 | AS30: 0 | AT30: =AR30-AS30 -> 83.03288 | AU30: =AT30*AE30 -> 36.639519 | AV30: =AU30*0.03 -> 1.0991856 | AW30: =(AT30-AU30)*$AQ$1 -> 1238.4754 | AX30: =AW30*0.03 -> 37.154263 | AY30: =AO30-AU30-AV30 -> 170.5965 | AZ30: =AP30-AW30-AX30 -> 5766.4395 | BA30: 0 | BB30: 0 | BD30: =70+50 -> 120 | BL30: =AY30-BI30-BG30-BH30-BD30+BJ30 -> 50.596496 | BM30: =AZ30-BA30-BC30-BE30-BF30+BK30 -> 5766.4395 | BN30: =IF(AQ30<100,0,0) -> 0 | BO30: =IF(AQ30<100,"",IF(AQ30<=300,AQ30*0.2-20,)) -> 0 | BP30: =IF(AQ30<300.01,"",IF(AQ30<=1000,AQ30*0.25-35,)) -> 83.03288 | BQ30: =IF(AQ30<1000.01,"",IF(AQ30<=2000,AQ30*0.3-85,)) | BR30: =IF(AQ30<2000.01,"",IF(AQ30<=3000,AQ30*0.35-185,)) | BS30: =IF(AQ30<3000.01,"",IF(AQ30>3000,AQ30*0.4-335,)) | BT30: =SUM(BN30:BS30) -> 83.03288 | BU30: NEDBANK | BV30: Zvishavane | BW30: 67790572388 | BX30: FBC | BY30: Zvishavane | CA30: 5.41 | CB30: 2.5 | CC30: 2 | CE30: =CA30+CB30-CC30-CD30 -> 5.91 | CF30: =M30*8 -> 14.08 | CG30: =CE30*CF30 -> 83.2128 | CH30: =CG30*0.4 -> 33.28512 | CI30: =(CG30-CH30)*$CI$2 -> 1332.8244
A31: AES-E012 | B31: Batsirai | C31: Gwenzi | D31: 75-303880Z51 | E31: =E30 -> 45747 | F31: Mimosa | G31: Service Assitant | H31: 4/3 | I31: 7818496R | J31: =AO31/AQ31 -> 0.45806809 | K31: =K30 -> 3/2025 | L31: 208 | M31: 1.62 | N31: 25 | P31: =L31*M31 -> 336.96 | Q31: =P31*$Q$1 -> 8995.1809 | S31: =P31*0.3*$S$1*0.5 -> 1349.2771 | T31: =N31*M31*8*0.05 -> 16.2 | U31: =O31*M31*0.1 -> 0 | W31: =Y31*M31*2 -> 0 | X31: =Z31*M31*1.5 -> 0 | AA31: =CD31 -> 15 | AB31: =P31*0.075 -> 25.272 | AC31: =M31*8*AA31 -> 194.4 | AE31: =AO31/AQ31 -> 0.45806809 | AF31: =P31+R31+T31+U31+V31+W31+X31+AB31+AC31+AD31 -> 572.832 | AG31: =AF31*0.5 -> 286.416 | AH31: =(AF31-AG31)*$AH$1+S31 -> 8995.1809 | AI31: =IF(Q31>18519.27,0.045*18519.27,Q31*0.045) -> 404.78314 | AJ31: =(AI31*0.5)/$AQ$1 -> 7.5816 | AK31: =(AI31*0.4) -> 161.91326 | AL31: 0 | AM31: =Q31*0.003 -> 26.985543 | AN31: =IF(AD31>320,320,AD31) -> 0 | AO31: =AG31-AN31-AJ31 -> 278.8344 | AP31: =AH31-AK31-AL31-AM31-BB31 -> 8806.2821 | AQ31: =AO31+(AP31/$AQ$1) -> 608.71824 | AR31: =BT31 -> 117.17956 | AS31: 0 | AT31: =AR31-AS31 -> 117.17956 | AU31: =AT31*AE31 -> 53.676217 | AV31: =AU31*0.03 -> 1.6102865 | AW31: =(AT31-AU31)*$AQ$1 -> 1695.2281 | AX31: =AW31*0.03 -> 50.856843 | AY31: =AO31-AU31-AV31 -> 223.5479 | AZ31: =AP31-AW31-AX31 -> 7060.1972 | BA31: ='Nyaradzo Workings'!K29 -> 170.1547 | BB31: 0 | BI31: 12.5 | BL31: =AY31-BI31-BG31-BH31-BD31+BJ31 -> 211.0479 | BM31: =AZ31-BA31-BC31-BE31-BF31+BK31 -> 6890.0425 | BN31: =IF(AQ31<100,0,0) -> 0 | BO31: =IF(AQ31<100,"",IF(AQ31<=300,AQ31*0.2-20,)) -> 0 | BP31: =IF(AQ31<300.01,"",IF(AQ31<=1000,AQ31*0.25-35,)) -> 117.17956 | BQ31: =IF(AQ31<1000.01,"",IF(AQ31<=2000,AQ31*0.3-85,)) | BR31: =IF(AQ31<2000.01,"",IF(AQ31<=3000,AQ31*0.35-185,)) | BS31: =IF(AQ31<3000.01,"",IF(AQ31>3000,AQ31*0.4-335,)) | BT31: =SUM(BN31:BS31) -> 117.17956 | BU31: FBC | BV31: Zvishavane | BW31: 8028689830037 | BX31: FBC | BY31: Zvishavane | BZ31: 3595208151988 | CA31: 30.07 | CB31: 2.5 | CD31: 15 | CE31: =CA31+CB31-CC31-CD31 -> 17.57 | CF31: =M31*8 -> 12.96 | CG31: =CE31*CF31 -> 227.7072 | CH31: =CG31*0.4 -> 91.08288 | CI31: =(CG31-CH31)*$CI$2 -> 3647.1999
A32: AES-E020 | B32: Tonderayi | C32: Nyamande | D32: 02-887443D56 | E32: =E31 -> 45747 | F32: Mimosa | G32: Service Assitant | H32: 4/3 | I32: 9164991E | J32: =AO32/AQ32 -> 0.43839344 | K32: =K31 -> 3/2025 | L32: 208 | M32: 1.62 | N32: 25 | P32: =L32*M32 -> 336.96 | Q32: =P32*$Q$1 -> 8995.1809 | S32: =P32*0.3*$S$1*0.5 -> 1349.2771 | T32: =N32*M32*8*0.05 -> 16.2 | U32: =O32*M32*0.1 -> 0 | W32: =Y32*M32*2 -> 0 | X32: =Z32*M32*1.5 -> 0 | AA32: =CD32 -> 0 | AB32: =P32*0.075 -> 25.272 | AC32: =M32*8*AA32 -> 0 | AE32: =AO32/AQ32 -> 0.43839344 | AF32: =P32+R32+T32+U32+V32+W32+X32+AB32+AC32+AD32 -> 378.432 | AG32: =AF32*0.5 -> 189.216 | AH32: =(AF32-AG32)*$AH$1+S32 -> 6400.4172 | AI32: =IF(Q32>18519.27,0.045*18519.27,Q32*0.045) -> 404.78314 | AJ32: =(AI32*0.5)/$AQ$1 -> 7.5816 | AK32: =(AI32*0.4) -> 161.91326 | AL32: 0 | AM32: =Q32*0.003 -> 26.985543 | AN32: 0 | AO32: =AG32-AN32-AJ32 -> 181.6344 | AP32: =AH32-AK32-AL32-AM32-BB32 -> 6211.5184 | AQ32: =AO32+(AP32/$AQ$1) -> 414.31824 | AR32: =BT32 -> 68.57956 | AS32: 0 | AT32: =AR32-AS32 -> 68.57956 | AU32: =AT32*AE32 -> 30.064829 | AV32: =AU32*0.03 -> 0.90194488 | AW32: =(AT32-AU32)*$AQ$1 -> 1028.1546 | AX32: =AW32*0.03 -> 30.844637 | AY32: =AO32-AU32-AV32 -> 150.66763 | AZ32: =AP32-AW32-AX32 -> 5152.5192 | BA32: 0 | BB32: 0 | BL32: =AY32-BI32-BG32-BH32-BD32+BJ32 -> 150.66763 | BM32: =AZ32-BA32-BC32-BE32-BF32+BK32 -> 5152.5192 | BN32: =IF(AQ32<100,0,0) -> 0 | BO32: =IF(AQ32<100,"",IF(AQ32<=300,AQ32*0.2-20,)) -> 0 | BP32: =IF(AQ32<300.01,"",IF(AQ32<=1000,AQ32*0.25-35,)) -> 68.57956 | BQ32: =IF(AQ32<1000.01,"",IF(AQ32<=2000,AQ32*0.3-85,)) | BR32: =IF(AQ32<2000.01,"",IF(AQ32<=3000,AQ32*0.35-185,)) | BS32: =IF(AQ32<3000.01,"",IF(AQ32>3000,AQ32*0.4-335,)) | BT32: =SUM(BN32:BS32) -> 68.57956 | BU32: FBC | BV32: Zvishavane | BW32: 4093316368647 | BX32: FBC | BY32: Zvishavane | BZ32: 1882463522262 | CA32: 28.7 | CB32: 2.5 | CE32: =CA32+CB32-CC32-CD32 -> 31.2 | CF32: =M32*8 -> 12.96 | CG32: =CE32*CF32 -> 404.352 | CH32: =CG32*0.4 -> 161.7408 | CI32: =(CG32-CH32)*$CI$2 -> 6476.5302
A33: AES-E021 | B33: Kudzai | C33: Ziyambi | D33: 73-361303D60 | E33: =E32 -> 45747 | F33: Mimosa | G33: Service Assitant | H33: 4/3 | I33: 5785687P | J33: =AO33/AQ33 -> 0.45301653 | K33: =K32 -> 3/2025 | L33: 208 | M33: 1.62 | N33: 24 | P33: =L33*M33 -> 336.96 | Q33: =P33*$Q$1 -> 8995.1809 | S33: =P33*0.3*$S$1*0.5 -> 1349.2771 | T33: =N33*M33*8*0.05 -> 15.552 | U33: =O33*M33*0.1 -> 0 | W33: =Y33*M33*2 -> 0 | X33: =Z33*M33*1.5 -> 0 | AA33: =CD33 -> 10 | AB33: =P33*0.075 -> 25.272 | AC33: =M33*8*AA33 -> 129.6 | AE33: =AO33/AQ33 -> 0.45301653 | AF33: =P33+R33+T33+U33+V33+W33+X33+AB33+AC33+AD33 -> 507.384 | AG33: =AF33*0.5 -> 253.692 | AH33: =(AF33-AG33)*$AH$1+S33 -> 8121.6104 | AI33: =IF(Q33>18519.27,0.045*18519.27,Q33*0.045) -> 404.78314 | AJ33: =(AI33*0.5)/$AQ$1 -> 7.5816 | AK33: =(AI33*0.4) -> 161.91326 | AL33: 0 | AM33: =Q33*0.003 -> 26.985543 | AN33: 0 | AO33: =AG33-AN33-AJ33 -> 246.1104 | AP33: =AH33-AK33-AL33-AM33-BB33 -> 7932.7116 | AQ33: =AO33+(AP33/$AQ$1) -> 543.27024 | AR33: =BT33 -> 100.81756 | AS33: 0 | AT33: =AR33-AS33 -> 100.81756 | AU33: =AT33*AE33 -> 45.672021 | AV33: =AU33*0.03 -> 1.3701606 | AW33: =(AT33-AU33)*$AQ$1 -> 1472.1157 | AX33: =AW33*0.03 -> 44.16347 | AY33: =AO33-AU33-AV33 -> 199.06822 | AZ33: =AP33-AW33-AX33 -> 6416.4325 | BA33: 0 | BB33: 0 | BI33: 12.5 | BL33: =AY33-BI33-BG33-BH33-BD33+BJ33 -> 186.56822 | BM33: =AZ33-BA33-BC33-BE33-BF33+BK33 -> 6416.4325 | BN33: =IF(AQ33<100,0,0) -> 0 | BO33: =IF(AQ33<100,"",IF(AQ33<=300,AQ33*0.2-20,)) -> 0 | BP33: =IF(AQ33<300.01,"",IF(AQ33<=1000,AQ33*0.25-35,)) -> 100.81756 | BQ33: =IF(AQ33<1000.01,"",IF(AQ33<=2000,AQ33*0.3-85,)) | BR33: =IF(AQ33<2000.01,"",IF(AQ33<=3000,AQ33*0.35-185,)) | BS33: =IF(AQ33<3000.01,"",IF(AQ33>3000,AQ33*0.4-335,)) | BT33: =SUM(BN33:BS33) -> 100.81756 | BU33: FBC | BV33: Zvishavane | BW33: 9881528598830 | BX33: FBC | BY33: Zvishavane | BZ33: 9353116515888 | CA33: 32.38 | CB33: 2.5 | CD33: 10 | CE33: =CA33+CB33-CC33-CD33 -> 24.88 | CF33: =M33*8 -> 12.96 | CG33: =CE33*CF33 -> 322.4448 | CH33: =CG33*0.4 -> 128.97792 | CI33: =(CG33-CH33)*$CI$2 -> 5164.6177
A34: AES-E027 | B34: Munashe | C34: Makoni | D34: 59-371782H37 | E34: =E33 -> 45747 | F34: Mimosa | G34: Service Assitant | H34: 4/3 | I34: 5449368Q | J34: =AO34/AQ34 -> 0.43829694 | K34: =K33 -> 3/2025 | L34: 208 | M34: 1.62 | N34: 24 | P34: =L34*M34 -> 336.96 | Q34: =P34*$Q$1 -> 8995.1809 | S34: =P34*0.3*$S$1*0.5 -> 1349.2771 | T34: =N34*M34*8*0.05 -> 15.552 | U34: =O34*M34*0.1 -> 0 | W34: =Y34*M34*2 -> 0 | X34: =Z34*M34*1.5 -> 0 | AA34: =CD34 -> 0 | AB34: =P34*0.075 -> 25.272 | AC34: =M34*8*AA34 -> 0 | AE34: =AO34/AQ34 -> 0.43829694 | AF34: =P34+R34+T34+U34+V34+W34+X34+AB34+AC34+AD34 -> 377.784 | AG34: =AF34*0.5 -> 188.892 | AH34: =(AF34-AG34)*$AH$1+S34 -> 6391.768 | AI34: =IF(Q34>18519.27,0.045*18519.27,Q34*0.045) -> 404.78314 | AJ34: =(AI34*0.5)/$AQ$1 -> 7.5816 | AK34: =(AI34*0.4) -> 161.91326 | AL34: 0 | AM34: =Q34*0.003 -> 26.985543 | AN34: 0 | AO34: =AG34-AN34-AJ34 -> 181.3104 | AP34: =AH34-AK34-AL34-AM34-BB34 -> 6202.8692 | AQ34: =AO34+(AP34/$AQ$1) -> 413.67024 | AR34: =BT34 -> 68.41756 | AS34: 0 | AT34: =AR34-AS34 -> 68.41756 | AU34: =AT34*AE34 -> 29.987207 | AV34: =AU34*0.03 -> 0.89961621 | AW34: =(AT34-AU34)*$AQ$1 -> 1025.9021 | AX34: =AW34*0.03 -> 30.777063 | AY34: =AO34-AU34-AV34 -> 150.42358 | AZ34: =AP34-AW34-AX34 -> 5146.19 | BB34: 0 | BI34: 12.5 | BL34: =AY34-BI34-BG34-BH34-BD34+BJ34 -> 137.92358 | BM34: =AZ34-BA34-BC34-BE34-BF34+BK34 -> 5146.19 | BN34: =IF(AQ34<100,0,0) -> 0 | BO34: =IF(AQ34<100,"",IF(AQ34<=300,AQ34*0.2-20,)) -> 0 | BP34: =IF(AQ34<300.01,"",IF(AQ34<=1000,AQ34*0.25-35,)) -> 68.41756 | BQ34: =IF(AQ34<1000.01,"",IF(AQ34<=2000,AQ34*0.3-85,)) | BR34: =IF(AQ34<2000.01,"",IF(AQ34<=3000,AQ34*0.35-185,)) | BS34: =IF(AQ34<3000.01,"",IF(AQ34>3000,AQ34*0.4-335,)) | BT34: =SUM(BN34:BS34) -> 68.41756 | BU34: FBC | BV34: VIRTUAL | BW34: 9523454080915 | BX34: FBC | BY34: Zvishavane | BZ34: 5207464846825 | CA34: 12.5 | CB34: 2.5 | CC34: 1 | CE34: =CA34+CB34-CC34-CD34 -> 14 | CF34: =M34*8 -> 12.96 | CG34: =CE34*CF34 -> 181.44 | CH34: =CG34*0.4 -> 72.576 | CI34: =(CG34-CH34)*$CI$2 -> 2906.1354
A35: AES-E029 | B35: Kudzai | C35: Mutsvairo | D35: 37-561239C38 | E35: =E34 -> 45747 | F35: Mimosa | G35: Service Assitant | H35: 4/3 | I35: TBA | J35: =AO35/AQ35 -> 0.43820013 | K35: =K34 -> 3/2025 | L35: 208 | M35: 1.62 | N35: 23 | P35: =L35*M35 -> 336.96 | Q35: =P35*$Q$1 -> 8995.1809 | S35: =P35*0.3*$S$1*0.5 -> 1349.2771 | T35: =N35*M35*8*0.05 -> 14.904 | U35: =O35*M35*0.1 -> 0 | W35: =Y35*M35*2 -> 0 | X35: =Z35*M35*1.5 -> 0 | AA35: =CD35 -> 0 | AB35: =P35*0.075 -> 25.272 | AC35: =M35*8*AA35 -> 0 | AE35: =AO35/AQ35 -> 0.43820013 | AF35: =P35+R35+T35+U35+V35+W35+X35+AB35+AC35+AD35 -> 377.136 | AG35: =AF35*0.5 -> 188.568 | AH35: =(AF35-AG35)*$AH$1+S35 -> 6383.1188 | AI35: =IF(Q35>18519.27,0.045*18519.27,Q35*0.045) -> 404.78314 | AJ35: =(AI35*0.5)/$AQ$1 -> 7.5816 | AK35: =(AI35*0.4) -> 161.91326 | AM35: =Q35*0.003 -> 26.985543 | AN35: 0 | AO35: =AG35-AN35-AJ35 -> 180.9864 | AP35: =AH35-AK35-AL35-AM35-BB35 -> 6194.22 | AQ35: =AO35+(AP35/$AQ$1) -> 413.02224 | AR35: =BT35 -> 68.25556 | AS35: 0 | AT35: =AR35-AS35 -> 68.25556 | AU35: =AT35*AE35 -> 29.909595 | AV35: =AU35*0.03 -> 0.89728786 | AW35: =(AT35-AU35)*$AQ$1 -> 1023.6494 | AX35: =AW35*0.03 -> 30.709481 | AY35: =AO35-AU35-AV35 -> 150.17952 | AZ35: =AP35-AW35-AX35 -> 5139.8611 | BB35: 0 | BI35: 12.5 | BL35: =AY35-BI35-BG35-BH35-BD35+BJ35 -> 137.67952 | BM35: =AZ35-BA35-BC35-BE35-BF35+BK35 -> 5139.8611 | BN35: =IF(AQ35<100,0,0) -> 0 | BO35: =IF(AQ35<100,"",IF(AQ35<=300,AQ35*0.2-20,)) -> 0 | BP35: =IF(AQ35<300.01,"",IF(AQ35<=1000,AQ35*0.25-35,)) -> 68.25556 | BQ35: =IF(AQ35<1000.01,"",IF(AQ35<=2000,AQ35*0.3-85,)) | BR35: =IF(AQ35<2000.01,"",IF(AQ35<=3000,AQ35*0.35-185,)) | BS35: =IF(AQ35<3000.01,"",IF(AQ35>3000,AQ35*0.4-335,)) | BT35: =SUM(BN35:BS35) -> 68.25556 | BU35: FBC | BV35: VIRTUAL | BW35: 5777010775412 | BX35: FBC | BY35: Zvishavane | BZ35: 6623554644664 | CA35: 14 | CB35: 2.5 | CE35: =CA35+CB35-CC35-CD35 -> 16.5 | CF35: =M35*8 -> 12.96 | CG35: =CE35*CF35 -> 213.84 | CH35: =CG35*0.4 -> 85.536 | CI35: =(CG35-CH35)*$CI$2 -> 3425.0881
A36: AES-E028 | B36: Tsitsi | C36: Chibanda | D36: 71-184491E21 | E36: =E35 -> 45747 | F36: Mimosa | G36: Service Assitant | H36: 4/3 | I36: TBA | J36: =AO36/AQ36 -> 0.43439155 | K36: =K35 -> 3/2025 | L36: 208 | M36: 1.62 | N36: 25 | P36: =L36*M36 -> 336.96 | Q36: =P36*$Q$1 -> 8995.1809 | S36: =P36*0.3*$S$1*0.5 -> 1349.2771 | T36: =N36*M36*8*0.05 -> 16.2 | U36: =O36*M36*0.1 -> 0 | W36: =Y36*M36*2 -> 0 | X36: =Z36*M36*1.5 -> 0 | AA36: =CD36 -> 0 | AB36: 0 | AC36: =M36*8*AA36 -> 0 | AE36: =AO36/AQ36 -> 0.43439155 | AF36: =P36+R36+T36+U36+V36+W36+X36+AB36+AC36+AD36 -> 353.16 | AG36: =AF36*0.5 -> 176.58 | AH36: =(AF36-AG36)*$AH$1+S36 -> 6063.0979 | AI36: =IF(Q36>18519.27,0.045*18519.27,Q36*0.045) -> 404.78314 | AJ36: =(AI36*0.5)/$AQ$1 -> 7.5816 | AK36: =(AI36*0.4) -> 161.91326 | AM36: =Q36*0.003 -> 26.985543 | AN36: 0 | AO36: =AG36-AN36-AJ36 -> 168.9984 | AP36: =AH36-AK36-AL36-AM36-BB36 -> 5874.1991 | AQ36: =AO36+(AP36/$AQ$1) -> 389.04624 | AR36: =BT36 -> 62.26156 | AS36: 0 | AT36: =AR36-AS36 -> 62.26156 | AU36: =AT36*AE36 -> 27.045896 | AV36: =AU36*0.03 -> 0.81137687 | AW36: =(AT36-AU36)*$AQ$1 -> 940.08568 | AX36: =AW36*0.03 -> 28.20257 | AY36: =AO36-AU36-AV36 -> 141.14113 | AZ36: =AP36-AW36-AX36 -> 4905.9108 | BB36: 0 | BI36: 12.5 | BL36: =AY36-BI36-BG36-BH36-BD36+BJ36 -> 128.64113 | BM36: =AZ36-BA36-BC36-BE36-BF36+BK36 -> 4905.9108 | BN36: =IF(AQ36<100,0,0) -> 0 | BO36: =IF(AQ36<100,"",IF(AQ36<=300,AQ36*0.2-20,)) -> 0 | BP36: =IF(AQ36<300.01,"",IF(AQ36<=1000,AQ36*0.25-35,)) -> 62.26156 | BQ36: =IF(AQ36<1000.01,"",IF(AQ36<=2000,AQ36*0.3-85,)) | BR36: =IF(AQ36<2000.01,"",IF(AQ36<=3000,AQ36*0.35-185,)) | BS36: =IF(AQ36<3000.01,"",IF(AQ36>3000,AQ36*0.4-335,)) | BT36: =SUM(BN36:BS36) -> 62.26156 | BU36: FBC | BV36: VIRTUAL | BW36: 7735501980632 | BX36: FBC | BY36: VIRTUAL | BZ36: 3687335051761 | CA36: 0 | CB36: 2.5 | CE36: =CA36+CB36-CC36-CD36 -> 2.5 | CF36: =M36*8 -> 12.96 | CG36: =CE36*CF36 -> 32.4 | CH36: =CG36*0.4 -> 12.96 | CI36: =(CG36-CH36)*$CI$2 -> 518.95274
A37: AES-E030 | B37: Tichaona | C37: Bere | E37: =E36 -> 45747 | F37: Mimosa | G37: Service Assitant | H37: 4/3 | I37: TBA | J37: =AO37/AQ37 -> 0.45307251 | K37: =K36 -> 3/2025 | L37: 208 | M37: 1.62 | N37: 25 | P37: =L37*M37 -> 336.96 | Q37: =P37*$Q$1 -> 8995.1809 | S37: =P37*0.3*$S$1*0.5 -> 1349.2771 | T37: =N37*M37*8*0.05 -> 16.2 | U37: =O37*M37*0.1 -> 0 | W37: =Y37*M37*2 -> 0 | X37: =Z37*M37*1.5 -> 0 | AA37: =CD37 -> 10 | AB37: =P37*0.075 -> 25.272 | AC37: =M37*8*AA37 -> 129.6 | AE37: =AO37/AQ37 -> 0.45307251 | AF37: =P37+R37+T37+U37+V37+W37+X37+AB37+AC37+AD37 -> 508.032 | AG37: =AF37*0.5 -> 254.016 | AH37: =(AF37-AG37)*$AH$1+S37 -> 8130.2597 | AI37: =IF(Q37>18519.27,0.045*18519.27,Q37*0.045) -> 404.78314 | AJ37: =(AI37*0.5)/$AQ$1 -> 7.5816 | AK37: =(AI37*0.4) -> 161.91326 | AM37: =Q37*0.003 -> 26.985543 | AN37: 0 | AO37: =AG37-AN37-AJ37 -> 246.4344 | AP37: =AH37-AK37-AL37-AM37-BB37 -> 7941.3609 | AQ37: =AO37+(AP37/$AQ$1) -> 543.91824 | AR37: =BT37 -> 100.97956 | AS37: 0 | AT37: =AR37-AS37 -> 100.97956 | AU37: =AT37*AE37 -> 45.751062 | AV37: =AU37*0.03 -> 1.3725319 | AW37: =(AT37-AU37)*$AQ$1 -> 1474.3303 | AX37: =AW37*0.03 -> 44.229908 | AY37: =AO37-AU37-AV37 -> 199.31081 | AZ37: =AP37-AW37-AX37 -> 6422.8007 | BB37: 0 | BI37: 12.5 | BL37: =AY37-BI37-BG37-BH37-BD37+BJ37 -> 186.81081 | BM37: =AZ37-BA37-BC37-BE37-BF37+BK37 -> 6422.8007 | BN37: =IF(AQ37<100,0,0) -> 0 | BO37: =IF(AQ37<100,"",IF(AQ37<=300,AQ37*0.2-20,)) -> 0 | BP37: =IF(AQ37<300.01,"",IF(AQ37<=1000,AQ37*0.25-35,)) -> 100.97956 | BQ37: =IF(AQ37<1000.01,"",IF(AQ37<=2000,AQ37*0.3-85,)) | BR37: =IF(AQ37<2000.01,"",IF(AQ37<=3000,AQ37*0.35-185,)) | BS37: =IF(AQ37<3000.01,"",IF(AQ37>3000,AQ37*0.4-335,)) | BT37: =SUM(BN37:BS37) -> 100.97956 | BU37: FBC | BV37: VIRTUAL | BW37: 4765425398414 | BX37: FBC | BY37: VIRTUAL | BZ37: 8297425296721 | CA37: 10.92 | CB37: 1.82 | CD37: 10 | CE37: =CA37+CB37-CC37-CD37 -> 2.74 | CF37: =M37*8 -> 12.96 | CG37: =CE37*CF37 -> 35.5104 | CH37: =CG37*0.4 -> 14.20416 | CI37: =(CG37-CH37)*$CI$2 -> 568.77221
A38: AES-E031 | B38: Nyarai | C38: Chikomo | E38: =E37 -> 45747 | F38: Mimosa | G38: Service Assitant | H38: 4/3 | I38: TBA | J38: =AO38/AQ38 -> 0.43839344 | K38: =K37 -> 3/2025 | L38: 208 | M38: 1.62 | N38: 25 | P38: =L38*M38 -> 336.96 | Q38: =P38*$Q$1 -> 8995.1809 | S38: =P38*0.3*$S$1*0.5 -> 1349.2771 | T38: =N38*M38*8*0.05 -> 16.2 | U38: =O38*M38*0.1 -> 0 | W38: =Y38*M38*2 -> 0 | X38: =Z38*M38*1.5 -> 0 | AA38: =CD38 -> 0 | AB38: =P38*0.075 -> 25.272 | AC38: =M38*8*AA38 -> 0 | AE38: =AO38/AQ38 -> 0.43839344 | AF38: =P38+R38+T38+U38+V38+W38+X38+AB38+AC38+AD38 -> 378.432 | AG38: =AF38*0.5 -> 189.216 | AH38: =(AF38-AG38)*$AH$1+S38 -> 6400.4172 | AI38: =IF(Q38>18519.27,0.045*18519.27,Q38*0.045) -> 404.78314 | AJ38: =(AI38*0.5)/$AQ$1 -> 7.5816 | AK38: =(AI38*0.4) -> 161.91326 | AM38: =Q38*0.003 -> 26.985543 | AN38: 0 | AO38: =AG38-AN38-AJ38 -> 181.6344 | AP38: =AH38-AK38-AL38-AM38-BB38 -> 6211.5184 | AQ38: =AO38+(AP38/$AQ$1) -> 414.31824 | AR38: =BT38 -> 68.57956 | AS38: 0 | AT38: =AR38-AS38 -> 68.57956 | AU38: =AT38*AE38 -> 30.064829 | AV38: =AU38*0.03 -> 0.90194488 | AW38: =(AT38-AU38)*$AQ$1 -> 1028.1546 | AX38: =AW38*0.03 -> 30.844637 | AY38: =AO38-AU38-AV38 -> 150.66763 | AZ38: =AP38-AW38-AX38 -> 5152.5192 | BB38: 0 | BI38: 12.5 | BL38: =AY38-BI38-BG38-BH38-BD38+BJ38 -> 138.16763 | BM38: =AZ38-BA38-BC38-BE38-BF38+BK38 -> 5152.5192 | BN38: =IF(AQ38<100,0,0) -> 0 | BO38: =IF(AQ38<100,"",IF(AQ38<=300,AQ38*0.2-20,)) -> 0 | BP38: =IF(AQ38<300.01,"",IF(AQ38<=1000,AQ38*0.25-35,)) -> 68.57956 | BQ38: =IF(AQ38<1000.01,"",IF(AQ38<=2000,AQ38*0.3-85,)) | BR38: =IF(AQ38<2000.01,"",IF(AQ38<=3000,AQ38*0.35-185,)) | BS38: =IF(AQ38<3000.01,"",IF(AQ38>3000,AQ38*0.4-335,)) | BT38: =SUM(BN38:BS38) -> 68.57956 | BU38: FBC | BV38: VIRTUAL | BW38: 6821431312058 | BX38: FBC | BY38: VIRTUAL | BZ38: 9197128097883 | CA38: 7.5 | CB38: 2.5 | CE38: =CA38+CB38-CC38-CD38 -> 10 | CF38: =M38*8 -> 12.96 | CG38: =CE38*CF38 -> 129.6 | CH38: =CG38*0.4 -> 51.84 | CI38: =(CG38-CH38)*$CI$2 -> 2075.811
A39: AES-E023 | B39: Tawanda | C39: Svosve | E39: =E38 -> 45747 | F39: Mimosa | G39: Service Assitant | H39: 4/3 | I39: TBA | J39: =AO39/AQ39 -> 0.43943541 | K39: =K38 -> 3/2025 | L39: 208 | M39: 1.62 | N39: 25 | P39: =L39*M39 -> 336.96 | Q39: =P39*$Q$1 -> 8995.1809 | S39: =P39*0.3*$S$1*0.5 -> 1349.2771 | T39: =N39*M39*8*0.05 -> 16.2 | U39: =O39*M39*0.1 -> 0 | W39: =Y39*M39*2 -> 0 | X39: =Z39*M39*1.5 -> 0 | AA39: =CD39 -> 2.5 | AC39: =M39*8*AA39 -> 32.4 | AE39: =AO39/AQ39 -> 0.43943541 | AF39: =P39+R39+T39+U39+V39+W39+X39+AB39+AC39+AD39 -> 385.56 | AG39: =AF39*0.5 -> 192.78 | AH39: =(AF39-AG39)*$AH$1+S39 -> 6495.5585 | AI39: =IF(Q39>18519.27,0.045*18519.27,Q39*0.045) -> 404.78314 | AJ39: =(AI39*0.5)/$AQ$1 -> 7.5816 | AK39: =(AI39*0.4) -> 161.91326 | AM39: =Q39*0.003 -> 26.985543 | AN39: 0 | AO39: =AG39-AN39-AJ39 -> 185.1984 | AP39: =AH39-AK39-AL39-AM39-BB39 -> 6306.6597 | AQ39: =AO39+(AP39/$AQ$1) -> 421.44624 | AR39: =BT39 -> 70.36156 | AS39: 0 | AT39: =AR39-AS39 -> 70.36156 | AU39: =AT39*AE39 -> 30.919361 | AV39: =AU39*0.03 -> 0.92758082 | AW39: =(AT39-AU39)*$AQ$1 -> 1052.9135 | AX39: =AW39*0.03 -> 31.587404 | AY39: =AO39-AU39-AV39 -> 153.35146 | AZ39: =AP39-AW39-AX39 -> 5222.1589 | BB39: 0 | BL39: =AY39-BI39-BG39-BH39-BD39+BJ39 -> 153.35146 | BM39: =AZ39-BA39-BC39-BE39-BF39+BK39 -> 5222.1589 | BN39: =IF(AQ39<100,0,0) -> 0 | BO39: =IF(AQ39<100,"",IF(AQ39<=300,AQ39*0.2-20,)) -> 0 | BP39: =IF(AQ39<300.01,"",IF(AQ39<=1000,AQ39*0.25-35,)) -> 70.36156 | BQ39: =IF(AQ39<1000.01,"",IF(AQ39<=2000,AQ39*0.3-85,)) | BR39: =IF(AQ39<2000.01,"",IF(AQ39<=3000,AQ39*0.35-185,)) | BS39: =IF(AQ39<3000.01,"",IF(AQ39>3000,AQ39*0.4-335,)) | BT39: =SUM(BN39:BS39) -> 70.36156 | BU39: FBC | BV39: Zvishavane | BW39: 2097002397231 | BX39: FBC | BY39: Zvishavane | BZ39: 7852277339807 | CA39: 0 | CB39: 2.5 | CD39: 2.5 | CE39: =CA39+CB39-CC39-CD39 -> 0 | CF39: =M39*8 -> 12.96 | CG39: =CE39*CF39 -> 0 | CH39: =CG39*0.4 -> 0 | CI39: =(CG39-CH39)*$CI$2 -> 0
A40: AES-E024 | B40: Gamuchirai | C40: Mukanya | E40: =E39 -> 45747 | F40: Mimosa | G40: Service Assitant | H40: 4/3 | I40: TBA | J40: =AO40/AQ40 -> 0.43943541 | K40: =K39 -> 3/2025 | L40: 208 | M40: 1.62 | N40: 25 | P40: =L40*M40 -> 336.96 | Q40: =P40*$Q$1 -> 8995.1809 | S40: =P40*0.3*$S$1*0.5 -> 1349.2771 | T40: =N40*M40*8*0.05 -> 16.2 | U40: =O40*M40*0.1 -> 0 | W40: =Y40*M40*2 -> 0 | X40: =Z40*M40*1.5 -> 0 | AA40: =CD40 -> 2.5 | AC40: =M40*8*AA40 -> 32.4 | AE40: =AO40/AQ40 -> 0.43943541 | AF40: =P40+R40+T40+U40+V40+W40+X40+AB40+AC40+AD40 -> 385.56 | AG40: =AF40*0.5 -> 192.78 | AH40: =(AF40-AG40)*$AH$1+S40 -> 6495.5585 | AI40: =IF(Q40>18519.27,0.045*18519.27,Q40*0.045) -> 404.78314 | AJ40: =(AI40*0.5)/$AQ$1 -> 7.5816 | AK40: =(AI40*0.4) -> 161.91326 | AM40: =Q40*0.003 -> 26.985543 | AN40: 0 | AO40: =AG40-AN40-AJ40 -> 185.1984 | AP40: =AH40-AK40-AL40-AM40-BB40 -> 6306.6597 | AQ40: =AO40+(AP40/$AQ$1) -> 421.44624 | AR40: =BT40 -> 70.36156 | AS40: 0 | AT40: =AR40-AS40 -> 70.36156 | AU40: =AT40*AE40 -> 30.919361 | AV40: =AU40*0.03 -> 0.92758082 | AW40: =(AT40-AU40)*$AQ$1 -> 1052.9135 | AX40: =AW40*0.03 -> 31.587404 | AY40: =AO40-AU40-AV40 -> 153.35146 | AZ40: =AP40-AW40-AX40 -> 5222.1589 | BB40: 0 | BL40: =AY40-BI40-BG40-BH40-BD40+BJ40 -> 153.35146 | BM40: =AZ40-BA40-BC40-BE40-BF40+BK40 -> 5222.1589 | BN40: =IF(AQ40<100,0,0) -> 0 | BO40: =IF(AQ40<100,"",IF(AQ40<=300,AQ40*0.2-20,)) -> 0 | BP40: =IF(AQ40<300.01,"",IF(AQ40<=1000,AQ40*0.25-35,)) -> 70.36156 | BQ40: =IF(AQ40<1000.01,"",IF(AQ40<=2000,AQ40*0.3-85,)) | BR40: =IF(AQ40<2000.01,"",IF(AQ40<=3000,AQ40*0.35-185,)) | BS40: =IF(AQ40<3000.01,"",IF(AQ40>3000,AQ40*0.4-335,)) | BT40: =SUM(BN40:BS40) -> 70.36156 | BU40: FBC | BV40: VIRTUAL | BW40: 1346584632174 | BX40: FBC | BY40: VIRTUAL | BZ40: 9389704853172 | CA40: 0 | CB40: 2.5 | CD40: 2.5 | CE40: =CA40+CB40-CC40-CD40 -> 0 | CF40: =M40*8 -> 12.96 | CG40: =CE40*CF40 -> 0 | CH40: =CG40*0.4 -> 0 | CI40: =(CG40-CH40)*$CI$2 -> 0
A41: AES-E025 | B41: Rutendo | C41: Mhike | E41: =E40 -> 45747 | F41: Mimosa | G41: Service Assitant | H41: 4/3 | I41: TBA | J41: =AO41/AQ41 -> 0.43961738 | K41: =K40 -> 3/2025 | L41: 200 | M41: 1.62 | N41: 24 | P41: =L41*M41 -> 324 | Q41: =P41*$Q$1 -> 8649.2124 | S41: =P41*0.3*$S$1*0.5 -> 1297.3819 | T41: =N41*M41*8*0.05 -> 15.552 | U41: =O41*M41*0.1 -> 0 | W41: =Y41*M41*2 -> 0 | X41: =Z41*M41*1.5 -> 0 | AA41: =CD41 -> 2.5 | AC41: =M41*8*AA41 -> 32.4 | AE41: =AO41/AQ41 -> 0.43961738 | AF41: =P41+R41+T41+U41+V41+W41+X41+AB41+AC41+AD41 -> 371.952 | AG41: =AF41*0.5 -> 185.976 | AH41: =(AF41-AG41)*$AH$1+S41 -> 6262.0298 | AI41: =IF(Q41>18519.27,0.045*18519.27,Q41*0.045) -> 389.21456 | AJ41: =(AI41*0.5)/$AQ$1 -> 7.29 | AK41: =(AI41*0.4) -> 155.68582 | AM41: =Q41*0.003 -> 25.947637 | AN41: 0 | AO41: =AG41-AN41-AJ41 -> 178.686 | AP41: =AH41-AK41-AL41-AM41-BB41 -> 6080.3963 | AQ41: =AO41+(AP41/$AQ$1) -> 406.458 | AR41: =BT41 -> 66.6145 | AS41: 0 | AT41: =AR41-AS41 -> 66.6145 | AU41: =AT41*AE41 -> 29.284892 | AV41: =AU41*0.03 -> 0.87854675 | AW41: =(AT41-AU41)*$AQ$1 -> 996.51762 | AX41: =AW41*0.03 -> 29.895529 | AY41: =AO41-AU41-AV41 -> 148.52256 | AZ41: =AP41-AW41-AX41 -> 5053.9832 | BB41: 0 | BI41: 12.5 | BL41: =AY41-BI41-BG41-BH41-BD41+BJ41 -> 136.02256 | BM41: =AZ41-BA41-BC41-BE41-BF41+BK41 -> 5053.9832 | BN41: =IF(AQ41<100,0,0) -> 0 | BO41: =IF(AQ41<100,"",IF(AQ41<=300,AQ41*0.2-20,)) -> 0 | BP41: =IF(AQ41<300.01,"",IF(AQ41<=1000,AQ41*0.25-35,)) -> 66.6145 | BQ41: =IF(AQ41<1000.01,"",IF(AQ41<=2000,AQ41*0.3-85,)) | BR41: =IF(AQ41<2000.01,"",IF(AQ41<=3000,AQ41*0.35-185,)) | BS41: =IF(AQ41<3000.01,"",IF(AQ41>3000,AQ41*0.4-335,)) | BT41: =SUM(BN41:BS41) -> 66.6145 | BU41: FBC | BV41: Zvishavane | BW41: 6254255795580 | BX41: FBC | BY41: Zvishavane | BZ41: 7862298922749 | CA41: 0 | CB41: 2.5 | CD41: 2.5 | CE41: =CA41+CB41-CC41-CD41 -> 0 | CF41: =M41*8 -> 12.96 | CG41: =CE41*CF41 -> 0 | CH41: =CG41*0.4 -> 0 | CI41: =(CG41-CH41)*$CI$2 -> 0
A42: AES-E026 | B42: Brighton | C42: Chinamasa2Z | E42: =E41 -> 45747 | F42: Mimosa | G42: Service Assitant | H42: 4/3 | I42: TBA | J42: =AO42/AQ42 -> 0.44260639 | K42: =K41 -> 3/2025 | L42: 120 | M42: 1.62 | N42: 14 | P42: =L42*M42 -> 194.4 | Q42: =P42*$Q$1 -> 5189.5274 | S42: =P42*0.3*$S$1*0.5 -> 778.42912 | T42: =N42*M42*8*0.05 -> 9.072 | U42: =O42*M42*0.1 -> 0 | W42: =Y42*M42*2 -> 0 | X42: =Z42*M42*1.5 -> 0 | AA42: =CD42 -> 2.5 | AC42: =M42*8*AA42 -> 32.4 | AE42: =AO42/AQ42 -> 0.44260639 | AF42: =P42+R42+T42+U42+V42+W42+X42+AB42+AC42+AD42 -> 235.872 | AG42: =AF42*0.5 -> 117.936 | AH42: =(AF42-AG42)*$AH$1+S42 -> 3926.7424 | AI42: =IF(Q42>18519.27,0.045*18519.27,Q42*0.045) -> 233.52873 | AJ42: =(AI42*0.5)/$AQ$1 -> 4.374 | AK42: =(AI42*0.4) -> 93.411494 | AM42: =Q42*0.003 -> 15.568582 | AN42: 0 | AO42: =AG42-AN42-AJ42 -> 113.562 | AP42: =AH42-AK42-AL42-AM42-BB42 -> 3817.7624 | AQ42: =AO42+(AP42/$AQ$1) -> 256.5756 | AR42: =BT42 -> 31.31512 | AS42: 0 | AT42: =AR42-AS42 -> 31.31512 | AU42: =AT42*AE42 -> 13.860272 | AV42: =AU42*0.03 -> 0.41580817 | AW42: =(AT42-AU42)*$AQ$1 -> 465.95891 | AX42: =AW42*0.03 -> 13.978767 | AY42: =AO42-AU42-AV42 -> 99.28592 | AZ42: =AP42-AW42-AX42 -> 3337.8247 | BB42: 0 | BL42: =AY42-BI42-BG42-BH42-BD42+BJ42 -> 99.28592 | BM42: =AZ42-BA42-BC42-BE42-BF42+BK42 -> 3337.8247 | BN42: =IF(AQ42<100,0,0) -> 0 | BO42: =IF(AQ42<100,"",IF(AQ42<=300,AQ42*0.2-20,)) -> 31.31512 | BP42: =IF(AQ42<300.01,"",IF(AQ42<=1000,AQ42*0.25-35,)) | BQ42: =IF(AQ42<1000.01,"",IF(AQ42<=2000,AQ42*0.3-85,)) | BR42: =IF(AQ42<2000.01,"",IF(AQ42<=3000,AQ42*0.35-185,)) | BS42: =IF(AQ42<3000.01,"",IF(AQ42>3000,AQ42*0.4-335,)) | BT42: =SUM(BN42:BS42) -> 31.31512 | BU42: FBC | BV42: Zvishavane | BW42: 9586586831180 | BX42: FBC | BY42: Zvishavane | BZ42: 5798420878399 | CA42: 0 | CB42: 2.5 | CD42: 2.5 | CE42: =CA42+CB42-CC42-CD42 -> 0 | CF42: =M42*8 -> 12.96 | CG42: =CE42*CF42 -> 0 | CH42: =CG42*0.4 -> 0 | CI42: =(CG42-CH42)*$CI$2 -> 0
A43: AES-E032 | B43: Mazvita | C43: Mhererwa | E43: =E42 -> 45747 | F43: Mimosa | G43: Service Assitant | H43: 4/4 | I43: TBA | J43: =AO43/AQ43 -> 0.43943541 | K43: =K42 -> 3/2025 | L43: 208 | M43: 1.62 | N43: 25 | P43: =L43*M43 -> 336.96 | Q43: =P43*$Q$1 -> 8995.1809 | S43: =P43*0.3*$S$1*0.5 -> 1349.2771 | T43: =N43*M43*8*0.05 -> 16.2 | U43: =O43*M43*0.1 -> 0 | W43: =Y43*M43*2 -> 0 | X43: =Z43*M43*1.5 -> 0 | AA43: =CD43 -> 2.5 | AC43: =M43*8*AA43 -> 32.4 | AE43: =AO43/AQ43 -> 0.43943541 | AF43: =P43+R43+T43+U43+V43+W43+X43+AB43+AC43+AD43 -> 385.56 | AG43: =AF43*0.5 -> 192.78 | AH43: =(AF43-AG43)*$AH$1+S43 -> 6495.5585 | AI43: =IF(Q43>18519.27,0.045*18519.27,Q43*0.045) -> 404.78314 | AJ43: =(AI43*0.5)/$AQ$1 -> 7.5816 | AK43: =(AI43*0.4) -> 161.91326 | AM43: =Q43*0.003 -> 26.985543 | AN43: 0 | AO43: =AG43-AN43-AJ43 -> 185.1984 | AP43: =AH43-AK43-AL43-AM43-BB43 -> 6306.6597 | AQ43: =AO43+(AP43/$AQ$1) -> 421.44624 | AR43: =BT43 -> 70.36156 | AS43: 0 | AT43: =AR43-AS43 -> 70.36156 | AU43: =AT43*AE43 -> 30.919361 | AV43: =AU43*0.03 -> 0.92758082 | AW43: =(AT43-AU43)*$AQ$1 -> 1052.9135 | AX43: =AW43*0.03 -> 31.587404 | AY43: =AO43-AU43-AV43 -> 153.35146 | AZ43: =AP43-AW43-AX43 -> 5222.1589 | BB43: 0 | BI43: 12.5 | BL43: =AY43-BI43-BG43-BH43-BD43+BJ43 -> 140.85146 | BM43: =AZ43-BA43-BC43-BE43-BF43+BK43 -> 5222.1589 | BN43: =IF(AQ43<100,0,0) -> 0 | BO43: =IF(AQ43<100,"",IF(AQ43<=300,AQ43*0.2-20,)) -> 0 | BP43: =IF(AQ43<300.01,"",IF(AQ43<=1000,AQ43*0.25-35,)) -> 70.36156 | BQ43: =IF(AQ43<1000.01,"",IF(AQ43<=2000,AQ43*0.3-85,)) | BR43: =IF(AQ43<2000.01,"",IF(AQ43<=3000,AQ43*0.35-185,)) | BS43: =IF(AQ43<3000.01,"",IF(AQ43>3000,AQ43*0.4-335,)) | BT43: =SUM(BN43:BS43) -> 70.36156 | BU43: FBC | BV43: Zvishavane | BW43: 9544561853022 | BX43: FBC | BY43: Zvishavane | BZ43: 7837712595898 | CA43: 0 | CB43: 2.5 | CD43: 2.5 | CE43: =CA43+CB43-CC43-CD43 -> 0 | CF43: =M43*8 -> 12.96 | CG43: =CE43*CF43 -> 0 | CH43: =CG43*0.4 -> 0 | CI43: =(CG43-CH43)*$CI$2 -> 0
BL44: =AY44-BI44-BG44-BH44-BD44+BJ44 -> 0 | BM44: =AZ44-BA44-BC44-BE44-BF44+BK44 -> 0 | BN44: =IF(AQ44<100,0,0) -> 0 | BO44: =IF(AQ44<100,"",IF(AQ44<=300,AQ44*0.2-20,)) | BP44: =IF(AQ44<300.01,"",IF(AQ44<=1000,AQ44*0.25-35,)) | BQ44: =IF(AQ44<1000.01,"",IF(AQ44<=2000,AQ44*0.3-85,)) | BR44: =IF(AQ44<2000.01,"",IF(AQ44<=3000,AQ44*0.35-185,)) | BS44: =IF(AQ44<3000.01,"",IF(AQ44>3000,AQ44*0.4-335,)) | BT44: =SUM(BN44:BS44) -> 0 | CG44: =CE44*CF44 -> 0 | CH44: =CG44*0.4 -> 0 | CI44: =(CG44-CH44)*$CI$2 -> 0
C45: Totals | N45: =SUM(N4:N44) -> 863 | O45: =SUM(O4:O44) -> 524 | P45: =SUM(P4:P44) -> 17449.76 | Q45: =SUM(Q4:Q44) -> 465823.09 | R45: =SUM(R4:R44) -> 3128 | S45: =SUM(S4:S44) -> 69873.463 | T45: =SUM(T4:T44) -> 648.016 | U45: =SUM(U4:U44) -> 102.56 | ... BT45: =SUM(BT4:BT44) -> 5671.0474 | CA45: =SUM(CA4:CA38) -> 656.92 | CB45: =SUM(CB4:CB43) -> 99.32 | CC45: =SUM(CC4:CC38) -> 7 | CD45: =SUM(CD4:CD38) -> 135.31 | CE45: =SUM(CE4:CE38) -> 601.43 | CG45: =SUM(CG4:CG38) -> 12363.518 | CH45: =SUM(CH4:CH38) -> 4945.4074 | CI45: =SUM(CI4:CI38) -> 198027.22
I51: =6000/150 -> 40

Sheet  Payslip 1
A1: AIRFLOW ENVIRONMENTAL SOLUTIONS PRIVATE LIMITED PAYSLIP | M1: Rate | N1: =Paysheet!AQ1 -> 26.6951
A2: Employee Details | D2: Earnings Details | E2: Units | F2: Earning Amounts | I2: Deduction Details | J2: Deduction Amounts | M2: AESV | N2: 71 | O2: =CONCATENATE(M2,N2) -> AESV71
A3: =VLOOKUP(B4,Paysheet!$A$4:$CE$34,COLUMN(Paysheet!B5),FALSE()) -> #N/A | B3: =VLOOKUP(B4,Paysheet!$A$4:$CE$34,COLUMN(Paysheet!C5),FALSE()) -> #N/A | F3: USD | G3: ZIG | J3: USD | K3: ZIG | M3: AESV | N3: 99 | O3: =CONCATENATE(M3,N3) -> AESV99
A4: Employee NO | B4: =O2 -> AESV71 | D4: Basic Pay | E4: =VLOOKUP(B4,Paysheet!$A$4:$CE$34,COLUMN(Paysheet!L6),FALSE()) -> #N/A | F4: =VLOOKUP(B4,Paysheet!$A$4:$CE$34,COLUMN(Paysheet!P4),FALSE())*0.5 -> #N/A | G4: =VLOOKUP(B4,Paysheet!$A$4:$CE$34,COLUMN(Paysheet!P4),FALSE())*0.5*N1 -> #N/A | I4: PAYE | J4: =VLOOKUP(B4,Paysheet!$A$4:$CE$34,COLUMN(Paysheet!AU6),FALSE()) -> #N/A | K4: =VLOOKUP(B4,Paysheet!$A$4:$CE$34,COLUMN(Paysheet!AW4),FALSE()) -> #N/A | M4: AESR | N4: 89 | O4: =CONCATENATE(M4,N4) -> AESR89
A5: Period | B5: =VLOOKUP(B4,Paysheet!$A$4:$CE$34,COLUMN(Paysheet!K7),FALSE()) -> #N/A | D5: Allowances | F5: =VLOOKUP(B4,Paysheet!$A$4:$CE$34,COLUMN(Paysheet!R7),FALSE())*0.5 -> #N/A | G5: =VLOOKUP(B4,Paysheet!$A$4:$CE$34,COLUMN(Paysheet!R7),FALSE())*0.5*N1 -> #N/A | I5: AIDS LEVY | J5: =VLOOKUP(B4,Paysheet!$A$4:$CE$34,COLUMN(Paysheet!AV7),FALSE()) -> #N/A | K5: =VLOOKUP(B4,Paysheet!$A$4:$CE$34,COLUMN(Paysheet!AX4),FALSE()) -> #N/A
A6: Nat ID | B6: =VLOOKUP(B4,Paysheet!$A$4:$CE$34,COLUMN(Paysheet!D8),FALSE()) -> #N/A | D6: Overtime 1.5 | F6: =VLOOKUP(B4,Paysheet!$A$4:$CE$34,COLUMN(Paysheet!X8),FALSE())*0.51 -> #N/A | I6: NSSA | J6: =VLOOKUP(B4,Paysheet!$A$4:$CE$34,COLUMN(Paysheet!AJ8),FALSE()) -> #N/A | K6: =VLOOKUP(B4,Paysheet!$A$4:$CE$34,COLUMN(Paysheet!AK4),FALSE()) -> #N/A
A7: Pay Method | B7: Transfer | D7: Overtime 2.0 | F7: =VLOOKUP(B4,Paysheet!$A$4:$CE$34,COLUMN(Paysheet!V8),FALSE())*0.51 -> #N/A | I7: NEC | K7: =VLOOKUP(B4,Paysheet!$A$4:$CE$34,COLUMN(Paysheet!AM4),FALSE()) -> #N/A
A8: Grade | B8: =VLOOKUP(B4,Paysheet!$A$4:$CE$34,COLUMN(Paysheet!H9),FALSE()) -> #N/A | D8: Loan/Advance | I8: Repayment
A9: Occupation | B9: =VLOOKUP(B4,Paysheet!$A$4:$CE$34,COLUMN(Paysheet!G10),FALSE()) -> #N/A | D9: Gratuity | F9: =VLOOKUP(B4,Paysheet!$A$4:$CE$34,COLUMN(Paysheet!AB10),FALSE())*0.5 -> #N/A | G9: =VLOOKUP(B4,Paysheet!$A$4:$CE$34,COLUMN(Paysheet!AB10),FALSE())*0.5*N1 -> #N/A | I9: Maintenance | J9: =VLOOKUP(B4,Paysheet!$A$4:$CE$34,COLUMN(Paysheet!BD10),FALSE()) -> #N/A | K9: =VLOOKUP(B4,Paysheet!$A$4:$CE$34,COLUMN(Paysheet!BC10),FALSE()) -> #N/A
A10: Leave Days | B10: =VLOOKUP(B4,Paysheet!$A$4:$CE$34,COLUMN(Paysheet!CE11),FALSE()) -> #N/A | D10: C.I.L.O.L | F10: =VLOOKUP(B4,Paysheet!$A$4:$CE$34,COLUMN(Paysheet!AC11),FALSE())*0.6 -> #N/A | G10: =VLOOKUP(B4,Paysheet!$A$4:$CE$34,COLUMN(Paysheet!AC11),FALSE())*0.4*N1 -> #N/A | I10: Nyaradzo | K10: =VLOOKUP(B4,Paysheet!$A$4:$CE$34,COLUMN(Paysheet!BA11),FALSE()) -> #N/A
A11: NSSA No | B11: =VLOOKUP(B4,Paysheet!$A$4:$CE$34,COLUMN(Paysheet!I11),FALSE()) -> #N/A | D11: Proj/Acting Allowance | F11: =VLOOKUP(B4,Paysheet!$A$4:$CE$34,COLUMN(Paysheet!V8),FALSE())*0.6 -> #N/A | G11: =VLOOKUP(B4,Paysheet!$A$4:$CE$34,COLUMN(Paysheet!V8),FALSE())*0.4*N1 -> #N/A | I11: MIPF | K11: =VLOOKUP(B4,Paysheet!$A$4:$CE$34,COLUMN(Paysheet!AL8),FALSE()) -> #N/A | M11: Checking
A12: Station | B12: =VLOOKUP(B4,Paysheet!$A$4:$CE$34,COLUMN(Paysheet!F12),FALSE()) -> #N/A | D12: C.O.L.A | G12: =VLOOKUP(B4,Paysheet!$A$4:$CE$34,COLUMN(Paysheet!S4),FALSE()) -> #N/A | I12: Funeral Assist | J12: =VLOOKUP(B4,Paysheet!$A$4:$CE$34,COLUMN(Paysheet!BH12),FALSE()) -> #N/A | K12: =VLOOKUP(B4,Paysheet!$A$4:$CE$34,COLUMN(Paysheet!BB12),FALSE()) -> #N/A | M12: USD | N12: =F15-J15 -> #N/A
A13: Pay Date | B13: =VLOOKUP(B4,Paysheet!$A$4:$CE$34,COLUMN(Paysheet!E11),FALSE()) -> #N/A | I13: May Day | J13: =VLOOKUP(B4,Paysheet!$A$4:$CE$34,COLUMN(Paysheet!BI8),FALSE()) -> #N/A | M13: ZIG | N13: =G15-K15 -> #N/A
A15: Hourly Rate | B15: =VLOOKUP(B4,Paysheet!$A$4:$CE$34,COLUMN(Paysheet!M14),FALSE()) -> #N/A | D15: Gross | F15: =SUM(F4:F14) -> #N/A | G15: =SUM(G4:G14) -> #N/A | I15: Total Deductions | J15: =SUM(J4:J14) -> #N/A | K15: =SUM(K4:K14) -> #N/A | N15: =K17-N13 -> #N/A
A17: ZIG Banked | B17: =VLOOKUP(B4,Paysheet!$A$4:$CE$34,COLUMN(Paysheet!BU14),FALSE()) -> #N/A | D17: =VLOOKUP(B4,Paysheet!$A$4:$CE$34,COLUMN(Paysheet!BW14),FALSE()) -> #N/A | F17: Tax Credit | I17: NET PAY | J17: ZIG | K17: =VLOOKUP(B4,Paysheet!$A$4:$CE$34,COLUMN(Paysheet!BM6),FALSE()) -> #N/A
A18: USD Banked | B18: =VLOOKUP(B4,Paysheet!$A$4:$CE$34,COLUMN(Paysheet!BX31),FALSE()) -> #N/A | D18: =VLOOKUP(B4,Paysheet!$A$4:$CE$34,COLUMN(Paysheet!BZ14),FALSE()) -> #N/A | F18: =VLOOKUP(B4,Paysheet!$A$4:$CE$34,COLUMN(Paysheet!AS14),FALSE()) -> #N/A | J18: USD | K18: =VLOOKUP(B4,Paysheet!$A$4:$CE$34,COLUMN(Paysheet!BL6),FALSE()) -> #N/A
A21: AIRFLOW ENVIRONMENTAL SOLUTIONS PRIVATE LIMITED PAYSLIP
A22: =VLOOKUP(B23,Paysheet!$A$4:$CE$34,COLUMN(Paysheet!B18),FALSE()) -> #N/A | B22: =VLOOKUP(B23,Paysheet!$A$4:$CE$34,COLUMN(Paysheet!C18),FALSE()) -> #N/A | D22: Earnings Details | E22: Units | F22: Earning Amounts | I22: Deduction Details | J22: Deduction Amounts
A23: Employee NO | B23: =O3 -> AESV99 | F23: USD | G23: ZIG | J23: USD | K23: ZIG
A24: Period | B24: =VLOOKUP(B23,Paysheet!$A$4:$CE$34,COLUMN(Paysheet!K20),FALSE()) -> #N/A | D24: Basic Pay | E24: =VLOOKUP($B$23,Paysheet!$A$4:$CE$34,COLUMN(Paysheet!L20),FALSE()) -> #N/A | F24: =VLOOKUP(B23,Paysheet!$A$4:$CE$34,COLUMN(Paysheet!P20),FALSE())*0.5 -> #N/A | G24: =VLOOKUP(B23,Paysheet!$A$4:$CE$34,COLUMN(Paysheet!P20),FALSE())*0.5*N1 -> #N/A | I24: PAYE | J24: =VLOOKUP(B23,Paysheet!$A$4:$CE$34,COLUMN(Paysheet!AU20),FALSE()) -> #N/A | K24: =VLOOKUP(B23,Paysheet!$A$4:$CE$34,COLUMN(Paysheet!AW20),FALSE()) -> #N/A
A25: Nat ID | B25: =VLOOKUP(B23,Paysheet!$A$4:$CE$34,COLUMN(Paysheet!D20),FALSE()) -> #N/A | D25: Allowances | F25: =VLOOKUP(B23,Paysheet!$A$4:$CE$34,COLUMN(Paysheet!R20),FALSE())*0.6 -> #N/A | G25: =VLOOKUP(B23,Paysheet!$A$4:$CE$34,COLUMN(Paysheet!R20),FALSE())*0.5*N1 -> #N/A | I25: AIDS LEVY | J25: =VLOOKUP(B23,Paysheet!$A$4:$CE$34,COLUMN(Paysheet!AV20),FALSE()) -> #N/A | K25: =VLOOKUP(B23,Paysheet!$A$4:$CE$34,COLUMN(Paysheet!AX20),FALSE()) -> #N/A
A26: Pay Method | B26: Transfer | D26: Overtime 1.5 | F26: =VLOOKUP(B23,Paysheet!$A$4:$CE$34,COLUMN(Paysheet!X21),FALSE())*0.6 -> #N/A | G26: =VLOOKUP(B23,Paysheet!$A$4:$CE$34,COLUMN(Paysheet!X21),FALSE())*0.4*N1 -> #N/A | I26: NSSA | J26: =VLOOKUP(B23,Paysheet!$A$4:$CE$34,COLUMN(Paysheet!AJ21),FALSE()) -> #N/A | K26: =VLOOKUP(B23,Paysheet!$A$4:$CE$34,COLUMN(Paysheet!AK21),FALSE()) -> #N/A
A27: Grade | B27: =VLOOKUP(B23,Paysheet!$A$4:$CE$34,COLUMN(Paysheet!H22),FALSE()) -> #N/A | D27: Overtime 2.0 | F27: =VLOOKUP($B$23,Paysheet!$A$4:$CE$34,COLUMN(Paysheet!W22),FALSE())*0.6 -> #N/A | G27: =VLOOKUP(B23,Paysheet!$A$4:$CE$34,COLUMN(Paysheet!W22),FALSE())*0.4*N1 -> #N/A | I27: NEC | K27: =VLOOKUP(B23,Paysheet!$A$4:$CE$34,COLUMN(Paysheet!AM22),FALSE()) -> #N/A
A28: Occupation | B28: =VLOOKUP(B23,Paysheet!$A$4:$CE$34,COLUMN(Paysheet!G23),FALSE()) -> #N/A | D28: Loan/Advance | I28: Repayment
A29: Leave Days | B29: =VLOOKUP(B23,Paysheet!$A$4:$CE$34,COLUMN(Paysheet!CE24),FALSE()) -> #N/A | D29: Gratuity | F29: =VLOOKUP(B23,Paysheet!$A$4:$CE$34,COLUMN(Paysheet!AB24),FALSE())*0.5 -> #N/A | G29: =VLOOKUP(B23,Paysheet!$A$4:$CE$34,COLUMN(Paysheet!AB24),FALSE())*0.5*N1 -> #N/A | I29: Maintenance | J29: =VLOOKUP(B23,Paysheet!$A$4:$CE$34,COLUMN(Paysheet!BD24),FALSE()) -> #N/A | K29: =VLOOKUP($B$23,Paysheet!$A$4:$CE$34,COLUMN(Paysheet!BC24),FALSE()) -> #N/A
A30: NSSA No | B30: =VLOOKUP(B23,Paysheet!$A$4:$CE$34,COLUMN(Paysheet!I25),FALSE()) -> #N/A | D30: C.I.L.O.L | F30: =VLOOKUP(B23,Paysheet!$A$4:$CE$34,COLUMN(Paysheet!AC25),FALSE())*0.6 -> #N/A | G30: =VLOOKUP(B23,Paysheet!$A$4:$CE$34,COLUMN(Paysheet!AC25),FALSE())*0.4*N1 -> #N/A | I30: Nyaradzo | K30: =VLOOKUP(B23,Paysheet!$A$4:$CE$34,COLUMN(Paysheet!BA25),FALSE()) -> #N/A
A31: Station | B31: =VLOOKUP(B23,Paysheet!$A$4:$CE$34,COLUMN(Paysheet!F26),FALSE()) -> #N/A | D31: Proj/Acting Allowance | F31: =VLOOKUP(B23,Paysheet!$A$4:$CE$34,COLUMN(Paysheet!V26),FALSE())*0.6 -> #N/A | G31: =VLOOKUP(B23,Paysheet!$A$4:$CE$34,COLUMN(Paysheet!V26),FALSE())*0.4*N1 -> #N/A | I31: MIPF | K31: =VLOOKUP(B23,Paysheet!$A$4:$CE$34,COLUMN(Paysheet!AL26),FALSE()) -> #N/A | M31: Checking
A32: Pay Date | B32: =VLOOKUP($B$23,Paysheet!$A$4:$CE$34,COLUMN(Paysheet!E34),FALSE()) -> #N/A | D32: C.O.L.A | G32: =(300*N1)+Paysheet!S5 -> 11215.145 | I32: Funeral Assist | J32: =VLOOKUP(B23,Paysheet!$A$4:$CE$34,COLUMN(Paysheet!BH20),FALSE()) -> #N/A | K32: =VLOOKUP(B23,Paysheet!$A$4:$CE$34,COLUMN(Paysheet!BE20),FALSE()) -> #N/A | M32: USD | N32: =F35-J35 -> #N/A
A33: Hourly Rate | B33: =VLOOKUP(B23,Paysheet!$A$4:$CE$34,COLUMN(Paysheet!M27),FALSE()) -> #N/A | D33: Underground Allowance | F33: =VLOOKUP(B23,Paysheet!$A$4:$CE$34,COLUMN(Paysheet!T27),FALSE())*0.5 -> #N/A | G33: =VLOOKUP(B23,Paysheet!$A$4:$CE$34,COLUMN(Paysheet!T27),FALSE())*0.5*N1 -> #N/A | I33: May Day | J33: =VLOOKUP(B23,Paysheet!$A$4:$CE$34,COLUMN(Paysheet!BI27),FALSE()) -> #N/A | M33: ZIG | N33: =G35-K35 -> #N/A
M34: =K38-N32 -> #N/A | N34: =K37-N33 -> #N/A
D35: Gross | F35: =SUM(F24:F34) -> #N/A | G35: =SUM(G24:G34) -> #N/A | I35: Total Deductions | J35: =SUM(J24:J34) -> #N/A | K35: =SUM(K24:K34) -> #N/A
A37: ZIG Banked | B37: =VLOOKUP(B23,Paysheet!$A$4:$CE$34,COLUMN(Paysheet!BU31),FALSE()) -> #N/A | D37: =VLOOKUP(B23,Paysheet!$A$4:$CE$34,COLUMN(Paysheet!BZ31),FALSE()) -> #N/A | F37: Tax Credit | I37: NET PAY | J37: ZIG | K37: =VLOOKUP(B23,Paysheet!$A$4:$CE$34,COLUMN(Paysheet!BM20),FALSE()) -> #N/A | N37: =K37-N33 -> #N/A
A38: USD Banked | B38: =VLOOKUP(B23,Paysheet!$A$4:$CE$34,COLUMN(Paysheet!BX31),FALSE()) -> #N/A | D38: =VLOOKUP(B23,Paysheet!$A$4:$CE$34,COLUMN(Paysheet!BZ31),FALSE()) -> #N/A | F38: =VLOOKUP($B$23,Paysheet!$A$4:$CE$34,COLUMN(Paysheet!AS14),FALSE()) -> #N/A | J38: USD | K38: =VLOOKUP(B23,Paysheet!$A$4:$CE$34,COLUMN(Paysheet!BL20),FALSE()) -> #N/A
A42: AIRFLOW ENVIRONMENTAL SOLUTIONS PRIVATE LIMITED PAYSLIP
A43: =VLOOKUP(B44,Paysheet!$A$4:$CE$34,COLUMN(Paysheet!B18),FALSE()) -> #N/A | B43: =VLOOKUP(B44,Paysheet!$A$4:$CE$34,COLUMN(Paysheet!C18),FALSE()) -> #N/A | D43: Earnings Details | E43: Units | F43: Earning Amounts | I43: Details | J43: Deduction Amounts
A44: Employee NO | B44: =O4 -> AESR89 | F44: USD | G44: ZIG | I44: Deduction Details | J44: USD | K44: ZIG
A45: Period | B45: =VLOOKUP(B44,Paysheet!$A$4:$CE$34,COLUMN(Paysheet!K20),FALSE()) -> #N/A | D45: Basic Pay | E45: =VLOOKUP($B$44,Paysheet!$A$4:$CE$34,COLUMN(Paysheet!L20),FALSE()) -> #N/A | F45: =VLOOKUP(B44,Paysheet!$A$4:$CE$34,COLUMN(Paysheet!P22),FALSE())*0.5 -> #N/A | G45: =VLOOKUP(B44,Paysheet!$A$4:$CE$34,COLUMN(Paysheet!P22),FALSE())*0.5*N1 -> #N/A | I45: PAYE | J45: =VLOOKUP(B44,Paysheet!$A$4:$CE$34,COLUMN(Paysheet!AU20),FALSE()) -> #N/A | K45: =VLOOKUP(B44,Paysheet!$A$4:$CE$34,COLUMN(Paysheet!AW20),FALSE()) -> #N/A
A46: Nat ID | B46: =VLOOKUP(B44,Paysheet!$A$4:$CE$34,COLUMN(Paysheet!D45),FALSE()) -> #N/A | D46: Trans & Housing Allowances | F46: =VLOOKUP(B44,Paysheet!$A$4:$CE$34,COLUMN(Paysheet!R45),FALSE())*0.5 -> #N/A | G46: =VLOOKUP(B44,Paysheet!$A$4:$CE$34,COLUMN(Paysheet!R45),FALSE())*0.5*N1 -> #N/A | I46: AIDS LEVY | J46: =VLOOKUP(B44,Paysheet!$A$4:$CE$34,COLUMN(Paysheet!AV45),FALSE()) -> #N/A | K46: =VLOOKUP(B44,Paysheet!$A$4:$CE$34,COLUMN(Paysheet!AX45),FALSE()) -> #N/A
A47: Pay Method | B47: Transfer | D47: Overtime 1.5 | F47: =VLOOKUP(B44,Paysheet!$A$4:$CE$34,COLUMN(Paysheet!X46),FALSE())*0.6 -> #N/A | G47: =VLOOKUP(B44,Paysheet!$A$4:$CE$34,COLUMN(Paysheet!X46),FALSE())*0.4*N22 -> #N/A | I47: NSSA | J47: =VLOOKUP(B44,Paysheet!$A$4:$CE$34,COLUMN(Paysheet!AJ46),FALSE()) -> #N/A | K47: =VLOOKUP(B44,Paysheet!$A$4:$CE$34,COLUMN(Paysheet!AK46),FALSE()) -> #N/A
A48: Grade | B48: =VLOOKUP(B44,Paysheet!$A$4:$CE$34,COLUMN(Paysheet!H47),FALSE()) -> #N/A | D48: Overtime 2.0 | F48: =VLOOKUP($B$23,Paysheet!$A$4:$CE$34,COLUMN(Paysheet!W47),FALSE())*0.6 -> #N/A | G48: =VLOOKUP(B44,Paysheet!$A$4:$CE$34,COLUMN(Paysheet!W47),FALSE())*0.4*N22 -> #N/A | I48: NEC | K48: =VLOOKUP(B44,Paysheet!$A$4:$CE$34,COLUMN(Paysheet!AM47),FALSE()) -> #N/A
A49: Occupation | B49: =VLOOKUP(B44,Paysheet!$A$4:$CE$34,COLUMN(Paysheet!G48),FALSE()) -> #N/A | D49: Loan/Advance | I49: Repayment
A50: Leave Days | B50: TBA | D50: Gratuity | F50: =VLOOKUP(B44,Paysheet!$A$4:$CE$34,COLUMN(Paysheet!AB49),FALSE())*0.5 -> #N/A | G50: =VLOOKUP(B44,Paysheet!$A$4:$CE$34,COLUMN(Paysheet!AB49),FALSE())*0.5*N1 -> #N/A | I50: Maintenance | J50: =VLOOKUP(B44,Paysheet!$A$4:$CE$34,COLUMN(Paysheet!BD49),FALSE()) -> #N/A | K50: =VLOOKUP($B$23,Paysheet!$A$4:$CE$34,COLUMN(Paysheet!BC49),FALSE()) -> #N/A
A51: NSSA No | B51: =VLOOKUP(B44,Paysheet!$A$4:$CE$34,COLUMN(Paysheet!I50),FALSE()) -> #N/A | D51: C.I.L.O.L | F51: =VLOOKUP(B44,Paysheet!$A$4:$CE$34,COLUMN(Paysheet!AC50),FALSE())*0.6 -> #N/A | G51: =VLOOKUP(B44,Paysheet!$A$4:$CE$34,COLUMN(Paysheet!AC50),FALSE())*0.4*N22 -> #N/A | I51: Nyaradzo | K51: =VLOOKUP(B44,Paysheet!$A$4:$CE$34,COLUMN(Paysheet!BA50),FALSE()) -> #N/A
A52: Station | B52: =VLOOKUP(B44,Paysheet!$A$4:$CE$34,COLUMN(Paysheet!F34),FALSE()) -> #N/A | D52: Proj/Acting Allowance | F52: =VLOOKUP(B44,Paysheet!$A$4:$CE$34,COLUMN(Paysheet!V34),FALSE())*0.6 -> #N/A | G52: =VLOOKUP(B44,Paysheet!$A$4:$CE$34,COLUMN(Paysheet!V34),FALSE())*0.4*N1 -> #N/A | I52: MIPF | K52: =VLOOKUP(B44,Paysheet!$A$4:$CE$34,COLUMN(Paysheet!AL51),FALSE()) -> #N/A | M52: Checking
A53: Pay Date | B53: =VLOOKUP($B$23,Paysheet!$A$4:$CE$34,COLUMN(Paysheet!E45),FALSE()) -> #N/A | D53: C.O.L.A | G53: =70*N1+Paysheet!S8 -> 5833.1997 | I53: Funeral Assist | J53: =VLOOKUP(B44,Paysheet!$A$4:$CE$34,COLUMN(Paysheet!BH45),FALSE()) -> #N/A | K53: =VLOOKUP(B44,Paysheet!$A$4:$CE$34,COLUMN(Paysheet!BB52),FALSE()) -> #N/A | M53: USD | N53: =F55-J55 -> #N/A
A54: Hourly Rate | B54: =VLOOKUP(B44,Paysheet!$A$4:$CE$34,COLUMN(Paysheet!M38),FALSE()) -> #N/A | D54: Underground Allowance | F54: =VLOOKUP(B44,Paysheet!$A$4:$CE$34,COLUMN(Paysheet!T46),FALSE())*0.6 -> #N/A | G54: =VLOOKUP(B44,Paysheet!$A$4:$CE$34,COLUMN(Paysheet!T46),FALSE())*0.4*N1 -> #N/A | I54: May Day | J54: =VLOOKUP(B44,Paysheet!$A$4:$CE$34,COLUMN(Paysheet!BI46),FALSE()) -> #N/A | M54: ZIG | N54: =G55-K55 -> #N/A
D55: Gross | F55: =SUM(F45:F54) -> #N/A | G55: =SUM(G45:G54) -> #N/A | I55: Total Deductions | J55: =SUM(J45:J54) -> #N/A | K55: =SUM(K45:K54) -> #N/A
A57: ZIG Banked | B57: =VLOOKUP(B44,Paysheet!$A$4:$CE$34,COLUMN(Paysheet!BU31),FALSE()) -> #N/A | D57: =VLOOKUP(B44,Paysheet!$A$4:$CE$34,COLUMN(Paysheet!BZ31),FALSE()) -> #N/A | F57: Tax Credit | I57: NET PAY | J57: ZIG | K57: =VLOOKUP(B44,Paysheet!$A$4:$CE$34,COLUMN(Paysheet!BM20),FALSE()) -> #N/A | N57: =K57-N54 -> #N/A
A58: USD Banked | B58: =VLOOKUP(B44,Paysheet!$A$4:$CE$34,COLUMN(Paysheet!BX31),FALSE()) -> #N/A | D58: =VLOOKUP(B44,Paysheet!$A$4:$CE$34,COLUMN(Paysheet!BZ31),FALSE()) -> #N/A | F58: =VLOOKUP($B$23,Paysheet!$A$4:$CE$34,COLUMN(Paysheet!AS14),FALSE()) -> #N/A | J58: USD | K58: =VLOOKUP(B44,Paysheet!$A$4:$CE$34,COLUMN(Paysheet!BL20),FALSE()) -> #N/A

Sheet Payslip 2
A1: AIRFLOW ENVIRONMENTAL SOLUTIONS PRIVATE LIMITED PAYSLIP | M1: Rate | N1: =' Payslip 1'!N1 -> 26.6951
A2: Employee Details | D2: Earnings Details | E2: Units | F2: Earning Amounts | I2: Deduction Details | J2: Deduction Amounts | M2: AESR | N2: 187 | O2: =CONCATENATE(M2,N2) -> AESR187
A3: =VLOOKUP(B4,Paysheet!$A$4:$CE$48,COLUMN(Paysheet!B5),FALSE()) -> #N/A | B3: =VLOOKUP(B4,Paysheet!$A$4:$CE$48,COLUMN(Paysheet!C5),FALSE()) -> #N/A | F3: USD | G3: ZIG | J3: USD | K3: ZIG | M3: AESR | N3: 179 | O3: =CONCATENATE(M3,N3) -> AESR179
A4: Employee NO | B4: =O2 -> AESR187 | D4: Basic Pay | E4: =VLOOKUP(B4,Paysheet!$A$4:$CE$48,COLUMN(Paysheet!L6),FALSE()) -> #N/A | F4: =VLOOKUP(B4,Paysheet!$A$4:$CE$48,COLUMN(Paysheet!P6),FALSE())*0.5 -> #N/A | G4: =VLOOKUP(B4,Paysheet!$A$4:$CE$48,COLUMN(Paysheet!P6),FALSE())*0.5*N1 -> #N/A | I4: PAYE | J4: =VLOOKUP(B4,Paysheet!$A$4:$CE$48,COLUMN(Paysheet!AU6),FALSE()) -> #N/A | K4: =VLOOKUP(B4,Paysheet!$A$4:$CE$48,COLUMN(Paysheet!AW6),FALSE()) -> #N/A | M4: AESR | N4: 183 | O4: =CONCATENATE(M4,N4) -> AESR183
A5: Period | B5: =VLOOKUP(B4,Paysheet!$A$4:$CE$48,COLUMN(Paysheet!K7),FALSE()) -> #N/A | D5: Allowances | F5: =VLOOKUP(B4,Paysheet!$A$4:$CE$48,COLUMN(Paysheet!R7),FALSE())*0.5 -> #N/A | G5: =VLOOKUP(B4,Paysheet!$A$4:$CE$48,COLUMN(Paysheet!R7),FALSE())*0.5*N1 -> #N/A | I5: AIDS LEVY | J5: =VLOOKUP(B4,Paysheet!$A$4:$CE$48,COLUMN(Paysheet!AV7),FALSE()) -> #N/A | K5: =VLOOKUP(B4,Paysheet!$A$4:$CE$48,COLUMN(Paysheet!AX7),FALSE()) -> #N/A
A6: Nat ID | B6: =VLOOKUP(B4,Paysheet!$A$4:$CE$48,COLUMN(Paysheet!D8),FALSE()) -> #N/A | D6: Overtime 1.5 | F6: =VLOOKUP(B4,Paysheet!$A$4:$CE$48,COLUMN(Paysheet!X8),FALSE())*0.5 -> #N/A | I6: NSSA | J6: =VLOOKUP(B4,Paysheet!$A$4:$CE$48,COLUMN(Paysheet!AJ8),FALSE()) -> #N/A | K6: =VLOOKUP(B4,Paysheet!$A$4:$CE$48,COLUMN(Paysheet!AK8),FALSE()) -> #N/A
A7: Pay Method | B7: Transfer | D7: Overtime 2.0 | F7: =VLOOKUP(B4,Paysheet!$A$4:$CE$48,COLUMN(Paysheet!W6),FALSE())*0.5 -> #N/A | G7: =VLOOKUP(B4,Paysheet!$A$4:$CE$48,COLUMN(Paysheet!W6),FALSE())*0.5*N1 -> #N/A | I7: NEC | K7: =VLOOKUP(B4,Paysheet!$A$4:$CE$48,COLUMN(Paysheet!AM12),FALSE()) -> #N/A
A8: Grade | B8: =VLOOKUP(B4,Paysheet!$A$4:$CE$48,COLUMN(Paysheet!H9),FALSE()) -> #N/A | D8: Loan/Advance | F8: =VLOOKUP(B4,Paysheet!$A$4:$CE$48,COLUMN(Paysheet!BJ9),FALSE()) -> #N/A | G8: =VLOOKUP(B4,Paysheet!$A$4:$CE$48,COLUMN(Paysheet!BK9),FALSE()) -> #N/A | I8: Repayment | J8: =VLOOKUP(B4,Paysheet!$A$4:$CE$48,COLUMN(Paysheet!BG9),FALSE()) -> #N/A
A9: Occupation | B9: =VLOOKUP(B4,Paysheet!$A$4:$CE$48,COLUMN(Paysheet!G10),FALSE()) -> #N/A | D9: Gratuity | F9: =VLOOKUP(B4,Paysheet!$A$4:$CE$48,COLUMN(Paysheet!AB10),FALSE())*0.5 -> #N/A | G9: =VLOOKUP(B4,Paysheet!$A$4:$CE$48,COLUMN(Paysheet!AB10),FALSE())*0.5*N1 -> #N/A | I9: Maintenance | J9: =VLOOKUP(B4,Paysheet!$A$4:$CE$48,COLUMN(Paysheet!BD10),FALSE()) -> #N/A | K9: =VLOOKUP(B4,Paysheet!$A$4:$CE$48,COLUMN(Paysheet!BC10),FALSE()) -> #N/A
A10: Leave Days | B10: =VLOOKUP(B4,Paysheet!$A$4:$CE$48,COLUMN(Paysheet!CE11),FALSE()) -> #N/A | D10: C.I.L.O.L | F10: =VLOOKUP(B4,Paysheet!$A$4:$CE$48,COLUMN(Paysheet!AC11),FALSE())*0.5 -> #N/A | G10: =VLOOKUP(B4,Paysheet!$A$4:$CE$48,COLUMN(Paysheet!AC11),FALSE())*0.5*N1 -> #N/A | I10: Nyaradzo | K10: =VLOOKUP(B4,Paysheet!$A$4:$CE$48,COLUMN(Paysheet!BA11),FALSE()) -> #N/A
A11: NSSA No | B11: =VLOOKUP(B4,Paysheet!$A$4:$CE$48,COLUMN(Paysheet!I25),FALSE()) -> #N/A | D11: Proj/Acting Allowance | F11: =VLOOKUP(B4,Paysheet!$A$4:$CE$48,COLUMN(Paysheet!V11),FALSE())*0.5 -> #N/A | G11: =VLOOKUP(B4,Paysheet!$A$4:$CE$48,COLUMN(Paysheet!V11),FALSE())*0.5*N1 -> #N/A | I11: MIPF | K11: =VLOOKUP(B4,Paysheet!$A$4:$CE$48,COLUMN(Paysheet!AL11),FALSE()) -> #N/A | M11: Checking
A12: Station | B12: =VLOOKUP(B4,Paysheet!$A$4:$CE$48,COLUMN(Paysheet!F12),FALSE()) -> #N/A | D12: Underground Allowance | F12: =VLOOKUP(B4,Paysheet!$A$4:$CE$48,COLUMN(Paysheet!T12),FALSE())*0.5 -> #N/A | G12: =VLOOKUP(B4,Paysheet!$A$4:$CE$48,COLUMN(Paysheet!T12),FALSE())*0.5*N1 -> #N/A | I12: Funeral Assist | J12: =VLOOKUP(B4,Paysheet!$A$4:$CE$48,COLUMN(Paysheet!BH12),FALSE()) -> #N/A | K12: =VLOOKUP(B4,Paysheet!$A$4:$CE$48,COLUMN(Paysheet!BB12),FALSE()) -> #N/A | M12: usd | N12: =F15-J15 -> #N/A
A13: Pay Date | B13: =VLOOKUP(B4,Paysheet!$A$4:$CE$48,COLUMN(Paysheet!E12),FALSE()) -> #N/A | D13: Night Shift Allowance | F13: =VLOOKUP(B4,Paysheet!$A$4:$CE$48,COLUMN(Paysheet!U12),FALSE())*0.5 -> #N/A | G13: =VLOOKUP(B4,Paysheet!$A$4:$CE$48,COLUMN(Paysheet!U12),FALSE())*0.5*N1 -> #N/A | I13: May Day | J13: =VLOOKUP(B4,Paysheet!$A$4:$CE$48,COLUMN(Paysheet!BI12),FALSE()) -> #N/A | M13: zwl | N13: =G15-K15 -> #N/A
A14: Hourly Rate | B14: =VLOOKUP(B4,Paysheet!$A$4:$CE$48,COLUMN(Paysheet!M13),FALSE()) -> #N/A | D14: COLA | G14: =VLOOKUP(B4,Paysheet!$A$4:$CE$48,COLUMN(Paysheet!S13),FALSE()) -> #N/A
D15: Gross | F15: =SUM(F4:F14) -> #N/A | G15: =SUM(G4:G14) -> #N/A | I15: Total Deductions | J15: =SUM(J4:J14) -> #N/A | K15: =SUM(K4:K14) -> #N/A | M15: =K18-N12 -> #N/A | N15: =K17-N13 -> #N/A
A17: ZIG Banked | B17: =VLOOKUP(B4,Paysheet!$A$4:$CE$48,COLUMN(Paysheet!BU12),FALSE()) -> #N/A | D17: =VLOOKUP(B4,Paysheet!$A$4:$CE$48,COLUMN(Paysheet!BW12),FALSE()) -> #N/A | F17: Tax Credit | I17: NET PAY | J17: ZIG | K17: =VLOOKUP(B4,Paysheet!$A$4:$CE$48,COLUMN(Paysheet!BM6),FALSE()) -> #N/A
A18: USD Banked | B18: =VLOOKUP(B4,Paysheet!$A$4:$CE$48,COLUMN(Paysheet!BX12),FALSE()) -> #N/A | D18: =VLOOKUP(B4,Paysheet!$A$4:$CE$48,COLUMN(Paysheet!BZ12),FALSE()) -> #N/A | F18: =VLOOKUP(B4,Paysheet!$A$4:$CE$48,COLUMN(Paysheet!AS12),FALSE()) -> #N/A | J18: USD | K18: =VLOOKUP(B4,Paysheet!$A$4:$CE$48,COLUMN(Paysheet!BL6),FALSE()) -> #N/A
A21: AIRFLOW ENVIRONMENTAL SOLUTIONS PRIVATE LIMITED PAYSLIP
A22: Employee Details | D22: Earnings Details | E22: Units | F22: Earning Amounts | I22: Deduction Details | J22: Deduction Amounts
A23: =VLOOKUP(B24,Paysheet!$A$4:$CE$44,COLUMN(Paysheet!B18),FALSE()) -> #N/A | B23: =VLOOKUP(B24,Paysheet!$A$4:$CE$46,COLUMN(Paysheet!C18),FALSE()) -> #N/A | F23: USD | G23: ZIG | J23: USD | K23: ZIG
A24: Employee NO | B24: =O3 -> AESR179 | D24: Basic Pay | E24: =VLOOKUP(B24,Paysheet!$A$4:$CE$46,COLUMN(Paysheet!L19),FALSE()) -> #N/A | F24: =VLOOKUP(B24,Paysheet!$A$4:$CE$46,COLUMN(Paysheet!P19),FALSE())*0.5 -> #N/A | G24: =VLOOKUP(B24,Paysheet!$A$4:$CE$46,COLUMN(Paysheet!P19),FALSE())*0.5*N1 -> #N/A | I24: PAYE | J24: =VLOOKUP(B24,Paysheet!$A$4:$CE$46,COLUMN(Paysheet!AU19),FALSE()) -> #N/A | K24: =VLOOKUP(B24,Paysheet!$A$4:$CE$46,COLUMN(Paysheet!AW19),FALSE()) -> #N/A
A25: Period | B25: =VLOOKUP(B24,Paysheet!$A$4:$CE$46,COLUMN(Paysheet!K20),FALSE()) -> #N/A | D25: Allowances | F25: =VLOOKUP(B24,Paysheet!$A$4:$CE$46,COLUMN(Paysheet!R20),FALSE())*0.5 -> #N/A | G25: =VLOOKUP(B24,Paysheet!$A$4:$CE$46,COLUMN(Paysheet!R20),FALSE())*0.5*N1 -> #N/A | I25: AIDS LEVY | J25: =VLOOKUP(B24,Paysheet!$A$4:$CE$46,COLUMN(Paysheet!AV20),FALSE()) -> #N/A | K25: =VLOOKUP(B24,Paysheet!$A$4:$CE$46,COLUMN(Paysheet!AX20),FALSE()) -> #N/A
A26: Nat ID | B26: =VLOOKUP(B24,Paysheet!$A$4:$CE$46,COLUMN(Paysheet!D20),FALSE()) -> #N/A | D26: Overtime 1.5 | F26: =VLOOKUP(B24,Paysheet!$A$4:$CE$46,COLUMN(Paysheet!X20),FALSE())*0.5 -> #N/A | I26: NSSA | J26: =VLOOKUP(B24,Paysheet!$A$4:$CE$46,COLUMN(Paysheet!AJ20),FALSE()) -> #N/A | K26: =VLOOKUP(B24,Paysheet!$A$4:$CE$46,COLUMN(Paysheet!AK20),FALSE()) -> #N/A
A27: Pay Method | B27: Transfer | D27: Overtime 2.0 | F27: =VLOOKUP(B24,Paysheet!$A$4:$CE$46,COLUMN(Paysheet!W21),FALSE())*0.5 -> #N/A | G27: =VLOOKUP(B24,Paysheet!$A$4:$CE$46,COLUMN(Paysheet!W21),FALSE())*0.5*N1 -> #N/A | I27: NEC | K27: =VLOOKUP(B24,Paysheet!$A$4:$CE$46,COLUMN(Paysheet!AM21),FALSE()) -> #N/A
A28: Grade | B28: =VLOOKUP(B24,Paysheet!$A$4:$CE$46,COLUMN(Paysheet!H22),FALSE()) -> #N/A | D28: Funeral Assistance | F28: =VLOOKUP(B24,Paysheet!$A$4:$CE$46,COLUMN(Paysheet!BJ22),FALSE()) -> #N/A | I28: Repayment | J28: =VLOOKUP(B24,Paysheet!$A$4:$CE$46,COLUMN(Paysheet!BG22),FALSE()) -> #N/A | K28: =VLOOKUP(B24,Paysheet!$A$4:$CE$46,COLUMN(Paysheet!BF22),FALSE()) -> #N/A
A29: Occupation | B29: =VLOOKUP(B24,Paysheet!$A$4:$CE$46,COLUMN(Paysheet!G23),FALSE()) -> #N/A | D29: Gratuity | F29: =VLOOKUP(B24,Paysheet!$A$4:$CE$46,COLUMN(Paysheet!AB23),FALSE())*0.5 -> #N/A | G29: =VLOOKUP(B24,Paysheet!$A$4:$CE$46,COLUMN(Paysheet!AB23),FALSE())*0.5*N1 -> #N/A | I29: Maintenance | J29: =VLOOKUP(B24,Paysheet!$A$4:$CE$46,COLUMN(Paysheet!BD23),FALSE()) -> #N/A | K29: =VLOOKUP(B24,Paysheet!$A$4:$CE$46,COLUMN(Paysheet!BC23),FALSE()) -> #N/A
A30: Leave Days | B30: =VLOOKUP(B24,Paysheet!$A$4:$CE$46,COLUMN(Paysheet!CE24),FALSE()) -> #N/A | D30: C.I.L.O.L | F30: =VLOOKUP(B24,Paysheet!$A$4:$CE$46,COLUMN(Paysheet!AC24),FALSE())*0.5 -> #N/A | G30: =VLOOKUP(B24,Paysheet!$A$4:$CE$46,COLUMN(Paysheet!AC24),FALSE())*0.5*N1 -> #N/A | I30: Nyaradzo | K30: =VLOOKUP(B24,Paysheet!$A$4:$CE$46,COLUMN(Paysheet!BA24),FALSE()) -> #N/A
A31: NSSA No | B31: =VLOOKUP(B24,Paysheet!$A$4:$CE$46,COLUMN(Paysheet!I25),FALSE()) -> #N/A | D31: Proj/Acting Allowance | F31: =VLOOKUP(B24,Paysheet!$A$4:$CE$46,COLUMN(Paysheet!V25),FALSE())*0.5 -> #N/A | G31: =VLOOKUP(B24,Paysheet!$A$4:$CE$46,COLUMN(Paysheet!V25),FALSE())*0.5*N1 -> #N/A | I31: MIPF | K31: =VLOOKUP(B24,Paysheet!$A$4:$CE$46,COLUMN(Paysheet!AL25),FALSE()) -> #N/A | M31: Checking
A32: Station | B32: =VLOOKUP(B24,Paysheet!$A$4:$CE$46,COLUMN(Paysheet!F26),FALSE()) -> #N/A | D32: Underground Allowance | F32: =VLOOKUP(B24,Paysheet!$A$4:$CE$46,COLUMN(Paysheet!T26),FALSE())*0.5 -> #N/A | G32: =VLOOKUP(B24,Paysheet!$A$4:$CE$46,COLUMN(Paysheet!T26),FALSE())*0.5*N1 -> #N/A | I32: Funeral Assist | J32: =VLOOKUP(B24,Paysheet!$A$4:$CE$46,COLUMN(Paysheet!BH26),FALSE()) -> #N/A | K32: =VLOOKUP(B24,Paysheet!$A$4:$CE$46,COLUMN(Paysheet!BB26),FALSE()) -> #N/A | M32: usd | N32: =F35-J35 -> #N/A
A33: Pay Date | B33: =VLOOKUP(B24,Paysheet!$A$4:$CE$46,COLUMN(Paysheet!E20),FALSE()) -> #N/A | D33: Night Shift Allowance | F33: =VLOOKUP(B24,Paysheet!$A$4:$CE$46,COLUMN(Paysheet!U20),FALSE())*0.5 -> #N/A | G33: =VLOOKUP(B24,Paysheet!$A$4:$CE$46,COLUMN(Paysheet!U12),FALSE())*0.5*N1 -> #N/A | I33: May Day | J33: =VLOOKUP(B24,Paysheet!$A$4:$CE$46,COLUMN(Paysheet!BI20),FALSE()) -> #N/A | M33: zwl | N33: =G35-K35 -> #N/A
A34: Hourly Rate | B34: =VLOOKUP(B24,Paysheet!$A$4:$CE$46,COLUMN(Paysheet!M28),FALSE()) -> #N/A | D34: COLA | G34: =VLOOKUP(B24,Paysheet!$A$4:$CE$46,COLUMN(Paysheet!S28),FALSE()) -> #N/A
D35: Gross | F35: =SUM(F24:F34) -> #N/A | G35: =SUM(G24:G34) -> #N/A | I35: Total Deductions | J35: =SUM(J24:J34) -> #N/A | K35: =SUM(K24:K34) -> #N/A
A37: ZIG Banked | B37: =VLOOKUP(B24,Paysheet!$A$4:$CE$46,COLUMN(Paysheet!BU30),FALSE()) -> #N/A | D37: =VLOOKUP(B24,Paysheet!$A$4:$CE$46,COLUMN(Paysheet!BW30),FALSE()) -> #N/A | F37: Tax Credit | I37: NET PAY | J37: ZIG | K37: =VLOOKUP(B24,Paysheet!$A$4:$CE$46,COLUMN(Paysheet!BM19),FALSE()) -> #N/A
A38: USD Banked | B38: =VLOOKUP(B24,Paysheet!$A$4:$CE$46,COLUMN(Paysheet!BX12),FALSE()) -> #N/A | D38: =VLOOKUP(B24,Paysheet!$A$4:$CE$46,COLUMN(Paysheet!BZ12),FALSE()) -> #N/A | F38: =VLOOKUP(B24,Paysheet!$A$4:$CE$48,COLUMN(Paysheet!AS30),FALSE()) -> #N/A | J38: USD | K38: =VLOOKUP(B24,Paysheet!$A$4:$CE$46,COLUMN(Paysheet!BL19),FALSE()) -> #N/A | N38: =K37-N33 -> #N/A
A42: AIRFLOW ENVIRONMENTAL SOLUTIONS PRIVATE LIMITED PAYSLIP
A43: Employee Details | D43: Earnings Details | E43: Units | F43: Earning Amounts | I43: Deduction Details | J43: Deduction Amounts
A44: =VLOOKUP(B45,Paysheet!$A$4:$CE$48,COLUMN(Paysheet!B32),FALSE()) -> #N/A | B44: =VLOOKUP(B45,Paysheet!$A$4:$CE$48,COLUMN(Paysheet!C32),FALSE()) -> #N/A | F44: USD | G44: ZIG | J44: USD | K44: ZIG
A45: Employee NO | B45: =O4 -> AESR183 | D45: Basic Pay | E45: =VLOOKUP(B45,Paysheet!$A$4:$CE$48,COLUMN(Paysheet!L33),FALSE()) -> #N/A | F45: =VLOOKUP(B45,Paysheet!$A$4:$CE$48,COLUMN(Paysheet!P33),FALSE())*0.5 -> #N/A | G45: =VLOOKUP(B45,Paysheet!$A$4:$CE$48,COLUMN(Paysheet!P33),FALSE())*0.5*N1 -> #N/A | I45: PAYE | J45: =VLOOKUP(B45,Paysheet!$A$4:$CE$48,COLUMN(Paysheet!AU33),FALSE()) -> #N/A | K45: =VLOOKUP(B45,Paysheet!$A$4:$CE$48,COLUMN(Paysheet!AW33),FALSE()) -> #N/A
A46: Period | B46: =VLOOKUP(B45,Paysheet!$A$4:$CE$48,COLUMN(Paysheet!K33),FALSE()) -> #N/A | D46: Allowances | F46: =VLOOKUP(B45,Paysheet!$A$4:$CE$48,COLUMN(Paysheet!R33),FALSE())*0.5 -> #N/A | G46: =VLOOKUP(B45,Paysheet!$A$4:$CE$48,COLUMN(Paysheet!R33),FALSE())*0.5*N1 -> #N/A | I46: AIDS LEVY | J46: =VLOOKUP(B45,Paysheet!$A$4:$CE$48,COLUMN(Paysheet!AV33),FALSE()) -> #N/A | K46: =VLOOKUP(B45,Paysheet!$A$4:$CE$48,COLUMN(Paysheet!AX33),FALSE()) -> #N/A
A47: Nat ID | B47: =VLOOKUP(B45,Paysheet!$A$4:$CE$48,COLUMN(Paysheet!D33),FALSE()) -> #N/A | D47: Overtime 1.5 | F47: =VLOOKUP(B45,Paysheet!$A$4:$CE$48,COLUMN(Paysheet!X33),FALSE())*0.5 -> #N/A | I47: NSSA | J47: =VLOOKUP(B45,Paysheet!$A$4:$CE$48,COLUMN(Paysheet!AJ33),FALSE()) -> #N/A | K47: =VLOOKUP(B45,Paysheet!$A$4:$CE$48,COLUMN(Paysheet!AK33),FALSE()) -> #N/A
A48: Pay Method | B48: Transfer | D48: Overtime 2.0 | F48: =VLOOKUP(B45,Paysheet!$A$4:$CE$48,COLUMN(Paysheet!W45),FALSE())*0.5 -> #N/A | G48: =VLOOKUP(B45,Paysheet!$A$4:$CE$48,COLUMN(Paysheet!W45),FALSE())*0.5*N1 -> #N/A | I48: NEC | K48: =VLOOKUP(B45,Paysheet!$A$4:$CE$48,COLUMN(Paysheet!AM45),FALSE()) -> #N/A
A49: Grade | B49: =VLOOKUP(B45,Paysheet!$A$4:$CE$48,COLUMN(Paysheet!H46),FALSE()) -> #N/A | D49: Loan/Advance | I49: Repayment | J49: =VLOOKUP(B45,Paysheet!$A$4:$CE$48,COLUMN(Paysheet!BG13),FALSE()) -> #N/A
A50: Occupation | B50: =VLOOKUP(B45,Paysheet!$A$4:$CE$48,COLUMN(Paysheet!G47),FALSE()) -> #N/A | D50: Gratuity | F50: =VLOOKUP(B45,Paysheet!$A$4:$CE$48,COLUMN(Paysheet!AB47),FALSE())*0.5 -> #N/A | G50: =VLOOKUP(B45,Paysheet!$A$4:$CE$48,COLUMN(Paysheet!AB47),FALSE())*0.5*N1 -> #N/A | I50: Maintenance | J50: =VLOOKUP(B45,Paysheet!$A$4:$CE$48,COLUMN(Paysheet!BD47),FALSE()) -> #N/A | K50: =VLOOKUP(B45,Paysheet!$A$4:$CE$48,COLUMN(Paysheet!BC47),FALSE()) -> #N/A
A51: Leave Days | B51: =VLOOKUP(B45,Paysheet!$A$4:$CE$48,COLUMN(Paysheet!CE48),FALSE()) -> #N/A | D51: C.I.L.O.L | F51: =VLOOKUP(B45,Paysheet!$A$4:$CE$48,COLUMN(Paysheet!AC48),FALSE())*0.5 -> #N/A | G51: =VLOOKUP(B45,Paysheet!$A$4:$CE$48,COLUMN(Paysheet!AC48),FALSE())*0.5*N1 -> #N/A | I51: Nyaradzo | K51: =VLOOKUP(B45,Paysheet!$A$4:$CE$48,COLUMN(Paysheet!BA48),FALSE()) -> #N/A
A52: NSSA No | B52: =VLOOKUP(B45,Paysheet!$A$4:$CE$48,COLUMN(Paysheet!I49),FALSE()) -> #N/A | D52: Proj/Acting Allowance | F52: =VLOOKUP(B45,Paysheet!$A$4:$CE$48,COLUMN(Paysheet!V49),FALSE())*0.5 -> #N/A | G52: =VLOOKUP(B45,Paysheet!$A$4:$CE$48,COLUMN(Paysheet!V49),FALSE())*0.5*N1 -> #N/A | I52: MIPF | K52: =VLOOKUP(B45,Paysheet!$A$4:$CE$48,COLUMN(Paysheet!AL49),FALSE()) -> #N/A | M52: Checking
A53: Station | B53: =VLOOKUP(B45,Paysheet!$A$4:$CE$48,COLUMN(Paysheet!F50),FALSE()) -> #N/A | D53: Underground Allowance | F53: =VLOOKUP(B45,Paysheet!$A$4:$CE$48,COLUMN(Paysheet!T50),FALSE())*0.5 -> #N/A | G53: =VLOOKUP(B45,Paysheet!$A$4:$CE$48,COLUMN(Paysheet!T50),FALSE())*0.5*N1 -> #N/A | I53: Funeral Assist | J53: =VLOOKUP(B45,Paysheet!$A$4:$CE$48,COLUMN(Paysheet!BH50),FALSE()) -> #N/A | K53: =VLOOKUP(B45,Paysheet!$A$4:$CE$48,COLUMN(Paysheet!BB50),FALSE()) -> #N/A | M53: usd | N53: =F56-J56 -> #N/A
A54: Pay Date | B54: =VLOOKUP(B45,Paysheet!$A$4:$CE$48,COLUMN(Paysheet!E51),FALSE()) -> #N/A | D54: Night Shift Allowance | F54: =VLOOKUP(B45,Paysheet!$A$4:$CE$48,COLUMN(Paysheet!U51),FALSE())*0.5 -> #N/A | G54: =VLOOKUP(B45,Paysheet!$A$4:$CE$48,COLUMN(Paysheet!U51),FALSE())*0.5*N1 -> #N/A | I54: May Day | J54: =VLOOKUP(B45,Paysheet!$A$4:$CE$48,COLUMN(Paysheet!BI51),FALSE()) -> #N/A | M54: zwl | N54: =G56-K56 -> #N/A
A55: Hourly Rate | B55: =VLOOKUP(B45,Paysheet!$A$4:$CE$48,COLUMN(Paysheet!M45),FALSE()) -> #N/A | D55: C.O.L.A | G55: =VLOOKUP(B45,Paysheet!$A$4:$CE$48,COLUMN(Paysheet!S54),FALSE()) -> #N/A
D56: Gross | F56: =SUM(F45:F55) -> #N/A | G56: =SUM(G45:G55) -> #N/A | I56: Total Deductions | J56: =SUM(J45:J55) -> #N/A | K56: =SUM(K45:K55) -> #N/A | N56: =K58-N54 -> #N/A
A58: ZIG Banked | B58: =VLOOKUP(B45,Paysheet!$A$4:$CE$48,COLUMN(Paysheet!BU49),FALSE()) -> #N/A | D58: =VLOOKUP(B45,Paysheet!$A$4:$CE$48,COLUMN(Paysheet!BW49),FALSE()) -> #N/A | F58: Tax Credit | I58: NET PAY | J58: ZIG | K58: =VLOOKUP(B45,Paysheet!$A$4:$CE$48,COLUMN(Paysheet!BM33),FALSE()) -> #N/A | N58: =K59-N53 -> #N/A
A59: USD Banked | B59: =VLOOKUP(B45,Paysheet!$A$4:$CE$48,COLUMN(Paysheet!BX50),FALSE()) -> #N/A | D59: =VLOOKUP(B45,Paysheet!$A$4:$CE$48,COLUMN(Paysheet!BZ50),FALSE()) -> #N/A | F59: =VLOOKUP(B45,Paysheet!$A$4:$CE$48,COLUMN(Paysheet!AS49),FALSE()) -> #N/A | J59: USD | K59: =VLOOKUP(B45,Paysheet!$A$4:$CE$48,COLUMN(Paysheet!BL33),FALSE()) -> #N/A

Sheet Bank Schedule
C1: Netsai | D1: Nhemachena | E1: Bank | F1: Branch | G1: Account Number | H1: Amount | I1: Bank | J1: Branch | K1: Account Number | L1: Amount
A2: 1 | B2: =Paysheet!A4 -> AES-E046 | C2: =Paysheet!B4 -> Tarisai | D2: =Paysheet!C4 -> Zinyama | E2: =Paysheet!BU4 -> FBC | F2: =Paysheet!BV4 -> Zvishavane | G2: =Paysheet!BW4 -> 8374810963284 | H2: =Paysheet!BM4 -> 32451.672 | I2: =Paysheet!BX4 -> FBC | J2: =Paysheet!BY4 -> Zvishavane | K2: =Paysheet!BZ4 -> 4591712639586 | L2: =Paysheet!BL4 -> 1103.1008
A3: 2 | B3: =Paysheet!A5 -> AES-E049 | C3: =Paysheet!B5 -> Marvellous | D3: =Paysheet!C5 -> Chakanetsa | E3: =Paysheet!BU5 -> FBC | F3: =Paysheet!BV5 -> Zvishavane | G3: =Paysheet!BW5 -> 6276992244264 | H3: =Paysheet!BM5 -> 20356.551 | I3: =Paysheet!BX5 -> FBC | J3: =Paysheet!BY5 -> Zvishavane | K3: =Paysheet!BZ5 -> 6563946412917 | L3: =Paysheet!BL5 -> 464.29592
A4: 3 | B4: =Paysheet!A6 -> AES-E022 | C4: =Paysheet!B6 -> Obvious | D4: =Paysheet!C6 -> Mpofu | E4: =Paysheet!BU6 -> FBC | F4: =Paysheet!BV6 -> VIRTUAL | G4: =Paysheet!BW6 -> 2760919825741 | H4: =Paysheet!BM6 -> 17106.286 | I4: =Paysheet!BX6 -> FBC | J4: =Paysheet!BY6 -> VIRTUAL | K4: =Paysheet!BZ6 -> 9900087728107 | L4: =Paysheet!BL6 -> 585.91219
A5: 4 | B5: =Paysheet!A7 -> AES-E035 | C5: =Paysheet!B7 -> Polite | D5: =Paysheet!C7 -> Mudarikwa | E5: =Paysheet!BU7 -> FBC | F5: =Paysheet!BV7 -> Zvishavane | G5: =Paysheet!BW7 -> 5298743732931 | H5: =Paysheet!BM7 -> 10734.852 | I5: =Paysheet!BX7 -> FBC | J5: =Paysheet!BY7 -> Zvishavane | K5: =Paysheet!BZ7 -> 6013813941202 | L5: =Paysheet!BL7 -> 346.69953
A6: 5 | B6: =Paysheet!A8 -> AES-E041 | C6: =Paysheet!B8 -> Chenai | D6: =Paysheet!C8 -> Runesu | E6: =Paysheet!BU8 -> FBC | F6: =Paysheet!BV8 -> Zvishavane | G6: =Paysheet!BW8 -> 2823915366343 | H6: =Paysheet!BM8 -> 16611.625 | I6: =Paysheet!BX8 -> FBC | J6: =Paysheet!BY8 -> Zvishavane | K6: =Paysheet!BZ8 -> 5652026357519 | L6: =Paysheet!BL8 -> 494.70387
A7: 6 | B7: =Paysheet!A9 -> AES-E033 | C7: =Paysheet!B9 -> Tafadzwa | D7: =Paysheet!C9 -> Mafukidze | E7: =Paysheet!BU9 -> FBC | F7: =Paysheet!BV9 -> Zvishavane | G7: =Paysheet!BW9 -> 5957561986265 | H7: =Paysheet!BM9 -> 7442.2597 | I7: =Paysheet!BX9 -> FBC | J7: =Paysheet!BY9 -> Zvishavane | K7: =Paysheet!BZ9 -> 4704859533483 | L7: =Paysheet!BL9 -> 257.17677
A8: 7 | B8: =Paysheet!A10 -> AES-E034 | C8: =Paysheet!B10 -> Kudzai | D8: =Paysheet!C10 -> Gwatidzo | E8: =Paysheet!BU10 -> FBC | F8: =Paysheet!BV10 -> Zvishavane | G8: =Paysheet!BW10 -> 9596400274673 | H8: =Paysheet!BM10 -> 9605.0923 | I8: =Paysheet!BX10 -> FBC | J8: =Paysheet!BY10 -> Zvishavane | K8: =Paysheet!BZ10 -> 2623715817487 | L8: =Paysheet!BL10 -> 358.81385
A9: 8 | B9: =Paysheet!A11 -> AES-E036 | C9: =Paysheet!B11 -> Dadirai | D9: =Paysheet!C11 -> Nyakudya | E9: =Paysheet!BU11 -> FBC | F9: =Paysheet!BV11 -> Zvishavane | G9: =Paysheet!BW11 -> 6866940554958 | H9: =Paysheet!BM11 -> 3590.5651 | I9: =Paysheet!BX11 -> FBC | J9: =Paysheet!BY11 -> Zvishavane | K9: =Paysheet!BZ11 -> 3301119435213 | L9: =Paysheet!BL11 -> 142.22904
A10: 10 | B10: =Paysheet!A12 -> AES-E037 | C10: =Paysheet!B12 -> Tarisai | D10: =Paysheet!C12 -> Chidzambwa | E10: =Paysheet!BU12 -> FBC | F10: =Paysheet!BV12 -> Zvishavane | G10: =Paysheet!BW12 -> 8523518553916 | H10: =Paysheet!BM12 -> 4375.9498 | I10: =Paysheet!BX12 -> FBC | J10: =Paysheet!BY12 -> Zvishavane | K10: =Paysheet!BZ12 -> 1169912801200 | L10: =Paysheet!BL12 -> 142.22904
A11: 11 | B11: =Paysheet!A13 -> AES-E015 | C11: =Paysheet!B13 -> Believe | D11: =Paysheet!C13 -> Mhererwa | E11: =Paysheet!BU13 -> FBC | F11: =Paysheet!BV13 -> Zvishavane | G11: =Paysheet!BW13 -> 1633703484987 | H11: =Paysheet!BM13 -> 5146.19 | I11: =Paysheet!BX13 -> FBC | J11: =Paysheet!BY13 -> Zvishavane | K11: =Paysheet!BZ13 -> 7497575109867 | L11: =Paysheet!BL13 -> 30.423577
A12: 12 | B12: =Paysheet!A14 -> AES-E016 | C12: =Paysheet!B14 -> Shingai | D12: =Paysheet!C14 -> Rusike | E12: =Paysheet!BU14 -> FBC | F12: =Paysheet!BV14 -> Zvishavane | G12: =Paysheet!BW14 -> 1734986781954 | H12: =Paysheet!BM14 -> 4748.0045 | I12: =Paysheet!BX14 -> FBC | J12: =Paysheet!BY14 -> Zvishavane | K12: =Paysheet!BZ14 -> 7413710132455 | L12: =Paysheet!BL14 -> 138.16763
A13: 14 | B13: =Paysheet!A15 -> AES-E018 | C13: =Paysheet!B15 -> Gamuchirai | D13: =Paysheet!C15 -> Chirenda | E13: =Paysheet!BU15 -> FBC | F13: =Paysheet!BV15 -> Zvishavane | G13: =Paysheet!BW15 -> 2811045688826 | H13: =Paysheet!BM15 -> 4679.7545 | I13: =Paysheet!BX15 -> FBC | J13: =Paysheet!BY15 -> Zvishavane | K13: =Paysheet!BZ15 -> 8150582443075 | L13: =Paysheet!BL15 -> 138.16763
... A27: 28 | B27: =Paysheet!A29 -> AES-E017 | C27: =Paysheet!B29 -> Ropafadzo | D27: =Paysheet!C29 -> Mangwende | E27: =Paysheet!BU29 -> FBC | F27: =Paysheet!BV29 -> Zvishavane | G27: =Paysheet!BW29 -> 4503862507510 | H27: =Paysheet!BM29 -> 5074.9143 | I27: =Paysheet!BX29 -> FBC | J27: =Paysheet!BY29 -> Zvishavane | K27: =Paysheet!BZ29 -> 1430129610059 | L27: =Paysheet!BL29 -> 135.48248
A28: 29 | B28: =Paysheet!A30 -> AES-E042 | C28: =Paysheet!B30 -> Vimbai | D28: =Paysheet!C30 -> Mpofu | E28: =Paysheet!BU30 -> NEDBANK | F28: =Paysheet!BV30 -> Zvishavane | G28: =Paysheet!BW30 -> 67790572388 | H28: =Paysheet!BM30 -> 5766.4395 | I28: =Paysheet!BX30 -> FBC | J28: =Paysheet!BY30 -> Zvishavane | K28: =Paysheet!BZ30 -> 0 | L28: 0
A29: 30 | B29: =paysheet!#ref! -> #NAME? | C29: =paysheet!#ref! -> #NAME? | D29: =paysheet!#ref! -> #NAME? | E29: =paysheet!#ref! -> #NAME? | F29: =paysheet!#ref! -> #NAME? | G29: =paysheet!#ref! -> #NAME? | H29: =paysheet!#ref! -> #NAME? | I29: =paysheet!#ref! -> #NAME? | ... L29: =paysheet!#ref! -> #NAME?
A30: 31 | B30: =Paysheet!A31 -> AES-E012 | C30: =Paysheet!B31 -> Batsirai | D30: =Paysheet!C31 -> Gwenzi | E30: =Paysheet!BU31 -> FBC | F30: =Paysheet!BV31 -> Zvishavane | G30: =Paysheet!BW31 -> 8028689830037 | H30: =Paysheet!BM31 -> 6890.0425 | I30: =Paysheet!BX31 -> FBC | J30: =Paysheet!BY31 -> Zvishavane | K30: =Paysheet!BZ31 -> 3595208151988 | L30: =Paysheet!BL31 -> 211.0479
A31: 32 | B31: =Paysheet!A32 -> AES-E020 | C31: =Paysheet!B32 -> Tonderayi | D31: =Paysheet!C32 -> Nyamande | E31: =Paysheet!BU32 -> FBC | F31: =Paysheet!BV32 -> Zvishavane | G31: =Paysheet!BW32 -> 4093316368647 | H31: =Paysheet!BM32 -> 5152.5192 | I31: =Paysheet!BX32 -> FBC | J31: =Paysheet!BY32 -> Zvishavane | K31: =Paysheet!BZ32 -> 1882463522262 | L31: =Paysheet!BL32 -> 150.66763
A32: 33 | B32: =Paysheet!A33 -> AES-E021 | C32: =Paysheet!B33 -> Kudzai | D32: =Paysheet!C33 -> Ziyambi | E32: =Paysheet!BU33 -> FBC | F32: =Paysheet!BV33 -> Zvishavane | G32: =Paysheet!BW33 -> 9881528598830 | H32: =Paysheet!BM33 -> 6416.4325 | I32: =Paysheet!BX33 -> FBC | J32: =Paysheet!BY33 -> Zvishavane | K32: =Paysheet!BZ33 -> 9353116515888 | L32: =Paysheet!BL33 -> 186.56822
A33: 34 | B33: =Paysheet!A34 -> AES-E027 | C33: =Paysheet!B34 -> Munashe | D33: =Paysheet!C34 -> Makoni | E33: =Paysheet!BU34 -> FBC | F33: =Paysheet!BV34 -> VIRTUAL | G33: =Paysheet!BW34 -> 9523454080915 | H33: =Paysheet!BM34 -> 5146.19 | I33: FBC | J33: VIRTUAL | K33: =Paysheet!BZ34 -> 5207464846825 | L33: =Paysheet!BL34 -> 137.92358
A34: 40 | B34: =Paysheet!A35 -> AES-E029 | C34: =Paysheet!B35 -> Kudzai | D34: =Paysheet!C35 -> Mutsvairo | E34: =Paysheet!BU35 -> FBC | F34: =Paysheet!BV35 -> VIRTUAL | G34: =Paysheet!BW35 -> 5777010775412 | H34: =Paysheet!BM35 -> 5139.8611 | I34: FBC | J34: =Paysheet!BY35 -> Zvishavane | K34: =Paysheet!BZ35 -> 6623554644664 | L34: =Paysheet!BL35 -> 137.67952
A35: 41 | B35: =Paysheet!A36 -> AES-E028 | C35: =Paysheet!B36 -> Tsitsi | D35: =Paysheet!C36 -> Chibanda | E35: =Paysheet!BU36 -> FBC | F35: =Paysheet!BV36 -> VIRTUAL | G35: =Paysheet!BW36 -> 7735501980632 | H35: =Paysheet!BM36 -> 4905.9108 | I35: FBC | J35: =Paysheet!BY36 -> VIRTUAL | K35: =Paysheet!BZ36 -> 3687335051761 | L35: =Paysheet!BL36 -> 128.64113
A36: 42 | B36: =Paysheet!A37 -> AES-E030 | C36: =Paysheet!B37 -> Tichaona | D36: =Paysheet!C37 -> Bere | E36: =Paysheet!BU37 -> FBC | F36: =Paysheet!BV37 -> VIRTUAL | G36: =Paysheet!BW37 -> 4765425398414 | H36: =Paysheet!BM37 -> 6422.8007 | I36: FBC | J36: =Paysheet!BY37 -> VIRTUAL | K36: =Paysheet!BZ37 -> 8297425296721 | L36: =Paysheet!BL37 -> 186.81081
A37: 43 | B37: =Paysheet!A38 -> AES-E031 | C37: =Paysheet!B38 -> Nyarai | D37: =Paysheet!C38 -> Chikomo | E37: =Paysheet!BU38 -> FBC | F37: =Paysheet!BV38 -> VIRTUAL | G37: =Paysheet!BW38 -> 6821431312058 | H37: =Paysheet!BM38 -> 5152.5192 | I37: FBC | J37: =Paysheet!BY38 -> VIRTUAL | K37: =Paysheet!BZ38 -> 9197128097883 | L37: =Paysheet!BL38 -> 138.16763
A38: 44 | B38: =Paysheet!A39 -> AES-E023 | C38: =Paysheet!B39 -> Tawanda | D38: =Paysheet!C39 -> Svosve | E38: =Paysheet!BU39 -> FBC | F38: =Paysheet!BV39 -> Zvishavane | G38: =Paysheet!BW39 -> 2097002397231 | H38: =Paysheet!BM39 -> 5222.1589 | I38: FBC | J38: =Paysheet!BY39 -> Zvishavane | K38: =Paysheet!BZ39 -> 7852277339807 | L38: =Paysheet!BL39 -> 153.35146
A39: 45 | B39: =Paysheet!A40 -> AES-E024 | C39: =Paysheet!B40 -> Gamuchirai | D39: =Paysheet!C40 -> Mukanya | E39: =Paysheet!BU40 -> FBC | F39: =Paysheet!BV40 -> VIRTUAL | G39: =Paysheet!BW40 -> 1346584632174 | H39: =Paysheet!BM40 -> 5222.1589 | I39: FBC | J39: =Paysheet!BY40 -> VIRTUAL | K39: =Paysheet!BZ40 -> 9389704853172 | L39: =Paysheet!BL40 -> 153.35146
B40: =Paysheet!A41 -> AES-E025 | C40: =Paysheet!B41 -> Rutendo | D40: =Paysheet!C41 -> Mhike | E40: =Paysheet!BU41 -> FBC | F40: =Paysheet!BV41 -> Zvishavane | G40: =Paysheet!BW41 -> 6254255795580 | H40: =Paysheet!BM41 -> 5053.9832 | I40: FBC | J40: =Paysheet!BY41 -> Zvishavane | K40: =Paysheet!BZ41 -> 7862298922749 | L40: =Paysheet!BL41 -> 136.02256
B41: =Paysheet!A42 -> AES-E026 | C41: =Paysheet!B42 -> Brighton | D41: =Paysheet!C42 -> Chinamasa2Z | E41: =Paysheet!BU42 -> FBC | F41: =Paysheet!BV42 -> Zvishavane | G41: =Paysheet!BW42 -> 9586586831180 | H41: =Paysheet!BM42 -> 3337.8247 | I41: FBC | J41: =Paysheet!BY42 -> Zvishavane | K41: =Paysheet!BZ42 -> 5798420878399 | L41: =Paysheet!BL42 -> 99.28592
C42: Oripa | D42: Shereni | I42: FBC | J42: Zvishavane | K42: 2473290184959 | L42: =Paysheet!BL30 -> 50.596496
C43: Edwin | D43: Mutangara | I43: Banc Abc | J43: Zvishavane | K43: 14451584333025 | L43: 120
C44: Alice | D44: Madamombe | E44: POSB | F44: Zvishavane | G44: 6048451010387997 | H44: =Paysheet!BC18 -> 533.902 | M44: Nhira
C45: Pretty | D45: Chibove | E45: POSB | F45: Zvishavane | G45: 570912023998 | H45: =Paysheet!BC30 -> 0 | I45: POSB | J45: Zvishavane | K45: 299551475357 | L45: =Paysheet!BD30-50 -> 70 | M45: Vimbai Mpofu
C46: Soliwe | D46: Gumbo | E46: Main Byo | F46: Zvishavane | G46: 383683812395 | H46: 0 | M46: kasaira
C47: Loveness | D47: Nhingo | E47: FBC | F47: Gweru BS | G47: 6756884415347 | H47: =Paysheet!BC29 -> 8.0002358 | M47: Ropafadzo vunganai
C48: Shylet | D48: R. Mzezewa | E48: POSB | F48: Zvishavane | G48: 599125280348 | H48: 0 | I48: POSB | J48: Zvishavane | K48: 470770979513 | L48: =Paysheet!BD30-70 -> 50 | M48: Vimbai Mpofu
C49: Nyaradzo Funeral | E49: STANBIC | F49: Parklane | G49: 5893596084836 | H49: =Nyaradzo!F33 -> 16906.705
H52: =SUM(H2:H51) -> #NAME? | L52: =SUM(L2:L51) -> #NAME?
D54: =16*7 -> 112

Sheet NSSA
D2: USD | E2: ZWL | F2: USD | G2: ZWL | H2: USD | I2: ZWL
B3: Netsai | C3: Nhemachena | D3: Employee Contribution | F3: Employer Contribution | H3: Total
A4: =Paysheet!A4 -> AES-E046 | B4: =Paysheet!B4 -> Tarisai | C4: =Paysheet!C4 -> Zinyama | D4: =Paysheet!AJ4 -> 15.608991 | E4: =Paysheet!AK4 -> 333.34686 | F4: =D4 -> 15.608991 | G4: =E4 -> 333.34686 | H4: =D4+F4 -> 31.217982 | I4: =E4+G4 -> 666.69372
A5: =Paysheet!A5 -> AES-E049 | B5: =Paysheet!B5 -> Marvellous | C5: =Paysheet!C5 -> Chakanetsa | D5: =Paysheet!AJ5 -> 15.608991 | E5: =Paysheet!AK5 -> 333.34686 | F5: =D5 -> 15.608991 | G5: =E5 -> 333.34686 | H5: =D5+F5 -> 31.217982 | I5: =E5+G5 -> 666.69372
A6: =Paysheet!A6 -> AES-E022 | B6: =Paysheet!B6 -> Obvious | C6: =Paysheet!C6 -> Mpofu | D6: =Paysheet!AJ6 -> 15.608991 | E6: =Paysheet!AK6 -> 333.34686 | F6: =D6 -> 15.608991 | G6: =E6 -> 333.34686 | H6: =D6+F6 -> 31.217982 | I6: =E6+G6 -> 666.69372
A7: =Paysheet!A7 -> AES-E035 | B7: =Paysheet!B7 -> Polite | C7: =Paysheet!C7 -> Mudarikwa | D7: =Paysheet!AJ7 -> 15.608991 | E7: =Paysheet!AK7 -> 333.34686 | F7: =D7 -> 15.608991 | G7: =E7 -> 333.34686 | H7: =D7+F7 -> 31.217982 | I7: =E7+G7 -> 666.69372
A8: =Paysheet!A8 -> AES-E041 | B8: =Paysheet!B8 -> Chenai | C8: =Paysheet!C8 -> Runesu | D8: =Paysheet!AJ8 -> 15.608991 | E8: =Paysheet!AK8 -> 333.34686 | F8: =D8 -> 15.608991 | G8: =E8 -> 333.34686 | H8: =D8+F8 -> 31.217982 | I8: =E8+G8 -> 666.69372
A9: =Paysheet!A9 -> AES-E033 | B9: =Paysheet!B9 -> Tafadzwa | C9: =Paysheet!C9 -> Mafukidze | D9: =Paysheet!AJ9 -> 13.104 | E9: =Paysheet!AK9 -> 279.85007 | F9: =D9 -> 13.104 | G9: =E9 -> 279.85007 | H9: =D9+F9 -> 26.208 | I9: =E9+G9 -> 559.70014
A10: =Paysheet!A10 -> AES-E034 | B10: =Paysheet!B10 -> Kudzai | C10: =Paysheet!C10 -> Gwatidzo | D10: =Paysheet!AJ10 -> 13.104 | E10: =Paysheet!AK10 -> 279.85007 | F10: =D10 -> 13.104 | G10: =E10 -> 279.85007 | H10: =D10+F10 -> 26.208 | I10: =E10+G10 -> 559.70014
A11: =Paysheet!A11 -> AES-E036 | B11: =Paysheet!B11 -> Dadirai | C11: =Paysheet!C11 -> Nyakudya | D11: =Paysheet!AJ11 -> 7.5816 | E11: =Paysheet!AK11 -> 161.91326 | F11: =D11 -> 7.5816 | G11: =E11 -> 161.91326 | H11: =D11+F11 -> 15.1632 | I11: =E11+G11 -> 323.82651
A12: =Paysheet!A12 -> AES-E037 | B12: =Paysheet!B12 -> Tarisai | C12: =Paysheet!C12 -> Chidzambwa | D12: =Paysheet!AJ12 -> 7.5816 | E12: =Paysheet!AK12 -> 161.91326 | F12: =D12 -> 7.5816 | G12: =E12 -> 161.91326 | H12: =D12+F12 -> 15.1632 | I12: =E12+G12 -> 323.82651
A13: =Paysheet!A13 -> AES-E015 | B13: =Paysheet!B13 -> Believe | C13: =Paysheet!C13 -> Mhererwa | D13: =Paysheet!AJ13 -> 7.5816 | E13: =Paysheet!AK13 -> 161.91326 | F13: =D13 -> 7.5816 | G13: =E13 -> 161.91326 | H13: =D13+F13 -> 15.1632 | I13: =E13+G13 -> 323.82651
A14: =Paysheet!A14 -> AES-E016 | B14: =Paysheet!B14 -> Shingai | C14: =Paysheet!C14 -> Rusike | D14: =Paysheet!AJ14 -> 7.5816 | E14: =Paysheet!AK14 -> 161.91326 | F14: =D14 -> 7.5816 | G14: =E14 -> 161.91326 | H14: =D14+F14 -> 15.1632 | I14: =E14+G14 -> 323.82651
A15: =Paysheet!A15 -> AES-E018 | B15: =Paysheet!B15 -> Gamuchirai | C15: =Paysheet!C15 -> Chirenda | D15: =Paysheet!AJ15 -> 7.5816 | E15: =Paysheet!AK15 -> 161.91326 | F15: =D15 -> 7.5816 | G15: =E15 -> 161.91326 | H15: =D15+F15 -> 15.1632 | I15: =E15+G15 -> 323.82651
... A30: =Paysheet!A30 -> AES-E042 | B30: =Paysheet!B30 -> Vimbai | C30: =Paysheet!C30 -> Mpofu | D30: =Paysheet!AJ30 -> 8.2368 | E30: =Paysheet!AK30 -> 175.90576 | F30: =D30 -> 8.2368 | G30: =E30 -> 175.90576 | H30: =D30+F30 -> 16.4736 | I30: =E30+G30 -> 351.81152
A31: =paysheet!#ref! -> #NAME? | B31: =paysheet!#ref! -> #NAME? | C31: =paysheet!#ref! -> #NAME? | D31: =paysheet!#ref! -> #NAME? | E31: =paysheet!#ref! -> #NAME? | F31: =D31 -> #NAME? | G31: =E31 -> #NAME? | H31: =D31+F31 -> #NAME? | I31: =E31+G31 -> #NAME?
A32: =Paysheet!A31 -> AES-E012 | B32: =Paysheet!B31 -> Batsirai | C32: =Paysheet!C31 -> Gwenzi | D32: =Paysheet!AJ31 -> 7.5816 | E32: =Paysheet!AK31 -> 161.91326 | F32: =D32 -> 7.5816 | G32: =E32 -> 161.91326 | H32: =D32+F32 -> 15.1632 | I32: =E32+G32 -> 323.82651
A33: =Paysheet!A32 -> AES-E020 | B33: =Paysheet!B32 -> Tonderayi | C33: =Paysheet!C32 -> Nyamande | D33: =Paysheet!AJ32 -> 7.5816 | E33: =Paysheet!AK32 -> 161.91326 | F33: =D33 -> 7.5816 | G33: =E33 -> 161.91326 | H33: =D33+F33 -> 15.1632 | I33: =E33+G33 -> 323.82651
A34: =Paysheet!A33 -> AES-E021 | B34: =Paysheet!B33 -> Kudzai | C34: =Paysheet!C33 -> Ziyambi | D34: =Paysheet!AJ33 -> 7.5816 | E34: =Paysheet!AK33 -> 161.91326 | F34: =D34 -> 7.5816 | G34: =E34 -> 161.91326 | H34: =D34+F34 -> 15.1632 | I34: =E34+G34 -> 323.82651
A35: =Paysheet!A34 -> AES-E027 | B35: =Paysheet!B34 -> Munashe | C35: =Paysheet!C34 -> Makoni | D35: =Paysheet!AJ34 -> 7.5816 | E35: =Paysheet!AK34 -> 161.91326 | F35: =D35 -> 7.5816 | G35: =E35 -> 161.91326 | H35: =D35+F35 -> 15.1632 | I35: =E35+G35 -> 323.82651
A36: =Paysheet!A35 -> AES-E029 | B36: =Paysheet!B35 -> Kudzai | C36: =Paysheet!C35 -> Mutsvairo | D36: =Paysheet!AJ35 -> 7.5816 | E36: =Paysheet!AK35 -> 161.91326 | F36: =D36 -> 7.5816 | G36: =E36 -> 161.91326 | H36: =D36+F36 -> 15.1632 | I36: =E36+G36 -> 323.82651
A37: =Paysheet!A36 -> AES-E028 | B37: =Paysheet!B36 -> Tsitsi | C37: =Paysheet!C36 -> Chibanda | D37: =Paysheet!AJ36 -> 7.5816 | E37: =Paysheet!AK36 -> 161.91326 | F37: =D37 -> 7.5816 | G37: =E37 -> 161.91326 | H37: =D37+F37 -> 15.1632 | I37: =E37+G37 -> 323.82651
A38: =Paysheet!A37 -> AES-E030 | B38: =Paysheet!B37 -> Tichaona | C38: =Paysheet!C37 -> Bere | D38: =Paysheet!AJ37 -> 7.5816 | E38: =Paysheet!AK37 -> 161.91326 | F38: =D38 -> 7.5816 | G38: =E38 -> 161.91326 | H38: =D38+F38 -> 15.1632 | I38: =E38+G38 -> 323.82651
A39: =Paysheet!A38 -> AES-E031 | B39: =Paysheet!B38 -> Nyarai | C39: =Paysheet!C38 -> Chikomo | D39: =Paysheet!AJ38 -> 7.5816 | E39: =Paysheet!AK38 -> 161.91326 | F39: =D39 -> 7.5816 | G39: =E39 -> 161.91326 | H39: =D39+F39 -> 15.1632 | I39: =E39+G39 -> 323.82651
A40: =Paysheet!A39 -> AES-E023 | B40: =Paysheet!B39 -> Tawanda | C40: =Paysheet!C39 -> Svosve | D40: =Paysheet!AJ39 -> 7.5816 | E40: =Paysheet!AK39 -> 161.91326 | F40: =D40 -> 7.5816 | G40: =E40 -> 161.91326 | H40: =D40+F40 -> 15.1632 | I40: =E40+G40 -> 323.82651
A41: =Paysheet!A40 -> AES-E024 | B41: =Paysheet!B40 -> Gamuchirai | C41: =Paysheet!C40 -> Mukanya | D41: =Paysheet!AJ40 -> 7.5816 | E41: =Paysheet!AK40 -> 161.91326 | F41: =D41 -> 7.5816 | G41: =E41 -> 161.91326 | H41: =D41+F41 -> 15.1632 | I41: =E41+G41 -> 323.82651
A42: =Paysheet!A41 -> AES-E025 | B42: =Paysheet!B41 -> Rutendo | C42: =Paysheet!C41 -> Mhike | D42: =Paysheet!AJ41 -> 7.29 | E42: =Paysheet!AK41 -> 155.68582 | F42: =D42 -> 7.29 | G42: =E42 -> 155.68582 | H42: =D42+F42 -> 14.58 | I42: =E42+G42 -> 311.37165
A43: =Paysheet!A42 -> AES-E026 | B43: =Paysheet!B42 -> Brighton | C43: =Paysheet!C42 -> Chinamasa2Z | D43: =Paysheet!AJ42 -> 4.374 | E43: =Paysheet!AK42 -> 93.411494 | F43: =D43 -> 4.374 | G43: =E43 -> 93.411494 | H43: =D43+F43 -> 8.748 | I43: =E43+G43 -> 186.82299
A44: =Paysheet!A43 -> AES-E032 | B44: =Paysheet!B43 -> Mazvita | C44: =Paysheet!C43 -> Mhererwa | D44: =Paysheet!AJ43 -> 7.5816 | E44: =Paysheet!AK43 -> 161.91326 | F44: =D44 -> 7.5816 | G44: =E44 -> 161.91326 | H44: =D44+F44 -> 15.1632 | I44: =E44+G44 -> 323.82651
A45: =Paysheet!A44 -> 0
D46: =SUM(D4:D44) -> #NAME? | E46: =SUM(E4:E44) -> #NAME? | F46: =SUM(F4:F44) -> #NAME? | G46: =SUM(G4:G44) -> #NAME? | H46: =SUM(H4:H44) -> #NAME? | I46: =SUM(I4:I44) -> #NAME?
G47: WCIF | H47: =H46*0.0177 -> #NAME? | I47: =I46*0.0177 -> #NAME?
G48: Payable | H48: =H46+H47 -> #NAME? | I48: =I46+I47 -> #NAME?
G51: Total Employer | H51: =F46+H47 -> #NAME? | I51: =E46+I47 -> #NAME?

Sheet PAYE
A1: Details | D1: USD | G1: ZWL
B2: Netsai | C2: Nhemachena | D2: PAYE | E2: AIDS LEVY | F2: Total | G2: PAYE | H2: AIDS LEVY | I2: Total
A3: =Paysheet!A4 -> AES-E046 | B3: =Paysheet!B4 -> Tarisai | C3: =Paysheet!C4 -> Zinyama | D3: =Paysheet!AU4 -> 431.42929 | E3: =Paysheet!AV4 -> 12.942879 | F3: =D3+E3 -> 444.37216 | G3: =Paysheet!AW4 -> 13005.136 | H3: =Paysheet!AX4 -> 390.15407 | I3: =G3+H3 -> 13395.29
A4: =Paysheet!A5 -> AES-E049 | B4: =Paysheet!B5 -> Marvellous | C4: =Paysheet!C5 -> Chakanetsa | D4: =Paysheet!AU5 -> 160.67484 | E4: =Paysheet!AV5 -> 4.8202453 | F4: =D4+E4 -> 165.49509 | G4: =Paysheet!AW5 -> 7099.6041 | H4: =Paysheet!AX5 -> 212.98812 | I4: =G4+H4 -> 7312.5922
A5: =Paysheet!A6 -> AES-E022 | B5: =Paysheet!B6 -> Obvious | C5: =Paysheet!C6 -> Mpofu | D5: =Paysheet!AU6 -> 202.58138 | E5: =Paysheet!AV6 -> 6.0774413 | F5: =D5+E5 -> 208.65882 | G5: =Paysheet!AW6 -> 6217.6371 | H5: =Paysheet!AX6 -> 186.52911 | I5: =G5+H5 -> 6404.1662
A6: =Paysheet!A7 -> AES-E035 | B6: =Paysheet!B7 -> Polite | C6: =Paysheet!C7 -> Mudarikwa | D6: =Paysheet!AU7 -> 101.13735 | E6: =Paysheet!AV7 -> 3.0341206 | F6: =D6+E6 -> 104.17148 | G6: =Paysheet!AW7 -> 3359.4147 | H6: =Paysheet!AX7 -> 100.78244 | I6: =G6+H6 -> 3460.1971
A7: =Paysheet!A8 -> AES-E041 | B7: =Paysheet!B8 -> Chenai | C7: =Paysheet!C8 -> Runesu | D7: =Paysheet!AU8 -> 161.99528 | E7: =Paysheet!AV8 -> 4.8598583 | F7: =D7+E7 -> 166.85513 | G7: =Paysheet!AW8 -> 5753.8404 | H7: =Paysheet!AX8 -> 172.61521 | I7: =G7+H7 -> 5926.4556
A8: =Paysheet!A9 -> AES-E033 | B8: =Paysheet!B9 -> Tafadzwa | C8: =Paysheet!C9 -> Mafukidze | D8: =Paysheet!AU9 -> 68.67886 | E8: =Paysheet!AV9 -> 2.0603658 | F8: =D8+E8 -> 70.739226 | G8: =Paysheet!AW9 -> 2073.3427 | H8: =Paysheet!AX9 -> 62.200282 | I8: =G8+H8 -> 2135.543
A9: =Paysheet!A10 -> AES-E034 | B9: =Paysheet!B10 -> Kudzai | C9: =Paysheet!C10 -> Gwatidzo | D9: =Paysheet!AU10 -> 98.33218 | E9: =Paysheet!AV10 -> 2.9499654 | F9: =D9+E9 -> 101.28215 | G9: =Paysheet!AW10 -> 2879.1792 | H9: =Paysheet!AX10 -> 86.375376 | I9: =G9+H9 -> 2965.5546
A10: =Paysheet!A11 -> AES-E036 | B10: =Paysheet!B11 -> Dadirai | C10: =Paysheet!C11 -> Nyakudya | D10: =Paysheet!AU11 -> 25.989669 | E10: =Paysheet!AV11 -> 0.77969007 | F10: =D10+E10 -> 26.769359 | G10: =Paysheet!AW11 -> 799.62211 | H10: =Paysheet!AX11 -> 23.988663 | I10: =G10+H10 -> 823.61078
A11: =Paysheet!A12 -> AES-E037 | B11: =Paysheet!B12 -> Tarisai | C11: =Paysheet!C12 -> Chidzambwa | D11: =Paysheet!AU12 -> 25.989669 | E11: =Paysheet!AV12 -> 0.77969007 | F11: =D11+E11 -> 26.769359 | G11: =Paysheet!AW12 -> 799.62211 | H11: =Paysheet!AX12 -> 23.988663 | I11: =G11+H11 -> 823.61078
A12: =Paysheet!A13 -> AES-E015 | B12: =Paysheet!B13 -> Believe | C12: =Paysheet!C13 -> Mhererwa | D12: =Paysheet!AU13 -> 29.987207 | E12: =Paysheet!AV13 -> 0.89961621 | F12: =D12+E12 -> 30.886823 | G12: =Paysheet!AW13 -> 1025.9021 | H12: =Paysheet!AX13 -> 30.777063 | I12: =G12+H12 -> 1056.6792
A13: =Paysheet!A14 -> AES-E016 | B13: =Paysheet!B14 -> Shingai | C13: =Paysheet!C14 -> Rusike | D13: =Paysheet!AU14 -> 30.064829 | E13: =Paysheet!AV14 -> 0.90194488 | F13: =D13+E13 -> 30.966774 | G13: =Paysheet!AW14 -> 1028.1546 | H13: =Paysheet!AX14 -> 30.844637 | I13: =G13+H13 -> 1058.9992
A14: =Paysheet!A15 -> AES-E018 | B14: =Paysheet!B15 -> Gamuchirai | C14: =Paysheet!C15 -> Chirenda | D14: =Paysheet!AU15 -> 30.064829 | E14: =Paysheet!AV15 -> 0.90194488 | F14: =D14+E14 -> 30.966774 | G14: =Paysheet!AW15 -> 1028.1546 | H14: =Paysheet!AX15 -> 30.844637 | I14: =G14+H14 -> 1058.9992
... A29: =Paysheet!A30 -> AES-E042 | B29: =Paysheet!B30 -> Vimbai | C29: =Paysheet!C30 -> Mpofu | D29: =Paysheet!AU30 -> 36.639519 | E29: =Paysheet!AV30 -> 1.0991856 | F29: =D29+E29 -> 37.738704 | G29: =Paysheet!AW30 -> 1238.4754 | H29: =Paysheet!AX30 -> 37.154263 | I29: =G29+H29 -> 1275.6297
A30: =paysheet!#ref! -> #NAME? | B30: =paysheet!#ref! -> #NAME? | C30: =paysheet!#ref! -> #NAME? | D30: =paysheet!#ref! -> #NAME? | E30: =paysheet!#ref! -> #NAME? | F30: =D30+E30 -> #NAME? | G30: =paysheet!#ref! -> #NAME? | H30: =paysheet!#ref! -> #NAME? | I30: =G30+H30 -> #NAME?
A31: =Paysheet!A31 -> AES-E012 | B31: =Paysheet!B31 -> Batsirai | C31: =Paysheet!C31 -> Gwenzi | D31: =Paysheet!AU31 -> 53.676217 | E31: =Paysheet!AV31 -> 1.6102865 | F31: =D31+E31 -> 55.286503 | G31: =Paysheet!AW31 -> 1695.2281 | H31: =Paysheet!AX31 -> 50.856843 | I31: =G31+H31 -> 1746.0849
A32: =Paysheet!A32 -> AES-E020 | B32: =Paysheet!B32 -> Tonderayi | C32: =Paysheet!C32 -> Nyamande | D32: =Paysheet!AU32 -> 30.064829 | E32: =Paysheet!AV32 -> 0.90194488 | F32: =D32+E32 -> 30.966774 | G32: =Paysheet!AW32 -> 1028.1546 | H32: =Paysheet!AX32 -> 30.844637 | I32: =G32+H32 -> 1058.9992
A33: =Paysheet!A33 -> AES-E021 | B33: =Paysheet!B33 -> Kudzai | C33: =Paysheet!C33 -> Ziyambi | D33: =Paysheet!AU33 -> 45.672021 | E33: =Paysheet!AV33 -> 1.3701606 | F33: =D33+E33 -> 47.042182 | G33: =Paysheet!AW33 -> 1472.1157 | H33: =Paysheet!AX33 -> 44.16347 | I33: =G33+H33 -> 1516.2791
A34: =Paysheet!A34 -> AES-E027 | B34: =Paysheet!B34 -> Munashe | C34: =Paysheet!C34 -> Makoni | D34: =Paysheet!AU34 -> 29.987207 | E34: =Paysheet!AV34 -> 0.89961621 | F34: =D34+E34 -> 30.886823 | G34: =Paysheet!AW34 -> 1025.9021 | H34: =Paysheet!AX34 -> 30.777063 | I34: =G34+H34 -> 1056.6792
A35: =Paysheet!A35 -> AES-E029 | B35: =Paysheet!B35 -> Kudzai | C35: =Paysheet!C35 -> Mutsvairo | D35: =Paysheet!AU35 -> 29.909595 | E35: =Paysheet!AV35 -> 0.89728786 | F35: =D35+E35 -> 30.806883 | G35: =Paysheet!AW35 -> 1023.6494 | H35: =Paysheet!AX35 -> 30.709481 | I35: =G35+H35 -> 1054.3588
A36: =Paysheet!A36 -> AES-E028 | B36: =Paysheet!B36 -> Tsitsi | C36: =Paysheet!C36 -> Chibanda | D36: =Paysheet!AU36 -> 27.045896 | E36: =Paysheet!AV36 -> 0.81137687 | F36: =D36+E36 -> 27.857273 | G36: =Paysheet!AW36 -> 940.08568 | H36: =Paysheet!AX36 -> 28.20257 | I36: =G36+H36 -> 968.28825
A37: =Paysheet!A37 -> AES-E030 | B37: =Paysheet!B37 -> Tichaona | C37: =Paysheet!C37 -> Bere | D37: =Paysheet!AU37 -> 45.751062 | E37: =Paysheet!AV37 -> 1.3725319 | F37: =D37+E37 -> 47.123594 | G37: =Paysheet!AW37 -> 1474.3303 | H37: =Paysheet!AX37 -> 44.229908 | I37: =G37+H37 -> 1518.5602
A38: =Paysheet!A38 -> AES-E031 | B38: =Paysheet!B38 -> Nyarai | C38: =Paysheet!C38 -> Chikomo | D38: =Paysheet!AU38 -> 30.064829 | E38: =Paysheet!AV38 -> 0.90194488 | F38: =D38+E38 -> 30.966774 | G38: =Paysheet!AW38 -> 1028.1546 | H38: =Paysheet!AX38 -> 30.844637 | I38: =G38+H38 -> 1058.9992
A39: =Paysheet!A39 -> AES-E023 | B39: =Paysheet!B39 -> Tawanda | C39: =Paysheet!C39 -> Svosve | D39: =Paysheet!AU39 -> 30.919361 | E39: =Paysheet!AV39 -> 0.92758082 | F39: =D39+E39 -> 31.846942 | G39: =Paysheet!AW39 -> 1052.9135 | H39: =Paysheet!AX39 -> 31.587404 | I39: =G39+H39 -> 1084.5009
A40: =Paysheet!A40 -> AES-E024 | B40: =Paysheet!B40 -> Gamuchirai | C40: =Paysheet!C40 -> Mukanya | D40: =Paysheet!AU40 -> 30.919361 | E40: =Paysheet!AV40 -> 0.92758082 | F40: =D40+E40 -> 31.846942 | G40: =Paysheet!AW40 -> 1052.9135 | H40: =Paysheet!AX40 -> 31.587404 | I40: =G40+H40 -> 1084.5009
A41: =Paysheet!A41 -> AES-E025 | B41: =Paysheet!B41 -> Rutendo | C41: =Paysheet!C41 -> Mhike | D41: =Paysheet!AU41 -> 29.284892 | E41: =Paysheet!AV41 -> 0.87854675 | F41: =D41+E41 -> 30.163439 | G41: =Paysheet!AW41 -> 996.51762 | H41: =Paysheet!AX41 -> 29.895529 | I41: =G41+H41 -> 1026.4132
A42: =Paysheet!A42 -> AES-E026 | B42: =Paysheet!B42 -> Brighton | C42: =Paysheet!C42 -> Chinamasa2Z | D42: =Paysheet!AU42 -> 13.860272 | E42: =Paysheet!AV42 -> 0.41580817 | F42: =D42+E42 -> 14.27608 | G42: =Paysheet!AW42 -> 465.95891 | H42: =Paysheet!AX42 -> 13.978767 | I42: =G42+H42 -> 479.93767
A43: =Paysheet!A43 -> AES-E032 | B43: =Paysheet!B43 -> Mazvita | C43: =Paysheet!C43 -> Mhererwa | D43: =Paysheet!AU43 -> 30.919361 | E43: =Paysheet!AV43 -> 0.92758082 | F43: =D43+E43 -> 31.846942 | G43: =Paysheet!AW43 -> 1052.9135 | H43: =Paysheet!AX43 -> 31.587404 | I43: =G43+H43 -> 1084.5009
A44: =Paysheet!A44 -> 0
A45: =Paysheet!A45 -> 0
C48: Total | D48: =SUM(D3:D47) -> #NAME? | E48: =SUM(E3:E47) -> #NAME? | F48: =SUM(F3:F47) -> #NAME? | G48: =SUM(G3:G47) -> #NAME? | H48: =SUM(H3:H47) -> #NAME? | I48: =SUM(I3:I47) -> #NAME?

Sheet Nyaradzo
B1: Airflow Environmental Solutions (Pvt) Ltd
B2: Nyaradzo Group Policy Contributions schedule
B3: Month of February 2025
B6: Netsai | C6: Nhemachena | D6: Mine # | E6: Policy Number | F6: Amount
A7: 1 | B7: Tarisai | C7: Zinyama | D7: AESV70 | E7: AENS000031 | F7: ='Nyaradzo Workings'!F8 -> 1390.9
A8: 2 | B8: Marvellous | C8: Chakanetsa | D8: AES-E049 | E8: AENS000001 | F8: ='Nyaradzo Workings'!F9 -> 924.79
A9: 3 | B9: Obvious | C9: Mpofu | D9: AES-E022 | E9: AENS000035 | F9: ='Nyaradzo Workings'!F10 -> 1473.77
A10: 4 | B10: Polite | C10: Mudarikwa | D10: AES-E035 | E10: AENS000002 | F10: ='Nyaradzo Workings'!F11 -> 1410.01
A11: 5 | B11: Chenai | C11: Runesu | D11: AES-E041 | E11: AENS000004 | F11: ='Nyaradzo Workings'!F12 -> 1173.11
A12: 6 | B12: Tafadzwa | C12: Mafukidze | D12: AES-E033 | E12: AENS000005 | F12: ='Nyaradzo Workings'!F13 -> 912.56
A13: 7 | B13: Kudzai | C13: Gwatidzo | D13: AES-E034 | E13: AENS000032 | F13: ='Nyaradzo Workings'!F14 -> 981.11
A14: 8 | B14: Dadirai | C14: Nyakudya | D14: AES-E036 | E14: AENS000009 | F14: ='Nyaradzo Workings'!F15 -> 865.47
A15: 10 | B15: Shingai | C15: Rusike | D15: AES-E016 | E15: AENS000029 | F15: ='Nyaradzo Workings'!F16 -> 484.6
A16: 12 | B16: Kudakwashe | C16: Chinouriri | D16: AES-E014 | E16: AENS000012 | F16: ='Nyaradzo Workings'!F17 -> 552.85
A17: 13 | B17: Gamuchirai | C17: Chirenda | D17: AES-E018 | E17: AENS000022 | F17: ='Nyaradzo Workings'!F18 -> 552.85
A18: 14 | B18: Chido | C18: Chigumba | D18: AES-E013 | E18: AENS000023 | F18: ='Nyaradzo Workings'!F19 -> 396.54
... A29: 25 | B29: Clever | C29: Chakabva | D29: CA01 | E29: AENS000028 | F29: ='Nyaradzo Workings'!F30 -> 1017.56
B31: Total contributions | F31: =SUM(F7:F30) -> 17340.21
B32: Admini fees | F32: =-F31*(2.5/100) -> -433.50525
B33: Total Payable | F33: =F31+F32 -> 16906.705
B35: Prepared :
B36: Beaven | C36: ……………………………….. | E36: Accountant
B38: Verified
B39: B. Bonga | C39: ………………………………………. | E39: HR Manager
B42: Terminated Employees Effective 30 June 2024
A44: 1 | B44: Joshua | C44: Nemukuyu | D44: AESR96 | E44: AENS000025
A45: 2 | B45: Tinaye | C45: Gorejena | D45: AESV5 | E45: AENS000013
A46: 3 | B46: Mufaro | C46: Nemukuyu | D46: AES-E015 | E46: AENS000019
A47: 4 | B47: Believe | C47: Munetsi | D47: AESR146 | E47: AENS000021

Sheet Nyaradzo Workings
B2: Airflow Environmental Solutions (Pvt) Ltd
B3: Nyaradzo Group Policy Contributions schedule
B4: Month of February 2025 | H4: Rate | I4: =Paysheet!AQ1 -> 26.6951
H6: Company Contribution | J6: Employee Contribution
B7: Netsai | C7: Nhemachena | D7: Mine # | E7: Policy Number | F7: Amount | H7: USD | I7: ZWL | J7: USD | K7: ZIG
A8: 1 | B8: Tarisai | C8: Zinyama | D8: AESV70 | E8: AENS000031 | F8: 1390.9 | H8: 8 | I8: =H8*$I$4 -> 213.5608 | J8: 0 | K8: =F8-I8 -> 1177.3392
A9: 2 | B9: Marvellous | C9: Chakanetsa | D9: AES-E049 | E9: AENS000001 | F9: 924.79 | H9: 8 | I9: =H9*$I$4 -> 213.5608 | J9: 0 | K9: =F9-I9 -> 711.2292
A10: 3 | B10: Obvious | C10: Mpofu | D10: AES-E022 | E10: AENS000035 | F10: 1473.77 | H10: 8 | I10: =H10*$I$4 -> 213.5608 | J10: 0 | K10: =F10-I10 -> 1260.2092
A11: 4 | B11: Polite | C11: Mudarikwa | D11: AES-E035 | E11: AENS000002 | F11: 1410.01 | H11: 8 | I11: =H11*$I$4 -> 213.5608 | J11: 0 | K11: =F11-I11 -> 1196.4492
A12: 5 | B12: Chenai | C12: Runesu | D12: AES-E041 | E12: AENS000004 | F12: 1173.11 | H12: 8 | I12: =H12*$I$4 -> 213.5608 | J12: 0 | K12: =F12-I12 -> 959.5492
A13: 6 | B13: Tafadzwa | C13: Mafukidze | D13: AES-E033 | E13: AENS000005 | F13: 912.56 | H13: 8 | I13: =H13*$I$4 -> 213.5608 | J13: 0 | K13: =F13-I13 -> 698.9992
A14: 7 | B14: Kudzai | C14: Gwatidzo | D14: AES-E034 | E14: AENS000032 | F14: 981.11 | H14: 3 | I14: =H14*$I$4 -> 80.0853 | J14: 0 | K14: =F14-I14 -> 901.0247
A15: 8 | B15: Dadirai | C15: Nyakudya | D15: AES-E036 | E15: AENS000009 | F15: 865.47 | H15: 3 | I15: =H15*$I$4 -> 80.0853 | J15: 0 | K15: =F15-I15 -> 785.3847
A16: 10 | B16: Shingai | C16: Rusike | D16: AES-E016 | E16: AENS000029 | F16: 484.6 | H16: 3 | I16: =H16*$I$4 -> 80.0853 | J16: 0 | K16: =F16-I16 -> 404.5147
A17: 12 | B17: Kudakwashe | C17: Chinouriri | D17: AES-E014 | E17: AENS000012 | F17: 552.85 | H17: 3 | I17: =H17*$I$4 -> 80.0853 | J17: 0 | K17: =F17-I17 -> 472.7647
A18: 13 | B18: Gamuchirai | C18: Chirenda | D18: AES-E018 | E18: AENS000022 | F18: 552.85 | H18: 3 | I18: =H18*$I$4 -> 80.0853 | J18: 0 | K18: =F18-I18 -> 472.7647
A19: 14 | B19: Chido | C19: Chigumba | D19: AES-E013 | E19: AENS000023 | F19: 396.54 | H19: 3 | I19: =H19*$I$4 -> 80.0853 | J19: 0 | K19: =F19-I19 -> 316.4547
... A30: 25 | B30: Clever | C30: Chakabva | D30: CA01 | E30: AENS000028 | F30: 1017.56 | H30: 3 | I30: =H30*$I$4 -> 80.0853 | J30: 0 | K30: =F30-I30 -> 937.4747
H31: =SUM(H8:H30) -> 99 | I31: =SUM(I8:I30) -> 2642.8149 | J31: =SUM(J8:J30) -> 0 | K31: =SUM(K8:K30) -> 14697.395
B32: Total contributions | F32: =SUM(F8:F31) -> 17340.21
B33: Admini fees | F33: =-F32*(2.5/100) -> -433.50525
B34: Total Payable | F34: =F32+F33 -> 16906.705
B36: Prepared :
B37: B. Muchingami | C37: ………………………………..
B39: Aurthorized By:
B40: B. Chaderopa | C40: ………………………………………..

Sheet Zimdef
B1: Zimdef Shedule February 2025 | F1: NSSA | H1: MIPF | I1: Total | K1: ZIMDEF
A2: Works # | B2: Netsai | C2: Nhemachena | D2: Gross USD | E2: Gross ZIG | F2: USD | G2: ZIG | H2: ZIG | I2: USD | J2: ZIG | K2: USD | L2: ZIG
A3: =Paysheet!A4 -> AES-E046 | B3: =Paysheet!B4 -> Tarisai | C3: =Paysheet!C4 -> Zinyama | D3: =Paysheet!AG4 -> 1575.582 | E3: =Paysheet!AH4 -> 47465.756 | F3: =Paysheet!AJ4 -> 15.608991 | G3: =Paysheet!AK4 -> 333.34686 | H3: =Paysheet!AL4 -> 0 | I3: =D3+F3 -> 1591.191 | J3: =E3+G3+H3 -> 47799.103 | K3: =I3*0.01 -> 15.91191 | L3: =J3*0.01 -> 477.99103
A4: =Paysheet!A5 -> AES-E049 | B4: =Paysheet!B5 -> Marvellous | C4: =Paysheet!C5 -> Chakanetsa | D4: =Paysheet!AG5 -> 657.9 | E4: =Paysheet!AH5 -> 28777.852 | F4: =Paysheet!AJ5 -> 15.608991 | G4: =Paysheet!AK5 -> 333.34686 | H4: =Paysheet!AL5 -> 0 | I4: =D4+F4 -> 673.50899 | J4: =E4+G4+H4 -> 29111.199 | K4: =I4*0.01 -> 6.7350899 | L4: =J4*0.01 -> 291.11199
A5: =Paysheet!A6 -> AES-E022 | B5: =Paysheet!B6 -> Obvious | C5: =Paysheet!C6 -> Mpofu | D5: =Paysheet!AG6 -> 822.68 | E5: =Paysheet!AH6 -> 25168.14 | F5: =Paysheet!AJ6 -> 15.608991 | G5: =Paysheet!AK6 -> 333.34686 | H5: =Paysheet!AL6 -> 0 | I5: =D5+F5 -> 838.28899 | J5: =E5+G5+H5 -> 25501.487 | K5: =I5*0.01 -> 8.3828899 | L5: =J5*0.01 -> 255.01487
A6: =Paysheet!A7 -> AES-E035 | B6: =Paysheet!B7 -> Polite | C6: =Paysheet!C7 -> Mudarikwa | D6: =Paysheet!AG7 -> 478.98 | E6: =Paysheet!AH7 -> 15784.813 | F6: =Paysheet!AJ7 -> 15.608991 | G6: =Paysheet!AK7 -> 333.34686 | H6: =Paysheet!AL7 -> 0 | I6: =D6+F6 -> 494.58899 | J6: =E6+G6+H6 -> 16118.159 | K6: =I6*0.01 -> 4.9458899 | L6: =J6*0.01 -> 161.18159
A7: =Paysheet!A8 -> AES-E041 | B7: =Paysheet!B8 -> Chenai | C7: =Paysheet!C8 -> Runesu | D7: =Paysheet!AG8 -> 677.168 | E7: =Paysheet!AH8 -> 23910.267 | F7: =Paysheet!AJ8 -> 15.608991 | G7: =Paysheet!AK8 -> 333.34686 | H7: =Paysheet!AL8 -> 0 | I7: =D7+F7 -> 692.77699 | J7: =E7+G7+H7 -> 24243.614 | K7: =I7*0.01 -> 6.9277699 | L7: =J7*0.01 -> 242.43614
A8: =Paysheet!A9 -> AES-E033 | B8: =Paysheet!B9 -> Tafadzwa | C8: =Paysheet!C9 -> Mafukidze | D8: =Paysheet!AG9 -> 353.52 | E8: =Paysheet!AH9 -> 11769.336 | F8: =Paysheet!AJ9 -> 13.104 | G8: =Paysheet!AK9 -> 279.85007 | H8: =Paysheet!AL9 -> 1166.042 | I8: =D8+F8 -> 366.624 | J8: =E8+G8+H8 -> 13215.228 | K8: =I8*0.01 -> 3.66624 | L8: =J8*0.01 -> 132.15228
A9: =Paysheet!A10 -> AES-E034 | B9: =Paysheet!B10 -> Kudzai | C9: =Paysheet!C10 -> Gwatidzo | D9: =Paysheet!AG10 -> 473.2 | E9: =Paysheet!AH10 -> 14964.205 | F9: =Paysheet!AJ10 -> 13.104 | G9: =Paysheet!AK10 -> 279.85007 | H9: =Paysheet!AL10 -> 1166.042 | I9: =D9+F9 -> 486.304 | J9: =E9+G9+H9 -> 16410.097 | K9: =I9*0.01 -> 4.86304 | L9: =J9*0.01 -> 164.10097
A10: =Paysheet!A11 -> AES-E036 | B10: =Paysheet!B11 -> Dadirai | C10: =Paysheet!C11 -> Nyakudya | D10: =Paysheet!AG11 -> 176.58 | E10: =Paysheet!AH11 -> 6063.0979 | F10: =Paysheet!AJ11 -> 7.5816 | G10: =Paysheet!AK11 -> 161.91326 | H10: =Paysheet!AL11 -> 674.63857 | I10: =D10+F10 -> 184.1616 | J10: =E10+G10+H10 -> 6899.6497 | K10: =I10*0.01 -> 1.841616 | L10: =J10*0.01 -> 68.996497
A11: =Paysheet!A12 -> AES-E037 | B11: =Paysheet!B12 -> Tarisai | C11: =Paysheet!C12 -> Chidzambwa | D11: =Paysheet!AG12 -> 176.58 | E11: =Paysheet!AH12 -> 6063.0979 | F11: =Paysheet!AJ12 -> 7.5816 | G11: =Paysheet!AK12 -> 161.91326 | H11: =Paysheet!AL12 -> 674.63857 | I11: =D11+F11 -> 184.1616 | J11: =E11+G11+H11 -> 6899.6497 | K11: =I11*0.01 -> 1.841616 | L11: =J11*0.01 -> 68.996497
A12: =Paysheet!A13 -> AES-E015 | B12: =Paysheet!B13 -> Believe | C12: =Paysheet!C13 -> Mhererwa | D12: =Paysheet!AG13 -> 188.892 | E12: =Paysheet!AH13 -> 6391.768 | F12: =Paysheet!AJ13 -> 7.5816 | G12: =Paysheet!AK13 -> 161.91326 | H12: =Paysheet!AL13 -> 0 | I12: =D12+F12 -> 196.4736 | J12: =E12+G12+H12 -> 6553.6812 | K12: =I12*0.01 -> 1.964736 | L12: =J12*0.01 -> 65.536812
A13: =Paysheet!A14 -> AES-E016 | B13: =Paysheet!B14 -> Shingai | C13: =Paysheet!C14 -> Rusike | D13: =Paysheet!AG14 -> 189.216 | E13: =Paysheet!AH14 -> 6400.4172 | F13: =Paysheet!AJ14 -> 7.5816 | G13: =Paysheet!AK14 -> 161.91326 | H13: =Paysheet!AL14 -> 0 | I13: =D13+F13 -> 196.7976 | J13: =E13+G13+H13 -> 6562.3304 | K13: =I13*0.01 -> 1.967976 | L13: =J13*0.01 -> 65.623304
A14: =Paysheet!A15 -> AES-E018 | B14: =Paysheet!B15 -> Gamuchirai | C14: =Paysheet!C15 -> Chirenda | D14: =Paysheet!AG15 -> 189.216 | E14: =Paysheet!AH15 -> 6400.4172 | F14: =Paysheet!AJ15 -> 7.5816 | G14: =Paysheet!AK15 -> 161.91326 | H14: =Paysheet!AL15 -> 0 | I14: =D14+F14 -> 196.7976 | J14: =E14+G14+H14 -> 6562.3304 | K14: =I14*0.01 -> 1.967976 | L14: =J14*0.01 -> 65.623304
... A29: =Paysheet!A30 -> AES-E042 | B29: =Paysheet!B30 -> Vimbai | C29: =Paysheet!C30 -> Mpofu | D29: =Paysheet!AG30 -> 216.572 | E29: =Paysheet!AH30 -> 7247.2925 | F29: =Paysheet!AJ30 -> 8.2368 | G29: =Paysheet!AK30 -> 175.90576 | H29: =Paysheet!AL30 -> 0 | I29: =D29+F29 -> 224.8088 | J29: =E29+G29+H29 -> 7423.1983 | K29: =I29*0.01 -> 2.248088 | L29: =J29*0.01 -> 74.231983
A30: =paysheet!#ref! -> #NAME? | B30: =paysheet!#ref! -> #NAME? | C30: =paysheet!#ref! -> #NAME? | D30: =paysheet!#ref! -> #NAME? | E30: =paysheet!#ref! -> #NAME? | F30: =paysheet!#ref! -> #NAME? | G30: =paysheet!#ref! -> #NAME? | H30: =paysheet!#ref! -> #NAME? | I30: =D30+F30 -> #NAME? | J30: =E30+G30+H30 -> #NAME? | K30: =I30*0.01 -> #NAME? | L30: =J30*0.01 -> #NAME?
A31: =Paysheet!A31 -> AES-E012 | B31: =Paysheet!B31 -> Batsirai | C31: =Paysheet!C31 -> Gwenzi | D31: =Paysheet!AG31 -> 286.416 | E31: =Paysheet!AH31 -> 8995.1809 | F31: =Paysheet!AJ31 -> 7.5816 | G31: =Paysheet!AK31 -> 161.91326 | H31: =Paysheet!AL31 -> 0 | I31: =D31+F31 -> 293.9976 | J31: =E31+G31+H31 -> 9157.0942 | K31: =I31*0.01 -> 2.939976 | L31: =J31*0.01 -> 91.570942
A32: =Paysheet!A32 -> AES-E020 | B32: =Paysheet!B32 -> Tonderayi | C32: =Paysheet!C32 -> Nyamande | D32: =Paysheet!AG32 -> 189.216 | E32: =Paysheet!AH32 -> 6400.4172 | F32: =Paysheet!AJ32 -> 7.5816 | G32: =Paysheet!AK32 -> 161.91326 | H32: =Paysheet!AL32 -> 0 | I32: =D32+F32 -> 196.7976 | J32: =E32+G32+H32 -> 6562.3304 | K32: =I32*0.01 -> 1.967976 | L32: =J32*0.01 -> 65.623304
A33: =Paysheet!A33 -> AES-E021 | B33: =Paysheet!B33 -> Kudzai | C33: =Paysheet!C33 -> Ziyambi | D33: =Paysheet!AG33 -> 253.692 | E33: =Paysheet!AH33 -> 8121.6104 | F33: =Paysheet!AJ33 -> 7.5816 | G33: =Paysheet!AK33 -> 161.91326 | H33: =Paysheet!AL33 -> 0 | I33: =D33+F33 -> 261.2736 | J33: =E33+G33+H33 -> 8283.5237 | K33: =I33*0.01 -> 2.612736 | L33: =J33*0.01 -> 82.835237
A34: =Paysheet!A34 -> AES-E027 | B34: =Paysheet!B34 -> Munashe | C34: =Paysheet!C34 -> Makoni | D34: =Paysheet!AG34 -> 188.892 | E34: =Paysheet!AH34 -> 6391.768 | F34: =Paysheet!AJ34 -> 7.5816 | G34: =Paysheet!AK34 -> 161.91326 | H34: =Paysheet!AL34 -> 0 | I34: =D34+F34 -> 196.4736 | J34: =E34+G34+H34 -> 6553.6812 | K34: =I34*0.01 -> 1.964736 | L34: =J34*0.01 -> 65.536812
A35: =Paysheet!A35 -> AES-E029 | B35: =Paysheet!B35 -> Kudzai | C35: =Paysheet!C35 -> Mutsvairo | D35: =Paysheet!AG35 -> 188.568 | E35: =Paysheet!AH35 -> 6383.1188 | F35: =Paysheet!AJ35 -> 7.5816 | G35: =Paysheet!AK35 -> 161.91326 | H35: =Paysheet!AL35 -> 0 | I35: =D35+F35 -> 196.1496 | J35: =E35+G35+H35 -> 6545.032 | K35: =I35*0.01 -> 1.961496 | L35: =J35*0.01 -> 65.45032
A36: =Paysheet!A36 -> AES-E028 | B36: =Paysheet!B36 -> Tsitsi | C36: =Paysheet!C36 -> Chibanda | D36: =Paysheet!AG36 -> 176.58 | E36: =Paysheet!AH36 -> 6063.0979 | F36: =Paysheet!AJ36 -> 7.5816 | G36: =Paysheet!AK36 -> 161.91326 | H36: =Paysheet!AL36 -> 0 | I36: =D36+F36 -> 184.1616 | J36: =E36+G36+H36 -> 6225.0111 | K36: =I36*0.01 -> 1.841616 | L36: =J36*0.01 -> 62.250111
A37: =Paysheet!A37 -> AES-E030 | B37: =Paysheet!B37 -> Tichaona | C37: =Paysheet!C37 -> Bere | D37: =Paysheet!AG37 -> 254.016 | E37: =Paysheet!AH37 -> 8130.2597 | F37: =Paysheet!AJ37 -> 7.5816 | G37: =Paysheet!AK37 -> 161.91326 | H37: =Paysheet!AL37 -> 0 | I37: =D37+F37 -> 261.5976 | J37: =E37+G37+H37 -> 8292.1729 | K37: =I37*0.01 -> 2.615976 | L37: =J37*0.01 -> 82.921729
A38: =Paysheet!A38 -> AES-E031 | B38: =Paysheet!B38 -> Nyarai | C38: =Paysheet!C38 -> Chikomo | D38: =Paysheet!AG38 -> 189.216 | E38: =Paysheet!AH38 -> 6400.4172 | F38: =Paysheet!AJ38 -> 7.5816 | G38: =Paysheet!AK38 -> 161.91326 | H38: =Paysheet!AL38 -> 0 | I38: =D38+F38 -> 196.7976 | J38: =E38+G38+H38 -> 6562.3304 | K38: =I38*0.01 -> 1.967976 | L38: =J38*0.01 -> 65.623304
A39: =Paysheet!A39 -> AES-E023 | B39: =Paysheet!B39 -> Tawanda | C39: =Paysheet!C39 -> Svosve | D39: =Paysheet!AG39 -> 192.78 | E39: =Paysheet!AH39 -> 6495.5585 | F39: =Paysheet!AJ39 -> 7.5816 | G39: =Paysheet!AK39 -> 161.91326 | H39: =Paysheet!AL39 -> 0 | I39: =D39+F39 -> 200.3616 | J39: =E39+G39+H39 -> 6657.4718 | K39: =I39*0.01 -> 2.003616 | L39: =J39*0.01 -> 66.574718
A40: =Paysheet!A40 -> AES-E024 | B40: =Paysheet!B40 -> Gamuchirai | C40: =Paysheet!C40 -> Mukanya | D40: =Paysheet!AG40 -> 192.78 | E40: =Paysheet!AH40 -> 6495.5585 | F40: =Paysheet!AJ40 -> 7.5816 | G40: =Paysheet!AK40 -> 161.91326 | H40: =Paysheet!AL40 -> 0 | I40: =D40+F40 -> 200.3616 | J40: =E40+G40+H40 -> 6657.4718 | K40: =I40*0.01 -> 2.003616 | L40: =J40*0.01 -> 66.574718
A41: =Paysheet!A41 -> AES-E025 | B41: =Paysheet!B41 -> Rutendo | C41: =Paysheet!C41 -> Mhike | D41: =Paysheet!AG41 -> 185.976 | E41: =Paysheet!AH41 -> 6262.0298 | F41: =Paysheet!AJ41 -> 7.29 | G41: =Paysheet!AK41 -> 155.68582 | H41: =Paysheet!AL41 -> 0 | I41: =D41+F41 -> 193.266 | J41: =E41+G41+H41 -> 6417.7156 | K41: =I41*0.01 -> 1.93266 | L41: =J41*0.01 -> 64.177156
A42: =Paysheet!A42 -> AES-E026 | B42: =Paysheet!B42 -> Brighton | C42: =Paysheet!C42 -> Chinamasa2Z | D42: =Paysheet!AG42 -> 117.936 | E42: =Paysheet!AH42 -> 3926.7424 | F42: =Paysheet!AJ42 -> 4.374 | G42: =Paysheet!AK42 -> 93.411494 | H42: =Paysheet!AL42 -> 0 | I42: =D42+F42 -> 122.31 | J42: =E42+G42+H42 -> 4020.1539 | K42: =I42*0.01 -> 1.2231 | L42: =J42*0.01 -> 40.201539
A43: =Paysheet!A43 -> AES-E032 | B43: =Paysheet!B43 -> Mazvita | C43: =Paysheet!C43 -> Mhererwa | D43: =Paysheet!AG43 -> 192.78 | E43: =Paysheet!AH43 -> 6495.5585 | F43: =Paysheet!AJ43 -> 7.5816 | G43: =Paysheet!AK43 -> 161.91326 | H43: =Paysheet!AL43 -> 0 | I43: =D43+F43 -> 200.3616 | J43: =E43+G43+H43 -> 6657.4718 | K43: =I43*0.01 -> 2.003616 | L43: =J43*0.01 -> 66.574718
A44: =Paysheet!A44 -> 0 | B44: =Paysheet!B44 -> 0 | C44: =Paysheet!C44 -> 0
A45: =Paysheet!A45 -> 0 | B45: =Paysheet!B45 -> 0
C51: Totals | D51: =SUM(D3:D50) -> #NAME? | E51: =SUM(E3:E50) -> #NAME? | F51: =SUM(F3:F50) -> #NAME? | G51: =SUM(G3:G50) -> #NAME? | H51: =SUM(H3:H50) -> #NAME? | I51: =SUM(I3:I50) -> #NAME? | J51: =SUM(J3:J50) -> #NAME? | K51: =SUM(K3:K50) -> #NAME? | L51: =SUM(L3:L50) -> #NAME?
D59: =D58/300 -> 0

Sheet MIPF
D1: MIPF Contributions -Invoices
B3: Mine Code : AIR11 ( 341 ) AIRFLOW ENVIRONMENTAL SOLUTION
C4: ***Month of February 2025***
A7: R/S NO. | B7: Netsai | C7: National | D7: Date of | E7: Payno | F7: Monthly | H7: Employer | J7: Employee
C8: Identy No. | D8: Birth | F8: Salary | G8: Rate | H8: Amount | I8: Rate | J8: Amount
A9: 0500752 | B9: MUDANHO MAXWELL | C9: 04-151082V 04 | D9: 32115 | E9: AES-E037 | F9: =Paysheet!Q12 -> 8995.1809 | G9: 7.5 | H9: =+F9*G9/100 -> 674.63857 | I9: 7.5 | J9: =+F9*I9/100 -> 674.63857
A10: 0500952 | B10: MUDANHO ERECK | C10: 04-126066D 04 | D10: 30605 | E10: AES-E044 | F10: =Paysheet!Q20 -> 10165.494 | G10: 7.5 | H10: =+F10*G10/100 -> 762.41206 | I10: 7.5 | J10: =+F10*I10/100 -> 762.41206
A11: 0603068 | B11: ZVAKANAKA JOSEPH | C11: 70-273576W 70 | D11: 32917 | E11: AES-E036 | F11: =Paysheet!Q11 -> 8995.1809 | G11: 7.5 | H11: =+F11*G11/100 -> 674.63857 | I11: 7.5 | J11: =+F11*I11/100 -> 674.63857
A12: 0707415 | B12: DUBE ISHEUNESU | C12: 67-133706T 67 | D12: 32370 | E12: AES-E043 | F12: =Paysheet!Q19 -> 8995.1809 | G12: 7.5 | H12: =+F12*G12/100 -> 674.63857 | I12: 7.5 | J12: =+F12*I12/100 -> 674.63857
A13: 4156922 | B13: STOCKEN BRIAN | C13: 24-121384V 24 | D13: 29167 | E13: AES-E034 | F13: =Paysheet!Q10 -> 15547.226 | G13: 7.5 | H13: =+F13*G13/100 -> 1166.042 | I13: 7.5 | J13: =+F13*I13/100 -> 1166.042
A14: 4321415 | B14: MHASHU TAKAINDISA ISAU | C14: 22-158650N 67 | D14: 27729 | E14: AES-E048 | F14: =Paysheet!Q18 -> 15547.226 | G14: 7.5 | H14: =+F14*G14/100 -> 1166.042 | I14: 7.5 | J14: =+F14*I14/100 -> 1166.042
A15: 7310848 | B15: RUDZINGI ALBERT | C15: 12-046849A 12 | D15: 27119 | E15: AES-E033 | F15: =Paysheet!Q9 -> 15547.226 | G15: 7.5 | H15: =+F15*G15/100 -> 1166.042 | I15: 7.5 | J15: =+F15*I15/100 -> 1166.042
F18: =SUM(F9:F17) -> 83792.715 | H18: =SUM(H9:H17) -> 6284.4537 | J18: =SUM(J9:J17) -> 6284.4537
F20: Total Employer/Employee Conts | J20: =J18+H18 -> 12568.907
F21: Compef | J21: =0.022*F18 -> 1843.4397
F22: TOTAL AMOUNT PAYABLE TO MIPF | J22: =SUM(J20:J21) -> 14412.347
J24: =H18+J21 -> 8127.8934
B25: TERMINATED EMPLOYEES
A27: 0500762 | B27: MOYO TINAYE | C27: 67-129498V 67 | D27: 32711 | E27: AESV5
A28: 0500822 | B28: MUTEMA MAXWELL | C28: 12-107177Z 22 | D28: 30922 | E28: AESV42
A29: 0707705 | B29: CHARLES VICTOR MUNYARADZI | C29: 66-078465S 66 | D29: 32630 | E29: AESR64

Sheet NEC
B1: Netsai | C1: Nhemachena
A2: =Paysheet!A2 -> 0 | B2: =Paysheet!B2 -> 0 | C2: =Paysheet!C2 -> Exchange rate
A3: =Paysheet!A3 -> Works # | B3: =Paysheet!B3 -> Netsai | C3: =Paysheet!C3 -> Nhemachena | D3: Employee Cont | E3: Company Cont | F3: Total
A4: =Paysheet!A4 -> AES-E046 | B4: =Paysheet!B4 -> Tarisai | C4: =Paysheet!C4 -> Zinyama | D4: =Paysheet!AM4 -> 108.10875 | E4: =D4 -> 108.10875 | F4: =D4+E4 -> 216.2175
A5: =Paysheet!A5 -> AES-E049 | B5: =Paysheet!B5 -> Marvellous | C5: =Paysheet!C5 -> Chakanetsa | D5: =Paysheet!AM5 -> 64.132308 | E5: =D5 -> 64.132308 | F5: =D5+E5 -> 128.26462
A6: =Paysheet!A6 -> AES-E022 | B6: =Paysheet!B6 -> Obvious | C6: =Paysheet!C6 -> Mpofu | D6: =Paysheet!AM6 -> 64.132308 | E6: =D6 -> 64.132308 | F6: =D6+E6 -> 128.26462
A7: =Paysheet!A7 -> AES-E035 | B7: =Paysheet!B7 -> Polite | C7: =Paysheet!C7 -> Mudarikwa | D7: =Paysheet!AM7 -> 59.967873 | E7: =D7 -> 59.967873 | F7: =D7+E7 -> 119.93575
A8: =Paysheet!A8 -> AES-E041 | B8: =Paysheet!B8 -> Chenai | C8: =Paysheet!C8 -> Runesu | D8: =Paysheet!AM8 -> 79.290854 | E8: =D8 -> 79.290854 | F8: =D8+E8 -> 158.58171
A9: =Paysheet!A9 -> AES-E033 | B9: =Paysheet!B9 -> Tafadzwa | C9: =Paysheet!C9 -> Mafukidze | D9: =Paysheet!AM9 -> 46.641679 | E9: =D9 -> 46.641679 | F9: =D9+E9 -> 93.283357
A10: =Paysheet!A10 -> AES-E034 | B10: =Paysheet!B10 -> Kudzai | C10: =Paysheet!C10 -> Gwatidzo | D10: =Paysheet!AM10 -> 46.641679 | E10: =D10 -> 46.641679 | F10: =D10+E10 -> 93.283357
A11: =Paysheet!A11 -> AES-E036 | B11: =Paysheet!B11 -> Dadirai | C11: =Paysheet!C11 -> Nyakudya | D11: =Paysheet!AM11 -> 26.985543 | E11: =D11 -> 26.985543 | F11: =D11+E11 -> 53.971085
A12: =Paysheet!A12 -> AES-E037 | B12: =Paysheet!B12 -> Tarisai | C12: =Paysheet!C12 -> Chidzambwa | D12: =Paysheet!AM12 -> 26.985543 | E12: =D12 -> 26.985543 | F12: =D12+E12 -> 53.971085
A13: =Paysheet!A13 -> AES-E015 | B13: =Paysheet!B13 -> Believe | C13: =Paysheet!C13 -> Mhererwa | D13: =Paysheet!AM13 -> 26.985543 | E13: =D13 -> 26.985543 | F13: =D13+E13 -> 53.971085
A14: =Paysheet!A14 -> AES-E016 | B14: =Paysheet!B14 -> Shingai | C14: =Paysheet!C14 -> Rusike | D14: =Paysheet!AM14 -> 26.985543 | E14: =D14 -> 26.985543 | F14: =D14+E14 -> 53.971085
A15: =Paysheet!A15 -> AES-E018 | B15: =Paysheet!B15 -> Gamuchirai | C15: =Paysheet!C15 -> Chirenda | D15: =Paysheet!AM15 -> 26.985543 | E15: =D15 -> 26.985543 | F15: =D15+E15 -> 53.971085
... A30: =Paysheet!A30 -> AES-E042 | B30: =Paysheet!B30 -> Vimbai | C30: =Paysheet!C30 -> Mpofu | D30: =Paysheet!AM30 -> 29.317627 | E30: =D30 -> 29.317627 | F30: =D30+E30 -> 58.635253
A31: =paysheet!#ref! -> #NAME? | B31: =paysheet!#ref! -> #NAME? | C31: =paysheet!#ref! -> #NAME? | D31: =paysheet!#ref! -> #NAME? | E31: =D31 -> #NAME? | F31: =D31+E31 -> #NAME?
A32: =Paysheet!A31 -> AES-E012 | B32: =Paysheet!B31 -> Batsirai | C32: =Paysheet!C31 -> Gwenzi | D32: =Paysheet!AM31 -> 26.985543 | E32: =D32 -> 26.985543 | F32: =D32+E32 -> 53.971085
A33: =Paysheet!A32 -> AES-E020 | B33: =Paysheet!B32 -> Tonderayi | C33: =Paysheet!C32 -> Nyamande | D33: =Paysheet!AM32 -> 26.985543 | E33: =D33 -> 26.985543 | F33: =D33+E33 -> 53.971085
A34: =Paysheet!A33 -> AES-E021 | B34: =Paysheet!B33 -> Kudzai | C34: =Paysheet!C33 -> Ziyambi | D34: =Paysheet!AM33 -> 26.985543 | E34: =D34 -> 26.985543 | F34: =D34+E34 -> 53.971085
A35: =Paysheet!A34 -> AES-E027 | B35: =Paysheet!B34 -> Munashe | C35: =Paysheet!C34 -> Makoni | D35: =Paysheet!AM34 -> 26.985543 | E35: =D35 -> 26.985543 | F35: =D35+E35 -> 53.971085
A36: =Paysheet!A35 -> AES-E029 | B36: =Paysheet!B35 -> Kudzai | C36: =Paysheet!C35 -> Mutsvairo | D36: =Paysheet!AM35 -> 26.985543 | E36: =D36 -> 26.985543 | F36: =D36+E36 -> 53.971085
A37: =Paysheet!A36 -> AES-E028 | B37: =Paysheet!B36 -> Tsitsi | C37: =Paysheet!C36 -> Chibanda | D37: =Paysheet!AM36 -> 26.985543 | E37: =D37 -> 26.985543 | F37: =D37+E37 -> 53.971085
A38: =Paysheet!A37 -> AES-E030 | B38: =Paysheet!B37 -> Tichaona | C38: =Paysheet!C37 -> Bere | D38: =Paysheet!AM37 -> 26.985543 | E38: =D38 -> 26.985543 | F38: =D38+E38 -> 53.971085
A39: =Paysheet!A38 -> AES-E031 | B39: =Paysheet!B38 -> Nyarai | C39: =Paysheet!C38 -> Chikomo | D39: =Paysheet!AM38 -> 26.985543 | E39: =D39 -> 26.985543 | F39: =D39+E39 -> 53.971085
A40: =Paysheet!A39 -> AES-E023 | B40: =Paysheet!B39 -> Tawanda | C40: =Paysheet!C39 -> Svosve | D40: =Paysheet!AM39 -> 26.985543 | E40: =D40 -> 26.985543 | F40: =D40+E40 -> 53.971085
A41: =Paysheet!A40 -> AES-E024 | B41: =Paysheet!B40 -> Gamuchirai | C41: =Paysheet!C40 -> Mukanya | D41: =Paysheet!AM40 -> 26.985543 | E41: =D41 -> 26.985543 | F41: =D41+E41 -> 53.971085
A42: =Paysheet!A41 -> AES-E025 | B42: =Paysheet!B41 -> Rutendo | C42: =Paysheet!C41 -> Mhike | D42: =Paysheet!AM41 -> 25.947637 | E42: =D42 -> 25.947637 | F42: =D42+E42 -> 51.895274
A43: =Paysheet!A42 -> AES-E026 | B43: =Paysheet!B42 -> Brighton | C43: =Paysheet!C42 -> Chinamasa2Z | D43: =Paysheet!AM42 -> 15.568582 | E43: =D43 -> 15.568582 | F43: =D43+E43 -> 31.137165
A44: =Paysheet!A43 -> AES-E032 | B44: =Paysheet!B43 -> Mazvita | C44: =Paysheet!C43 -> Mhererwa | D44: =Paysheet!AM43 -> 26.985543 | E44: =D44 -> 26.985543 | F44: =D44+E44 -> 53.971085
A45: =Paysheet!A44 -> 0
A48: =Paysheet!A45 -> 0 | B48: =Paysheet!B45 -> 0 | C48: =Paysheet!C45 -> Totals | D48: =SUM(D4:D47) -> #NAME? | E48: =SUM(E4:E47) -> #NAME? | F48: =SUM(F4:F47) -> #NAME?

Sheet Sage Journal Entry
B1: USD | D1: ZWL
A2: Details | B2: Debit | C2: Credit | D2: Debit | E2: Credit
A3: Gross Salaries | B3: =Paysheet!AG45 -> 12497.544 | D3: =Paysheet!AH45 -> 413373.84
A4: NSSA | C4: =Paysheet!AJ45 -> 365.13055 | E4: =Paysheet!AK45 -> 7797.7573
A5: PAYE | C5: =Paysheet!AU45+Paysheet!AV45 -> 2588.5765 | E5: =Paysheet!AW45+Paysheet!AX45 -> 84766.349
A6: Maintenance | C6: =Paysheet!BD45 -> 120 | E6: =Paysheet!BC45 -> 541.90224
A7: Garnish | C7: =Paysheet!BG45 -> 120 | E7: 0
A8: Net | C8: =Paysheet!BL45 -> 9016.337 | E8: =Paysheet!BM45 -> 299927.82
A9: MIPF | E9: =Paysheet!AL45 -> 6284.4537
A10: Nyaradzo | E10: =Paysheet!BA45 -> 12658.081
A11: NEC | E11: =Paysheet!AM45 -> 1397.4693
A12: Totals | B12: =SUM(B3:B11) -> 12497.544 | C12: =SUM(C3:C11) -> 12210.044 | D12: =SUM(D3:D11) -> 413373.84 | E12: =SUM(E3:E11) -> 413373.84
C14: =B12-C12 -> 287.5
E15: =D12-E12 -> 0
